Workbook

Sheet 1) Kpler
A1: . | E1: Name | F1: Capacity (m3) | G1: Deadweight | H1: State | I1: Status | J1: MMSI | K1: IMO | L1: Next destination | M1: Next destination ETA | N1: Loaded | Q1: LAST DOWNLOADED | U1: According to Kpler: | Y1: From '2) VLGC' + "India, Iran, FS" | AA1: Not In Kpler List | AE1: VLEC Check > 93k cbm | AF1: Not in Kpler. In Sorter | AG1: In Kpler. Not in sorter
A2: From 2) Tracker | B2: =COUNTA('2) Tracker'!A3:A510) -> 341 | E2: Al Ain | F2: 86000 | G2: 55324 | H2: loaded | I2: Active | J2: 636021495 | K2: 9916812 | N2: TRUE | U2: Actively trading: | V2: =COUNTIF($I$2:$I$1000,"active") -> 473 | Y2: =IFERROR(__xludf.DUMMYFUNCTION("filter($E$4:$E$600,not(countif('2) Tracker'!$A$3:$A$609,$E$4:$E$600)))"),"Apollo Ocean") -> Apollo Ocean | Z2: 1 | AA2: =IFERROR(__xludf.DUMMYFUNCTION("FILTER(Y2:Y501, ISNA(MATCH(TRIM(LOWER(CLEAN(Y2:Y501))), $E$2:$E$501, 0)))"),"") | AC2: NEWSHIPS? | AE2: =IF(E174="","", IF(F2>93000,1,"")) | AF2: =IF(ISERROR(VLOOKUP(#REF!,$E$2:$F$600,2, FALSE)),1,"") -> 1 | AG2: =IF(ISERROR(VLOOKUP(E174,$Y$2:$Z$600,2,FALSE)),1,"") -> 1
A3: From 3) Sorter | B3: =COUNTA('3) Sorter'!F4:F507) -> 349 | E3: Al Maryah | F3: 83765 | G3: 54474 | H3: ballast | I3: Active | J3: 636023795 | K3: 9393682 | N3: FALSE | Q3: Date | R3: Time | S3: By: | U3: Soon-to-be delivered | V3: =COUNTIF($I$2:$I$1000,"under construction") -> 25 | Y3: =IFERROR(__xludf.DUMMYFUNCTION("""COMPUTED_VALUE"""),"Astra") -> Astra | AC3: =IFERROR(__xludf.DUMMYFUNCTION("FILTER(E2:E501, ISNA(MATCH(TRIM(LOWER(CLEAN(E2:E501))), $Y$2:$Y$501, 0)))"),"Al Ain") -> Al Ain | AE3: =IF(E3="","", IF(F3>93000,1,"")) | AF3: =IF(ISERROR(VLOOKUP(Y3,$E$2:$F$600,2, FALSE)),1,"") | AG3: =IF(ISERROR(VLOOKUP(E3,$Y$2:$Z$600,2,FALSE)),1,"") -> 1
A4: Missing: | B4: =B2-B3 -> -8 | E4: Al Salam | F4: 86000 | G4: 54000 | H4: loaded | I4: Active | J4: 636021498 | K4: 9923085 | N4: TRUE | Q4: 46125 | R4: 0.41666667 | S4: GP | U4: VLEC | V4: =SUM(AE2:AE500) -> #REF! | Y4: =IFERROR(__xludf.DUMMYFUNCTION("""COMPUTED_VALUE"""),"Astram") -> Astram | AC4: =IFERROR(__xludf.DUMMYFUNCTION("""COMPUTED_VALUE"""),"Al Maryah") -> Al Maryah | AE4: =IF(E4="","", IF(F4>93000,1,"")) | AF4: =IF(ISERROR(VLOOKUP(Y4,$E$2:$F$600,2, FALSE)),1,"") | AG4: =IF(ISERROR(VLOOKUP(E4,$Y$2:$Z$600,2,FALSE)),1,"") -> 1
A5: In 2) but not in 3) | B5: In 3) but not in 2) | E5: Al Wukir | F5: 80841 | G5: 53999 | H5: ballast | I5: Active | J5: 538005255 | K5: 9359466 | L5: Houston | M5: 46138.125 | N5: FALSE | U5: Not in Kpler. In Sorter | V5: =SUM(AF2:AF399) -> 275 | Y5: =IFERROR(__xludf.DUMMYFUNCTION("""COMPUTED_VALUE"""),"Aura") -> Aura | AC5: =IFERROR(__xludf.DUMMYFUNCTION("""COMPUTED_VALUE"""),"Al Salam") -> Al Salam | AE5: =IF(E5="","", IF(F5>93000,1,"")) | AF5: =IF(ISERROR(VLOOKUP(Y5,$E$2:$F$600,2, FALSE)),1,"") | AG5: =IF(ISERROR(VLOOKUP(E5,$Y$2:$Z$600,2,FALSE)),1,"") -> 1
A6: =IFERROR(__xludf.DUMMYFUNCTION("filter('2) Tracker'!$A3:$A$402,not(countif('3) Sorter'!$F$4:$F$344,'2) Tracker'!$A$3:$A$402)))"),"") | B6: =IFERROR(__xludf.DUMMYFUNCTION("filter('3) Sorter'!$F$4:$F$366,not(countif('2) Tracker'!$A$3:$A$503,'3) Sorter'!$F$4:$F$366)))"),"") | E6: Albert | F6: 84000 | G6: 54354 | H6: loaded | I6: Active | J6: 371353000 | K6: 9682447 | L6: Pajaritos | M6: 46132.625 | N6: TRUE | U6: In Kpler. Not in sorter | V6: =SUM(AG2:AG394) -> 303 | Y6: =IFERROR(__xludf.DUMMYFUNCTION("""COMPUTED_VALUE"""),"Aurora") -> Aurora | AC6: =IFERROR(__xludf.DUMMYFUNCTION("""COMPUTED_VALUE"""),"Al Wukir") -> Al Wukir | AE6: =IF(E6="","", IF(F6>93000,1,"")) | AF6: =IF(ISERROR(VLOOKUP(Y6,$E$2:$F$600,2, FALSE)),1,"") | AG6: =IF(ISERROR(VLOOKUP(E6,$Y$2:$Z$600,2,FALSE)),1,"") -> 1
E7: Albert Ii | F7: 84000 | G7: 54358 | H7: loaded | I7: Active | J7: 371669000 | K7: 9780732 | L7: Houston | M7: 46134.896 | N7: TRUE | Y7: =IFERROR(__xludf.DUMMYFUNCTION("""COMPUTED_VALUE"""),"Axon I") -> Axon I | AC7: =IFERROR(__xludf.DUMMYFUNCTION("""COMPUTED_VALUE"""),"Albert") -> Albert | AE7: =IF(E7="","", IF(F7>93000,1,"")) | AF7: =IF(ISERROR(VLOOKUP(Y7,$E$2:$F$600,2, FALSE)),1,"") | AG7: =IF(ISERROR(VLOOKUP(E7,$Y$2:$Z$600,2,FALSE)),1,"") -> 1
E8: Albert Iii | F8: 84000 | G8: 54365 | H8: ballast | I8: Active | J8: 371557000 | K8: 9794288 | L8: Energy Transfer Nederland | M8: 46132.542 | N8: FALSE | U8: Newbuilds | Y8: =IFERROR(__xludf.DUMMYFUNCTION("""COMPUTED_VALUE"""),"Banian") -> Banian | AC8: =IFERROR(__xludf.DUMMYFUNCTION("""COMPUTED_VALUE"""),"Albert Ii") -> Albert Ii | AE8: =IF(E8="","", IF(F8>93000,1,"")) | AF8: =IF(ISERROR(VLOOKUP(Y8,$E$2:$F$600,2, FALSE)),1,"") | AG8: =IF(ISERROR(VLOOKUP(E8,$Y$2:$Z$600,2,FALSE)),1,"") -> 1
E9: Apollo Ocean | F9: 78907 | G9: 49999 | H9: ballast | I9: Active | J9: 574005600 | K9: 9423322 | L9: Advario Oman | M9: 46134.458 | N9: FALSE | U9: 1) Manual check on all the under constructions with newbuild list | Y9: =IFERROR(__xludf.DUMMYFUNCTION("""COMPUTED_VALUE"""),"Bao Yu") -> Bao Yu | AC9: =IFERROR(__xludf.DUMMYFUNCTION("""COMPUTED_VALUE"""),"Albert Iii") -> Albert Iii | AE9: =IF(E9="","", IF(F9>93000,1,"")) | AF9: =IF(ISERROR(VLOOKUP(Y9,$E$2:$F$600,2, FALSE)),1,"") | AG9: =IF(ISERROR(VLOOKUP(E9,$Y$2:$Z$600,2,FALSE)),1,"")
E10: Aquamarine Progress | F10: 83278 | G10: 54866 | H10: ballast | I10: Active | J10: 565210000 | K10: 9415650 | L10: Houston | M10: 46159.208 | N10: FALSE | Y10: =IFERROR(__xludf.DUMMYFUNCTION("""COMPUTED_VALUE"""),"Bw Birch") -> Bw Birch | AC10: =IFERROR(__xludf.DUMMYFUNCTION("""COMPUTED_VALUE"""),"Aquamarine Progress") -> Aquamarine Progress | AE10: =IF(E10="","", IF(F10>93000,1,"")) | AF10: =IF(ISERROR(VLOOKUP(Y10,$E$2:$F$600,2, FALSE)),1,"") | AG10: =IF(ISERROR(VLOOKUP(E10,$Y$2:$Z$600,2,FALSE)),1,"") -> 1
E11: Aquamarine Progress Ii | F11: 87000 | G11: 56805 | H11: ballast | I11: Active | J11: 563220700 | K11: 9947495 | L11: Houston | M11: 46137.292 | N11: FALSE | Y11: =IFERROR(__xludf.DUMMYFUNCTION("""COMPUTED_VALUE"""),"Bw Chinook") -> Bw Chinook | AC11: =IFERROR(__xludf.DUMMYFUNCTION("""COMPUTED_VALUE"""),"Aquamarine Progress Ii") -> Aquamarine Progress Ii | AE11: =IF(E11="","", IF(F11>93000,1,"")) | AF11: =IF(ISERROR(VLOOKUP(Y11,$E$2:$F$600,2, FALSE)),1,"") | AG11: =IF(ISERROR(VLOOKUP(E11,$Y$2:$Z$600,2,FALSE)),1,"") -> 1
E12: Astir Thuban | F12: 80546 | G12: 54650 | H12: ballast | I12: Active | J12: 636018567 | K12: 9840867 | L12: Energy Transfer Nederland | M12: 46134.042 | N12: FALSE | Y12: =IFERROR(__xludf.DUMMYFUNCTION("""COMPUTED_VALUE"""),"Bw Oak") -> Bw Oak | AC12: =IFERROR(__xludf.DUMMYFUNCTION("""COMPUTED_VALUE"""),"Astir Thuban") -> Astir Thuban | AE12: =IF(E12="","", IF(F12>93000,1,"")) | AF12: =IF(ISERROR(VLOOKUP(Y12,$E$2:$F$600,2, FALSE)),1,"") | AG12: =IF(ISERROR(VLOOKUP(E12,$Y$2:$Z$600,2,FALSE)),1,"") -> 1
E13: Astomos Earth | F13: 83426 | G13: 55250 | H13: ballast | I13: Active | J13: 373740000 | K13: 9607069 | L13: Freeport Texas | M13: 46154.646 | N13: FALSE | U13: Daily | Y13: =IFERROR(__xludf.DUMMYFUNCTION("""COMPUTED_VALUE"""),"Bw Tyr") -> Bw Tyr | AC13: =IFERROR(__xludf.DUMMYFUNCTION("""COMPUTED_VALUE"""),"Astomos Earth") -> Astomos Earth | AE13: =IF(E13="","", IF(F13>93000,1,"")) | AF13: =IF(ISERROR(VLOOKUP(Y13,$E$2:$F$600,2, FALSE)),1,"") | AG13: =IF(ISERROR(VLOOKUP(E13,$Y$2:$Z$600,2,FALSE)),1,"") -> 1
E14: Astomos Venus | F14: 83000 | G14: 55209 | H14: loaded | I14: Active | J14: 374614000 | K14: 9738545 | N14: TRUE | U14: WA -> Position lists | Y14: =IFERROR(__xludf.DUMMYFUNCTION("""COMPUTED_VALUE"""),"Celeste") -> Celeste | AC14: =IFERROR(__xludf.DUMMYFUNCTION("""COMPUTED_VALUE"""),"Astomos Venus") -> Astomos Venus | AE14: =IF(E14="","", IF(F14>93000,1,"")) | AF14: =IF(ISERROR(VLOOKUP(Y14,$E$2:$F$600,2, FALSE)),1,"") | AG14: =IF(ISERROR(VLOOKUP(E14,$Y$2:$Z$600,2,FALSE)),1,"") -> 1
E15: Astra | F15: 82000 | G15: 54368 | H15: ballast | I15: Active | J15: 650000174 | K15: 9350422 | L15: Advario Oman | M15: 46133.75 | N15: FALSE | U15: 1) Sorter to align with position lists | Y15: =IFERROR(__xludf.DUMMYFUNCTION("""COMPUTED_VALUE"""),"Clipper Galiot") -> Clipper Galiot | AC15: =IFERROR(__xludf.DUMMYFUNCTION("""COMPUTED_VALUE"""),"Atlantic Victory") -> Atlantic Victory | AE15: =IF(E15="","", IF(F15>93000,1,"")) | AF15: =IF(ISERROR(VLOOKUP(Y15,$E$2:$F$600,2, FALSE)),1,"") | AG15: =IF(ISERROR(VLOOKUP(E15,$Y$2:$Z$600,2,FALSE)),1,"")
E16: Astram | F16: 81605 | G16: 54533 | H16: ballast | I16: Active | J16: 603914000 | K16: 9307748 | L16: Khor Fakkan Anchorage | M16: 46132.875 | N16: FALSE | U16: 2) VL and Product operations info to be reflected | Y16: =IFERROR(__xludf.DUMMYFUNCTION("""COMPUTED_VALUE"""),"Clipper Galleon") -> Clipper Galleon | AC16: =IFERROR(__xludf.DUMMYFUNCTION("""COMPUTED_VALUE"""),"Atlantic Voyager") -> Atlantic Voyager | AE16: =IF(E16="","", IF(F16>93000,1,"")) | AF16: =IF(ISERROR(VLOOKUP(Y16,$E$2:$F$600,2, FALSE)),1,"") | AG16: =IF(ISERROR(VLOOKUP(E16,$Y$2:$Z$600,2,FALSE)),1,"")
E17: Atlantic Victory | F17: 75000 | G17: 54048 | H17: loaded | I17: Active | J17: 352003378 | K17: 9379399 | N17: TRUE | U17: 3) Haldia / India line up to be updated | Y17: =IFERROR(__xludf.DUMMYFUNCTION("""COMPUTED_VALUE"""),"Clipper Gannet") -> Clipper Gannet | AC17: =IFERROR(__xludf.DUMMYFUNCTION("""COMPUTED_VALUE"""),"Aurora Guardian") -> Aurora Guardian | AE17: =IF(E17="","", IF(F17>93000,1,"")) | AF17: =IF(ISERROR(VLOOKUP(Y17,$E$2:$F$600,2, FALSE)),1,"") | AG17: =IF(ISERROR(VLOOKUP(E17,$Y$2:$Z$600,2,FALSE)),1,"") -> 1
E18: Atlantic Voyager | F18: 87000 | G18: 55885 | H18: ballast | I18: Active | J18: 311001673 | K18: 9996020 | L18: Ningbo Area | M18: 46145.625 | N18: FALSE | Y18: =IFERROR(__xludf.DUMMYFUNCTION("""COMPUTED_VALUE"""),"Clipper Genesis") -> Clipper Genesis | AC18: =IFERROR(__xludf.DUMMYFUNCTION("""COMPUTED_VALUE"""),"Axis River") -> Axis River | AE18: =IF(E18="","", IF(F18>93000,1,"")) | AF18: =IF(ISERROR(VLOOKUP(Y2,$E$2:$F$600,2, FALSE)),1,"") | AG18: =IF(ISERROR(VLOOKUP(E18,$Y$2:$Z$600,2,FALSE)),1,"") -> 1
E19: Aura | F19: 80138 | G19: 53395 | H19: floatingStorage | I19: Active | J19: 650000181 | K19: 9274563 | L19: Guangzhou | M19: 46133.125 | N19: TRUE | U19: Then use Kpler AIS to update | Y19: =IFERROR(__xludf.DUMMYFUNCTION("""COMPUTED_VALUE"""),"Clipper Geneva") -> Clipper Geneva | AC19: =IFERROR(__xludf.DUMMYFUNCTION("""COMPUTED_VALUE"""),"Ayame") -> Ayame | AE19: =IF(E19="","", IF(F19>93000,1,"")) | AF19: =IF(ISERROR(VLOOKUP(Y19,$E$2:$F$600,2, FALSE)),1,"") | AG19: =IF(ISERROR(VLOOKUP(E19,$Y$2:$Z$600,2,FALSE)),1,"")
E20: Aurora | F20: 78462 | G20: 49679 | H20: loaded | I20: Active | J20: 511101458 | K20: 9088536 | N20: TRUE | Y20: =IFERROR(__xludf.DUMMYFUNCTION("""COMPUTED_VALUE"""),"Clipper Grace") -> Clipper Grace | AC20: =IFERROR(__xludf.DUMMYFUNCTION("""COMPUTED_VALUE"""),"Badrinath") -> Badrinath | AE20: =IF(E20="","", IF(F20>93000,1,"")) | AF20: =IF(ISERROR(VLOOKUP(Y20,$E$2:$F$600,2, FALSE)),1,"") | AG20: =IF(ISERROR(VLOOKUP(E20,$Y$2:$Z$600,2,FALSE)),1,"")
E21: Aurora Guardian | F21: 86700 | G21: 55000 | H21: underConstruction | I21: Under Construction | J21: 563319300 | K21: 1015399 | N21: FALSE | Y21: =IFERROR(__xludf.DUMMYFUNCTION("""COMPUTED_VALUE"""),"Clipper Guardian") -> Clipper Guardian | AC21: =IFERROR(__xludf.DUMMYFUNCTION("""COMPUTED_VALUE"""),"Baynounah") -> Baynounah | AE21: =IF(E21="","", IF(F21>93000,1,"")) | AF21: =IF(ISERROR(VLOOKUP(Y21,$E$2:$F$600,2, FALSE)),1,"") | AG21: =IF(ISERROR(VLOOKUP(E21,$Y$2:$Z$600,2,FALSE)),1,"") -> 1
E22: Axis River | F22: 86700 | G22: 55000 | H22: ballast | I22: Active | J22: 352002455 | K22: 9949704 | L22: RIPET | M22: 46133.833 | N22: FALSE | Y22: =IFERROR(__xludf.DUMMYFUNCTION("""COMPUTED_VALUE"""),"Da Li") -> Da Li | AC22: =IFERROR(__xludf.DUMMYFUNCTION("""COMPUTED_VALUE"""),"Bella Niagara") -> Bella Niagara | AE22: =IF(E22="","", IF(F22>93000,1,"")) | AF22: =IF(ISERROR(VLOOKUP(Y22,$E$2:$F$600,2, FALSE)),1,"") | AG22: =IF(ISERROR(VLOOKUP(E22,$Y$2:$Z$600,2,FALSE)),1,"") -> 1
E23: Axon I | F23: 76905 | G23: 49874 | H23: ballast | I23: Active | J23: 603920000 | K23: 9005053 | L23: Sharjah | M23: 46132.583 | N23: FALSE | Y23: =IFERROR(__xludf.DUMMYFUNCTION("""COMPUTED_VALUE"""),"Danisa") -> Danisa | AC23: =IFERROR(__xludf.DUMMYFUNCTION("""COMPUTED_VALUE"""),"Bellavista Explorer") -> Bellavista Explorer | AE23: =IF(E23="","", IF(F23>93000,1,"")) | AF23: =IF(ISERROR(VLOOKUP(Y23,$E$2:$F$600,2, FALSE)),1,"") | AG23: =IF(ISERROR(VLOOKUP(E23,$Y$2:$Z$600,2,FALSE)),1,"")
E24: Ayame | F24: 81605 | G24: 55076 | H24: ballast | I24: Active | J24: 565238000 | K24: 9415662 | N24: FALSE | Y24: =IFERROR(__xludf.DUMMYFUNCTION("""COMPUTED_VALUE"""),"Danuta I") -> Danuta I | AC24: =IFERROR(__xludf.DUMMYFUNCTION("""COMPUTED_VALUE"""),"Berge Nantong") -> Berge Nantong | AE24: =IF(E24="","", IF(F24>93000,1,"")) | AF24: =IF(ISERROR(VLOOKUP(Y24,$E$2:$F$600,2, FALSE)),1,"") | AG24: =IF(ISERROR(VLOOKUP(E24,$Y$2:$Z$600,2,FALSE)),1,"") -> 1
E25: Badrinath | F25: 82230 | G25: 54901 | H25: loaded | I25: Active | J25: 538011595 | K25: 9608300 | L25: Mangalore | M25: 46169.5 | N25: TRUE | Y25: =IFERROR(__xludf.DUMMYFUNCTION("""COMPUTED_VALUE"""),"Double In") -> Double In | AC25: =IFERROR(__xludf.DUMMYFUNCTION("""COMPUTED_VALUE"""),"Berge Ningbo") -> Berge Ningbo | AE25: =IF(E25="","", IF(F25>93000,1,"")) | AF25: =IF(ISERROR(VLOOKUP(Y25,$E$2:$F$600,2, FALSE)),1,"") | AG25: =IF(ISERROR(VLOOKUP(E25,$Y$2:$Z$600,2,FALSE)),1,"") -> 1
E26: Banian | F26: 76928 | G26: 49999 | H26: loaded | I26: Active | J26: 603919000 | K26: 9046784 | N26: TRUE | Y26: =IFERROR(__xludf.DUMMYFUNCTION("""COMPUTED_VALUE"""),"Elly") -> Elly | AC26: =IFERROR(__xludf.DUMMYFUNCTION("""COMPUTED_VALUE"""),"Bonneville") -> Bonneville | AE26: =IF(E26="","", IF(F26>93000,1,"")) | AF26: =IF(ISERROR(VLOOKUP(Y26,$E$2:$F$600,2, FALSE)),1,"") | AG26: =IF(ISERROR(VLOOKUP(E26,$Y$2:$Z$600,2,FALSE)),1,"")
E27: Bao Yu | F27: 76194 | G27: 51466 | H27: ballast | I27: Active | J27: 610000074 | K27: 8519966 | N27: FALSE | Y27: =IFERROR(__xludf.DUMMYFUNCTION("""COMPUTED_VALUE"""),"Energia Soleil") -> Energia Soleil | AC27: =IFERROR(__xludf.DUMMYFUNCTION("""COMPUTED_VALUE"""),"Boreal Pioneer") -> Boreal Pioneer | AE27: =IF(E27="","", IF(F27>93000,1,"")) | AF27: =IF(ISERROR(VLOOKUP(Y27,$E$2:$F$600,2, FALSE)),1,"") | AG27: =IF(ISERROR(VLOOKUP(E27,$Y$2:$Z$600,2,FALSE)),1,"")
E28: Baynounah | F28: 86000 | G28: 54000 | H28: ballast | I28: Active | J28: 636021499 | K28: 9923097 | N28: FALSE | Y28: =IFERROR(__xludf.DUMMYFUNCTION("""COMPUTED_VALUE"""),"Exonave") -> Exonave | AC28: =IFERROR(__xludf.DUMMYFUNCTION("""COMPUTED_VALUE"""),"Boreal Voyager") -> Boreal Voyager | AE28: =IF(E28="","", IF(F28>93000,1,"")) | AF28: =IF(ISERROR(VLOOKUP(Y28,$E$2:$F$600,2, FALSE)),1,"") | AG28: =IF(ISERROR(VLOOKUP(E28,$Y$2:$Z$600,2,FALSE)),1,"") -> 1
E29: Bella Niagara | F29: 91000 | G29: 62500 | H29: ballast | I29: Active | J29: 636022369 | K29: 9933781 | L29: Energy Transfer Nederland | M29: 46143.667 | N29: FALSE | Y29: =IFERROR(__xludf.DUMMYFUNCTION("""COMPUTED_VALUE"""),"Fas Gas") -> Fas Gas | AC29: =IFERROR(__xludf.DUMMYFUNCTION("""COMPUTED_VALUE"""),"Botan") -> Botan | AE29: =IF(E29="","", IF(F29>93000,1,"")) | AF29: =IF(ISERROR(VLOOKUP(Y29,$E$2:$F$600,2, FALSE)),1,"") | AG29: =IF(ISERROR(VLOOKUP(E29,$Y$2:$Z$600,2,FALSE)),1,"") -> 1
E30: Bellavista Explorer | F30: 90000 | G30: 54000 | H30: loaded | I30: Active | J30: 538090722 | K30: 9895305 | L30: FREP Plant | M30: 46141.5 | N30: TRUE | Y30: =IFERROR(__xludf.DUMMYFUNCTION("""COMPUTED_VALUE"""),"Fogas") -> Fogas | AC30: =IFERROR(__xludf.DUMMYFUNCTION("""COMPUTED_VALUE"""),"Brizo") -> Brizo | AE30: =IF(E30="","", IF(F30>93000,1,"")) | AF30: =IF(ISERROR(VLOOKUP(Y30,$E$2:$F$600,2, FALSE)),1,"") | AG30: =IF(ISERROR(VLOOKUP(E30,$Y$2:$Z$600,2,FALSE)),1,"") -> 1
E31: Berge Nantong | F31: 80360 | G31: 58757 | H31: ballast | I31: Active | J31: 477241500 | K31: 9317987 | L31: Houston | M31: 46144.5 | N31: FALSE | Y31: =IFERROR(__xludf.DUMMYFUNCTION("""COMPUTED_VALUE"""),"Fotis") -> Fotis | AC31: =IFERROR(__xludf.DUMMYFUNCTION("""COMPUTED_VALUE"""),"Bw Aries") -> Bw Aries | AE31: =IF(E31="","", IF(F31>93000,1,"")) | AF31: =IF(ISERROR(VLOOKUP(Y31,$E$2:$F$600,2, FALSE)),1,"") | AG31: =IF(ISERROR(VLOOKUP(E31,$Y$2:$Z$600,2,FALSE)),1,"") -> 1
E32: Berge Ningbo | F32: 80607 | G32: 58899 | H32: ballast | I32: Active | J32: 477099600 | K32: 9308493 | L32: Port Elizabeth | M32: 46135.833 | N32: FALSE | Y32: =IFERROR(__xludf.DUMMYFUNCTION("""COMPUTED_VALUE"""),"Future Japan") -> Future Japan | AC32: =IFERROR(__xludf.DUMMYFUNCTION("""COMPUTED_VALUE"""),"Bw Avior") -> Bw Avior | AE32: =IF(E32="","", IF(F32>93000,1,"")) | AF32: =IF(ISERROR(VLOOKUP(Y32,$E$2:$F$600,2, FALSE)),1,"") | AG32: =IF(ISERROR(VLOOKUP(E32,$Y$2:$Z$600,2,FALSE)),1,"") -> 1
E33: Bonneville | F33: 88000 | G33: 56044 | H33: ballast | I33: Active | J33: 636022845 | K33: 9993626 | L33: Houston | M33: 46135.75 | N33: FALSE | Y33: =IFERROR(__xludf.DUMMYFUNCTION("""COMPUTED_VALUE"""),"Gafus") -> Gafus | AC33: =IFERROR(__xludf.DUMMYFUNCTION("""COMPUTED_VALUE"""),"Bw Balder") -> Bw Balder | AE33: =IF(E33="","", IF(F33>93000,1,"")) | AF33: =IF(ISERROR(VLOOKUP(Y33,$E$2:$F$600,2, FALSE)),1,"") | AG33: =IF(ISERROR(VLOOKUP(E33,$Y$2:$Z$600,2,FALSE)),1,"") -> 1
E34: Boreal Pioneer | F34: 91000 | G34: 59206 | H34: ballast | I34: Active | J34: 636023404 | K34: 9945198 | L34: RIPET | M34: 46135.125 | N34: FALSE | Y34: =IFERROR(__xludf.DUMMYFUNCTION("""COMPUTED_VALUE"""),"Galvin") -> Galvin | AC34: =IFERROR(__xludf.DUMMYFUNCTION("""COMPUTED_VALUE"""),"Bw Brage") -> Bw Brage | AE34: =IF(E34="","", IF(F34>93000,1,"")) | AF34: =IF(ISERROR(VLOOKUP(Y34,$E$2:$F$600,2, FALSE)),1,"") | AG34: =IF(ISERROR(VLOOKUP(E34,$Y$2:$Z$600,2,FALSE)),1,"") -> 1
E35: Boreal Voyager | F35: 91000 | G35: 58263 | H35: loaded | I35: Active | J35: 636023667 | K35: 9945203 | L35: Wenzhou | M35: 46132.708 | N35: TRUE | Y35: =IFERROR(__xludf.DUMMYFUNCTION("""COMPUTED_VALUE"""),"Gardian") -> Gardian | AC35: =IFERROR(__xludf.DUMMYFUNCTION("""COMPUTED_VALUE"""),"Bw Breeze") -> Bw Breeze | AE35: =IF(E35="","", IF(F35>93000,1,"")) | AF35: =IF(ISERROR(VLOOKUP(Y35,$E$2:$F$600,2, FALSE)),1,"") | AG35: =IF(ISERROR(VLOOKUP(E35,$Y$2:$Z$600,2,FALSE)),1,"") -> 1
E36: Botan | F36: 91000 | G36: 59312 | H36: ballast | I36: Active | J36: 538010117 | K36: 9940966 | L36: Singapore | M36: 46133.667 | N36: FALSE | Y36: =IFERROR(__xludf.DUMMYFUNCTION("""COMPUTED_VALUE"""),"Gas Concept") -> Gas Concept | AC36: =IFERROR(__xludf.DUMMYFUNCTION("""COMPUTED_VALUE"""),"Bw Capella") -> Bw Capella | AE36: =IF(E36="","", IF(F36>93000,1,"")) | AF36: =IF(ISERROR(VLOOKUP(Y36,$E$2:$F$600,2, FALSE)),1,"") | AG36: =IF(ISERROR(VLOOKUP(E36,$Y$2:$Z$600,2,FALSE)),1,"") -> 1
E37: Brizo | F37: 82557 | G37: 53677 | H37: ballast | I37: Active | J37: 352004952 | K37: 9238284 | N37: FALSE | Y37: =IFERROR(__xludf.DUMMYFUNCTION("""COMPUTED_VALUE"""),"Gas Endurance") -> Gas Endurance | AC37: =IFERROR(__xludf.DUMMYFUNCTION("""COMPUTED_VALUE"""),"Bw Carina") -> Bw Carina | AE37: =IF(E37="","", IF(F37>93000,1,"")) | AF37: =IF(ISERROR(VLOOKUP(Y37,$E$2:$F$600,2, FALSE)),1,"") | AG37: =IF(ISERROR(VLOOKUP(E37,$Y$2:$Z$600,2,FALSE)),1,"") -> 1
E38: Bw Aries | F38: 84196 | G38: 54561 | H38: loaded | I38: Active | J38: 235106302 | K38: 9701786 | N38: TRUE | Y38: =IFERROR(__xludf.DUMMYFUNCTION("""COMPUTED_VALUE"""),"Gas Lagoon") -> Gas Lagoon | AC38: =IFERROR(__xludf.DUMMYFUNCTION("""COMPUTED_VALUE"""),"Bw Elm") -> Bw Elm | AE38: =IF(E38="","", IF(F38>93000,1,"")) | AF38: =IF(ISERROR(VLOOKUP(Y38,$E$2:$F$600,2, FALSE)),1,"") | AG38: =IF(ISERROR(VLOOKUP(E38,$Y$2:$Z$600,2,FALSE)),1,"") -> 1
E39: Bw Avior | F39: 91000 | G39: 62500 | H39: loaded | I39: Active | J39: 538010183 | K39: 9930296 | L39: Kashima | M39: 46131.875 | N39: TRUE | Y39: =IFERROR(__xludf.DUMMYFUNCTION("""COMPUTED_VALUE"""),"Gas Marakua") -> Gas Marakua | AC39: =IFERROR(__xludf.DUMMYFUNCTION("""COMPUTED_VALUE"""),"Bw Freyja") -> Bw Freyja | AE39: =IF(E39="","", IF(F39>93000,1,"")) | AF39: =IF(ISERROR(VLOOKUP(Y39,$E$2:$F$600,2, FALSE)),1,"") | AG39: =IF(ISERROR(VLOOKUP(E39,$Y$2:$Z$600,2,FALSE)),1,"") -> 1
E40: Bw Balder | F40: 84000 | G40: 54053 | H40: ballast | I40: Active | J40: 538006835 | K40: 9732527 | L40: Panama Canal | M40: 46135.542 | N40: FALSE | Y40: =IFERROR(__xludf.DUMMYFUNCTION("""COMPUTED_VALUE"""),"Gas Strength") -> Gas Strength | AC40: =IFERROR(__xludf.DUMMYFUNCTION("""COMPUTED_VALUE"""),"Bw Frigg") -> Bw Frigg | AE40: =IF(E40="","", IF(F40>93000,1,"")) | AF40: =IF(ISERROR(VLOOKUP(Y40,$E$2:$F$600,2, FALSE)),1,"") | AG40: =IF(ISERROR(VLOOKUP(E40,$Y$2:$Z$600,2,FALSE)),1,"") -> 1
E41: Bw Birch | F41: 82291 | G41: 58124 | H41: ballast | I41: Active | J41: 419001563 | K41: 9320740 | L41: Ruwais Refinery | M41: 46132.272 | N41: FALSE | Y41: =IFERROR(__xludf.DUMMYFUNCTION("""COMPUTED_VALUE"""),"Gas Wanaka") -> Gas Wanaka | AC41: =IFERROR(__xludf.DUMMYFUNCTION("""COMPUTED_VALUE"""),"Bw Gemini") -> Bw Gemini | AE41: =IF(E41="","", IF(F41>93000,1,"")) | AF41: =IF(ISERROR(VLOOKUP(Y41,$E$2:$F$600,2, FALSE)),1,"") | AG41: =IF(ISERROR(VLOOKUP(E41,$Y$2:$Z$600,2,FALSE)),1,"")
E42: Bw Brage | F42: 84000 | G42: 54053 | H42: ballast | I42: Active | J42: 538006837 | K42: 9732539 | N42: FALSE | Y42: =IFERROR(__xludf.DUMMYFUNCTION("""COMPUTED_VALUE"""),"Gaz Gms") -> Gaz Gms | AC42: =IFERROR(__xludf.DUMMYFUNCTION("""COMPUTED_VALUE"""),"Bw Kizoku") -> Bw Kizoku | AE42: =IF(E42="","", IF(F42>93000,1,"")) | AF42: =IF(ISERROR(VLOOKUP(Y42,$E$2:$F$600,2, FALSE)),1,"") | AG42: =IF(ISERROR(VLOOKUP(E42,$Y$2:$Z$600,2,FALSE)),1,"") -> 1
E43: Bw Breeze | F43: 83000 | G43: 53781 | H43: loaded | I43: Active | J43: 538005615 | K43: 9674842 | L43: Kalbut | M43: 46139.875 | N43: TRUE | Y43: =IFERROR(__xludf.DUMMYFUNCTION("""COMPUTED_VALUE"""),"Global Vivian") -> Global Vivian | AC43: =IFERROR(__xludf.DUMMYFUNCTION("""COMPUTED_VALUE"""),"Bw Kyoto") -> Bw Kyoto | AE43: =IF(E43="","", IF(F43>93000,1,"")) | AF43: =IF(ISERROR(VLOOKUP(Y43,$E$2:$F$600,2, FALSE)),1,"") | AG43: =IF(ISERROR(VLOOKUP(E43,$Y$2:$Z$600,2,FALSE)),1,"") -> 1
E44: Bw Capella | F44: 91000 | G44: 62500 | H44: ballast | I44: Active | J44: 538009680 | K44: 9901996 | L44: Ferndale | M44: 46148.25 | N44: FALSE | Y44: =IFERROR(__xludf.DUMMYFUNCTION("""COMPUTED_VALUE"""),"Gong De Tian") -> Gong De Tian | AC44: =IFERROR(__xludf.DUMMYFUNCTION("""COMPUTED_VALUE"""),"Bw Leo") -> Bw Leo | AE44: =IF(E44="","", IF(F44>93000,1,"")) | AF44: =IF(ISERROR(VLOOKUP(Y44,$E$2:$F$600,2, FALSE)),1,"") | AG44: =IF(ISERROR(VLOOKUP(E44,$Y$2:$Z$600,2,FALSE)),1,"") -> 1
E45: Bw Carina | F45: 84195 | G45: 54561 | H45: ballast | I45: Active | J45: 235108619 | K45: 9701798 | L45: Panama Canal | M45: 46149.5 | N45: FALSE | Y45: =IFERROR(__xludf.DUMMYFUNCTION("""COMPUTED_VALUE"""),"Green Sachi") -> Green Sachi | AC45: =IFERROR(__xludf.DUMMYFUNCTION("""COMPUTED_VALUE"""),"Bw Levant") -> Bw Levant | AE45: =IF(E45="","", IF(F45>93000,1,"")) | AF45: =IF(ISERROR(VLOOKUP(Y45,$E$2:$F$600,2, FALSE)),1,"") | AG45: =IF(ISERROR(VLOOKUP(E45,$Y$2:$Z$600,2,FALSE)),1,"") -> 1
E46: Bw Chinook | F46: 83000 | G46: 53660 | H46: ballast | I46: Active | J46: 419002041 | K46: 9689536 | L46: Houston | M46: 46165.458 | N46: FALSE | Y46: =IFERROR(__xludf.DUMMYFUNCTION("""COMPUTED_VALUE"""),"Green Sanvi") -> Green Sanvi | AC46: =IFERROR(__xludf.DUMMYFUNCTION("""COMPUTED_VALUE"""),"Bw Libra") -> Bw Libra | AE46: =IF(E46="","", IF(F46>93000,1,"")) | AF46: =IF(ISERROR(VLOOKUP(Y46,$E$2:$F$600,2, FALSE)),1,"") | AG46: =IF(ISERROR(VLOOKUP(E46,$Y$2:$Z$600,2,FALSE)),1,"")
E47: Bw Elm | F47: 82291 | G47: 58136 | H47: ballast | I47: Active | J47: 419001620 | K47: 9320752 | N47: FALSE | Y47: =IFERROR(__xludf.DUMMYFUNCTION("""COMPUTED_VALUE"""),"Green Sarita") -> Green Sarita | AC47: =IFERROR(__xludf.DUMMYFUNCTION("""COMPUTED_VALUE"""),"Bw Loyalty") -> Bw Loyalty | AE47: =IF(E47="","", IF(F47>93000,1,"")) | AF47: =IF(ISERROR(VLOOKUP(Y47,$E$2:$F$600,2, FALSE)),1,"") | AG47: =IF(ISERROR(VLOOKUP(E47,$Y$2:$Z$600,2,FALSE)),1,"") -> 1
E48: Bw Freyja | F48: 84000 | G48: 54053 | H48: ballast | I48: Active | J48: 538006838 | K48: 9733325 | N48: FALSE | Y48: =IFERROR(__xludf.DUMMYFUNCTION("""COMPUTED_VALUE"""),"Green Shakti") -> Green Shakti | AC48: =IFERROR(__xludf.DUMMYFUNCTION("""COMPUTED_VALUE"""),"Bw Magellan") -> Bw Magellan | AE48: =IF(E48="","", IF(F48>93000,1,"")) | AF48: =IF(ISERROR(VLOOKUP(Y48,$E$2:$F$600,2, FALSE)),1,"") | AG48: =IF(ISERROR(VLOOKUP(E48,$Y$2:$Z$600,2,FALSE)),1,"") -> 1
E49: Bw Frigg | F49: 84000 | G49: 54053 | H49: loaded | I49: Active | J49: 538006839 | K49: 9733337 | L49: Mohammedia Refinery | M49: 46140.708 | N49: TRUE | Y49: =IFERROR(__xludf.DUMMYFUNCTION("""COMPUTED_VALUE"""),"Hanwha Ocean") -> Hanwha Ocean | AC49: =IFERROR(__xludf.DUMMYFUNCTION("""COMPUTED_VALUE"""),"Bw Malacca") -> Bw Malacca | AE49: =IF(E49="","", IF(F49>93000,1,"")) | AF49: =IF(ISERROR(VLOOKUP(Y49,$E$2:$F$600,2, FALSE)),1,"") | AG49: =IF(ISERROR(VLOOKUP(E49,$Y$2:$Z$600,2,FALSE)),1,"") -> 1
E50: Bw Gemini | F50: 84196 | G50: 54116 | H50: ballast | I50: Active | J50: 235108666 | K50: 9703007 | L50: Freeport Texas | M50: 46132.125 | N50: FALSE | Y50: =IFERROR(__xludf.DUMMYFUNCTION("""COMPUTED_VALUE"""),"Hanwha Ocean") -> Hanwha Ocean | AC50: =IFERROR(__xludf.DUMMYFUNCTION("""COMPUTED_VALUE"""),"Bw Messina") -> Bw Messina | AE50: =IF(E50="","", IF(F50>93000,1,"")) | AF50: =IF(ISERROR(VLOOKUP(Y50,$E$2:$F$600,2, FALSE)),1,"") | AG50: =IF(ISERROR(VLOOKUP(E50,$Y$2:$Z$600,2,FALSE)),1,"") -> 1
E51: Bw Kizoku | F51: 83325 | G51: 51100 | H51: loaded | I51: Active | J51: 563094300 | K51: 9810032 | L51: Panama Canal | M51: 46133.5 | N51: TRUE | Y51: =IFERROR(__xludf.DUMMYFUNCTION("""COMPUTED_VALUE"""),"Hh Glory") -> Hh Glory | AC51: =IFERROR(__xludf.DUMMYFUNCTION("""COMPUTED_VALUE"""),"Bw Mindoro") -> Bw Mindoro | AE51: =IF(E51="","", IF(F51>93000,1,"")) | AF51: =IF(ISERROR(VLOOKUP(Y51,$E$2:$F$600,2, FALSE)),1,"") | AG51: =IF(ISERROR(VLOOKUP(E51,$Y$2:$Z$600,2,FALSE)),1,"") -> 1
E52: Bw Kyoto | F52: 83298 | G52: 54920 | H52: ballast | I52: Active | J52: 564818000 | K52: 9405083 | L52: Panama Canal | M52: 46155.708 | N52: FALSE | Y52: =IFERROR(__xludf.DUMMYFUNCTION("""COMPUTED_VALUE"""),"Hisui") -> Hisui | AC52: =IFERROR(__xludf.DUMMYFUNCTION("""COMPUTED_VALUE"""),"Bw Mistral") -> Bw Mistral | AE52: =IF(E52="","", IF(F52>93000,1,"")) | AF52: =IF(ISERROR(VLOOKUP(Y52,$E$2:$F$600,2, FALSE)),1,"") | AG52: =IF(ISERROR(VLOOKUP(E52,$Y$2:$Z$600,2,FALSE)),1,"") -> 1
E53: Bw Leo | F53: 84195 | G53: 54116 | H53: loaded | I53: Active | J53: 235109137 | K53: 9703019 | L53: Panama Canal | M53: 46135.001 | N53: TRUE | Y53: =IFERROR(__xludf.DUMMYFUNCTION("""COMPUTED_VALUE"""),"Hyundai Ulsan 3503") -> Hyundai Ulsan 3503 | AC53: =IFERROR(__xludf.DUMMYFUNCTION("""COMPUTED_VALUE"""),"Bw Monsoon") -> Bw Monsoon | AE53: =IF(E53="","", IF(F53>93000,1,"")) | AF53: =IF(ISERROR(VLOOKUP(Y53,$E$2:$F$600,2, FALSE)),1,"") | AG53: =IF(ISERROR(VLOOKUP(E53,$Y$2:$Z$600,2,FALSE)),1,"") -> 1
E54: Bw Levant | F54: 83000 | G54: 53658 | H54: ballast | I54: Active | J54: 538012003 | K54: 9686388 | L54: Panama Canal | M54: 46144.208 | N54: FALSE | Y54: =IFERROR(__xludf.DUMMYFUNCTION("""COMPUTED_VALUE"""),"Hyundai Ulsan 3504") -> Hyundai Ulsan 3504 | AC54: =IFERROR(__xludf.DUMMYFUNCTION("""COMPUTED_VALUE"""),"Bw Njord") -> Bw Njord | AE54: =IF(E54="","", IF(F54>93000,1,"")) | AF54: =IF(ISERROR(VLOOKUP(Y54,$E$2:$F$600,2, FALSE)),1,"") | AG54: =IF(ISERROR(VLOOKUP(E54,$Y$2:$Z$600,2,FALSE)),1,"") -> 1
E55: Bw Libra | F55: 84000 | G55: 54561 | H55: loaded | I55: Active | J55: 235111639 | K55: 9719496 | L55: Lianyungang | M55: 46139.583 | N55: TRUE | Y55: =IFERROR(__xludf.DUMMYFUNCTION("""COMPUTED_VALUE"""),"Hyundai Ulsan 3531") -> Hyundai Ulsan 3531 | AC55: =IFERROR(__xludf.DUMMYFUNCTION("""COMPUTED_VALUE"""),"Bw Orion") -> Bw Orion | AE55: =IF(E55="","", IF(F55>93000,1,"")) | AF55: =IF(ISERROR(VLOOKUP(Y55,$E$2:$F$600,2, FALSE)),1,"") | AG55: =IF(ISERROR(VLOOKUP(E55,$Y$2:$Z$600,2,FALSE)),1,"") -> 1
E56: Bw Loyalty | F56: 84631 | G56: 55057 | H56: loaded | I56: Active | J56: 419001720 | K56: 9350290 | N56: TRUE | Y56: =IFERROR(__xludf.DUMMYFUNCTION("""COMPUTED_VALUE"""),"Hyundai Ulsan 3532") -> Hyundai Ulsan 3532 | AC56: =IFERROR(__xludf.DUMMYFUNCTION("""COMPUTED_VALUE"""),"Bw Pampero") -> Bw Pampero | AE56: =IF(E56="","", IF(F56>93000,1,"")) | AF56: =IF(ISERROR(VLOOKUP(Y56,$E$2:$F$600,2, FALSE)),1,"") | AG56: =IF(ISERROR(VLOOKUP(E56,$Y$2:$Z$600,2,FALSE)),1,"") -> 1
E57: Bw Magellan | F57: 84000 | G57: 54268 | H57: loaded | I57: Active | J57: 232003788 | K57: 9735036 | L57: Ennore Port | M57: 46136.854 | N57: TRUE | Y57: =IFERROR(__xludf.DUMMYFUNCTION("""COMPUTED_VALUE"""),"Hyundai Ulsan 3542") -> Hyundai Ulsan 3542 | AC57: =IFERROR(__xludf.DUMMYFUNCTION("""COMPUTED_VALUE"""),"Bw Passat") -> Bw Passat | AE57: =IF(E57="","", IF(F57>93000,1,"")) | AF57: =IF(ISERROR(VLOOKUP(Y57,$E$2:$F$600,2, FALSE)),1,"") | AG57: =IF(ISERROR(VLOOKUP(E57,$Y$2:$Z$600,2,FALSE)),1,"") -> 1
E58: Bw Malacca | F58: 84000 | G58: 54268 | H58: loaded | I58: Active | J58: 232004100 | K58: 9735048 | L58: Kalbut | M58: 46148.208 | N58: TRUE | Y58: =IFERROR(__xludf.DUMMYFUNCTION("""COMPUTED_VALUE"""),"Jag Viraat") -> Jag Viraat | AC58: =IFERROR(__xludf.DUMMYFUNCTION("""COMPUTED_VALUE"""),"Bw Pine") -> Bw Pine | AE58: =IF(E58="","", IF(F58>93000,1,"")) | AF58: =IF(ISERROR(VLOOKUP(Y58,$E$2:$F$600,2, FALSE)),1,"") | AG58: =IF(ISERROR(VLOOKUP(E58,$Y$2:$Z$600,2,FALSE)),1,"") -> 1
E59: Bw Messina | F59: 84000 | G59: 54647 | H59: ballast | I59: Active | J59: 357498000 | K59: 9735062 | L59: Energy Transfer Marcus Hook | M59: 46137.583 | N59: FALSE | Y59: =IFERROR(__xludf.DUMMYFUNCTION("""COMPUTED_VALUE"""),"Jiangnan H2754") -> Jiangnan H2754 | AC59: =IFERROR(__xludf.DUMMYFUNCTION("""COMPUTED_VALUE"""),"Bw Polaris") -> Bw Polaris | AE59: =IF(E59="","", IF(F59>93000,1,"")) | AF59: =IF(ISERROR(VLOOKUP(Y59,$E$2:$F$600,2, FALSE)),1,"") | AG59: =IF(ISERROR(VLOOKUP(E59,$Y$2:$Z$600,2,FALSE)),1,"") -> 1
E60: Bw Mindoro | F60: 84000 | G60: 54647 | H60: ballast | I60: Active | J60: 232005596 | K60: 9735050 | L60: Energy Transfer Nederland | M60: 46138.375 | N60: FALSE | Y60: =IFERROR(__xludf.DUMMYFUNCTION("""COMPUTED_VALUE"""),"Jiangnan H2755") -> Jiangnan H2755 | AC60: =IFERROR(__xludf.DUMMYFUNCTION("""COMPUTED_VALUE"""),"Bw Rigel") -> Bw Rigel | AE60: =IF(E60="","", IF(F60>93000,1,"")) | AF60: =IF(ISERROR(VLOOKUP(Y60,$E$2:$F$600,2, FALSE)),1,"") | AG60: =IF(ISERROR(VLOOKUP(E60,$Y$2:$Z$600,2,FALSE)),1,"") -> 1
E61: Bw Mistral | F61: 83000 | G61: 53854 | H61: loaded | I61: Active | J61: 538005576 | K61: 9667540 | L61: Ko Sichang | M61: 46152.792 | N61: TRUE | Y61: =IFERROR(__xludf.DUMMYFUNCTION("""COMPUTED_VALUE"""),"Jiangsu Yangzi Xinfu Yzj2024-1715") -> Jiangsu Yangzi Xinfu Yzj2024-1715 | AC61: =IFERROR(__xludf.DUMMYFUNCTION("""COMPUTED_VALUE"""),"Bw Sirocco") -> Bw Sirocco | AE61: =IF(E61="","", IF(F61>93000,1,"")) | AF61: =IF(ISERROR(VLOOKUP(Y61,$E$2:$F$600,2, FALSE)),1,"") | AG61: =IF(ISERROR(VLOOKUP(E61,$Y$2:$Z$600,2,FALSE)),1,"") -> 1
E62: Bw Monsoon | F62: 83000 | G62: 53751 | H62: loaded | I62: Active | J62: 538005614 | K62: 9667564 | L62: Zanzibar | M62: 46138.5 | N62: TRUE | Y62: =IFERROR(__xludf.DUMMYFUNCTION("""COMPUTED_VALUE"""),"Kalastin") -> Kalastin | AC62: =IFERROR(__xludf.DUMMYFUNCTION("""COMPUTED_VALUE"""),"Bw Tokyo") -> Bw Tokyo | AE62: =IF(E62="","", IF(F62>93000,1,"")) | AF62: =IF(ISERROR(VLOOKUP(Y62,$E$2:$F$600,2, FALSE)),1,"") | AG62: =IF(ISERROR(VLOOKUP(E62,$Y$2:$Z$600,2,FALSE)),1,"") -> 1
E63: Bw Njord | F63: 84000 | G63: 54053 | H63: ballast | I63: Active | J63: 538006840 | K63: 9741827 | L63: PADD 3 | M63: 46132 | N63: FALSE | Y63: =IFERROR(__xludf.DUMMYFUNCTION("""COMPUTED_VALUE"""),"Kawasaki Sakaide 1769") -> Kawasaki Sakaide 1769 | AC63: =IFERROR(__xludf.DUMMYFUNCTION("""COMPUTED_VALUE"""),"Bw Tucana") -> Bw Tucana | AE63: =IF(E63="","", IF(F63>93000,1,"")) | AF63: =IF(ISERROR(VLOOKUP(Y63,$E$2:$F$600,2, FALSE)),1,"") | AG63: =IF(ISERROR(VLOOKUP(E63,$Y$2:$Z$600,2,FALSE)),1,"") -> 1
E64: Bw Oak | F64: 82291 | G64: 58159 | H64: ballast | I64: Active | J64: 419001669 | K64: 9320764 | L64: Kandla | M64: 46131.75 | N64: FALSE | Y64: =IFERROR(__xludf.DUMMYFUNCTION("""COMPUTED_VALUE"""),"Kawasaki Sakaide 1770") -> Kawasaki Sakaide 1770 | AC64: =IFERROR(__xludf.DUMMYFUNCTION("""COMPUTED_VALUE"""),"Bw Var") -> Bw Var | AE64: =IF(E64="","", IF(F64>93000,1,"")) | AF64: =IF(ISERROR(VLOOKUP(Y64,$E$2:$F$600,2, FALSE)),1,"") | AG64: =IF(ISERROR(VLOOKUP(E64,$Y$2:$Z$600,2,FALSE)),1,"")
E65: Bw Orion | F65: 84195 | G65: 54116 | H65: loaded | I65: Active | J65: 235112806 | K65: 9719501 | L65: Kalbut | M65: 46143.5 | N65: TRUE | Y65: =IFERROR(__xludf.DUMMYFUNCTION("""COMPUTED_VALUE"""),"Lumina Polaris") -> Lumina Polaris | AC65: =IFERROR(__xludf.DUMMYFUNCTION("""COMPUTED_VALUE"""),"Bw Volans") -> Bw Volans | AE65: =IF(E65="","", IF(F65>93000,1,"")) | AF65: =IF(ISERROR(VLOOKUP(Y65,$E$2:$F$600,2, FALSE)),1,"") | AG65: =IF(ISERROR(VLOOKUP(E65,$Y$2:$Z$600,2,FALSE)),1,"") -> 1
E66: Bw Pampero | F66: 83000 | G66: 53503 | H66: ballast | I66: Active | J66: 419002054 | K66: 9689548 | L66: Freeport Texas | M66: 46131.875 | N66: FALSE | Y66: =IFERROR(__xludf.DUMMYFUNCTION("""COMPUTED_VALUE"""),"Manasarovar") -> Manasarovar | AC66: =IFERROR(__xludf.DUMMYFUNCTION("""COMPUTED_VALUE"""),"Bw Yushi") -> Bw Yushi | AE66: =IF(E66="","", IF(F66>93000,1,"")) | AF66: =IF(ISERROR(VLOOKUP(Y66,$E$2:$F$600,2, FALSE)),1,"") | AG66: =IF(ISERROR(VLOOKUP(E66,$Y$2:$Z$600,2,FALSE)),1,"") -> 1
E67: Bw Passat | F67: 83000 | G67: 53701 | H67: ballast | I67: Active | J67: 538005616 | K67: 9674854 | L67: Port Louis | M67: 46134.396 | N67: FALSE | Y67: =IFERROR(__xludf.DUMMYFUNCTION("""COMPUTED_VALUE"""),"Marser") -> Marser | AC67: =IFERROR(__xludf.DUMMYFUNCTION("""COMPUTED_VALUE"""),"Calluna Gas") -> Calluna Gas | AE67: =IF(E67="","", IF(F67>93000,1,"")) | AF67: =IF(ISERROR(VLOOKUP(Y67,$E$2:$F$600,2, FALSE)),1,"") | AG67: =IF(ISERROR(VLOOKUP(E67,$Y$2:$Z$600,2,FALSE)),1,"") -> 1
E68: Bw Pine | F68: 80156 | G68: 53028 | H68: loaded | I68: Active | J68: 419001637 | K68: 9479929 | N68: FALSE | Y68: =IFERROR(__xludf.DUMMYFUNCTION("""COMPUTED_VALUE"""),"Meda") -> Meda | AC68: =IFERROR(__xludf.DUMMYFUNCTION("""COMPUTED_VALUE"""),"Captain John Np") -> Captain John Np | AE68: =IF(E68="","", IF(F68>93000,1,"")) | AF68: =IF(ISERROR(VLOOKUP(Y68,$E$2:$F$600,2, FALSE)),1,"") | AG68: =IF(ISERROR(VLOOKUP(E68,$Y$2:$Z$600,2,FALSE)),1,"") -> 1
E69: Bw Polaris | F69: 91000 | G69: 62500 | H69: loaded | I69: Active | J69: 538009599 | K69: 9901984 | L69: Mangalore | M69: 46133.417 | N69: TRUE | Y69: =IFERROR(__xludf.DUMMYFUNCTION("""COMPUTED_VALUE"""),"Mighty Navigator") -> Mighty Navigator | AC69: =IFERROR(__xludf.DUMMYFUNCTION("""COMPUTED_VALUE"""),"Captain Markos") -> Captain Markos | AE69: =IF(E69="","", IF(F69>93000,1,"")) | AF69: =IF(ISERROR(VLOOKUP(Y69,$E$2:$F$600,2, FALSE)),1,"") | AG69: =IF(ISERROR(VLOOKUP(E69,$Y$2:$Z$600,2,FALSE)),1,"") -> 1
E70: Bw Rigel | F70: 91000 | G70: 62500 | H70: ballast | I70: Active | J70: 538010182 | K70: 9540091 | L70: Houston | M70: 46146.708 | N70: FALSE | Y70: =IFERROR(__xludf.DUMMYFUNCTION("""COMPUTED_VALUE"""),"Mile") -> Mile | AC70: =IFERROR(__xludf.DUMMYFUNCTION("""COMPUTED_VALUE"""),"Caravelle") -> Caravelle | AE70: =IF(E70="","", IF(F70>93000,1,"")) | AF70: =IF(ISERROR(VLOOKUP(Y70,$E$2:$F$600,2, FALSE)),1,"") | AG70: =IF(ISERROR(VLOOKUP(E70,$Y$2:$Z$600,2,FALSE)),1,"") -> 1
E71: Bw Sirocco | F71: 83000 | G71: 53558 | H71: loaded | I71: Active | J71: 538006045 | K71: 9686376 | L71: Yeosu | M71: 46153.583 | N71: TRUE | Y71: =IFERROR(__xludf.DUMMYFUNCTION("""COMPUTED_VALUE"""),"Ming Long") -> Ming Long | AC71: =IFERROR(__xludf.DUMMYFUNCTION("""COMPUTED_VALUE"""),"Challenger") -> Challenger | AE71: =IF(E71="","", IF(F71>93000,1,"")) | AF71: =IF(ISERROR(VLOOKUP(Y71,$E$2:$F$600,2, FALSE)),1,"") | AG71: =IF(ISERROR(VLOOKUP(E71,$Y$2:$Z$600,2,FALSE)),1,"") -> 1
E72: Bw Tokyo | F72: 83270 | G72: 54936 | H72: loaded | I72: Active | J72: 563343000 | K72: 9398307 | L72: Incheon LPG | M72: 46139.75 | N72: TRUE | Y72: =IFERROR(__xludf.DUMMYFUNCTION("""COMPUTED_VALUE"""),"Miura") -> Miura | AC72: =IFERROR(__xludf.DUMMYFUNCTION("""COMPUTED_VALUE"""),"Chang Xing Yuan") -> Chang Xing Yuan | AE72: =IF(E72="","", IF(F72>93000,1,"")) | AF72: =IF(ISERROR(VLOOKUP(Y72,$E$2:$F$600,2, FALSE)),1,"") | AG72: =IF(ISERROR(VLOOKUP(E72,$Y$2:$Z$600,2,FALSE)),1,"") -> 1
E73: Bw Tucana | F73: 84195 | G73: 54116 | H73: loaded | I73: Active | J73: 235115081 | K73: 9735658 | L73: Cristobal Light. | M73: 46134.25 | N73: TRUE | Y73: =IFERROR(__xludf.DUMMYFUNCTION("""COMPUTED_VALUE"""),"Myra Gas") -> Myra Gas | AC73: =IFERROR(__xludf.DUMMYFUNCTION("""COMPUTED_VALUE"""),"Chaparral") -> Chaparral | AE73: =IF(E73="","", IF(F73>93000,1,"")) | AF73: =IF(ISERROR(VLOOKUP(Y73,$E$2:$F$600,2, FALSE)),1,"") | AG73: =IF(ISERROR(VLOOKUP(E73,$Y$2:$Z$600,2,FALSE)),1,"") -> 1
E74: Bw Tyr | F74: 80657 | G74: 50700 | H74: loaded | I74: Active | J74: 419001673 | K74: 9346122 | N74: TRUE | Y74: =IFERROR(__xludf.DUMMYFUNCTION("""COMPUTED_VALUE"""),"Nanda Devi") -> Nanda Devi | AC74: =IFERROR(__xludf.DUMMYFUNCTION("""COMPUTED_VALUE"""),"Cheyenne") -> Cheyenne | AE74: =IF(E74="","", IF(F74>93000,1,"")) | AF74: =IF(ISERROR(VLOOKUP(Y74,$E$2:$F$600,2, FALSE)),1,"") | AG74: =IF(ISERROR(VLOOKUP(E74,$Y$2:$Z$600,2,FALSE)),1,"")
E75: Bw Var | F75: 84000 | G75: 54053 | H75: ballast | I75: Active | J75: 538006841 | K75: 9748227 | L75: Panama Canal | M75: 46137.375 | N75: FALSE | Y75: =IFERROR(__xludf.DUMMYFUNCTION("""COMPUTED_VALUE"""),"Navixon") -> Navixon | AC75: =IFERROR(__xludf.DUMMYFUNCTION("""COMPUTED_VALUE"""),"Clermont") -> Clermont | AE75: =IF(E75="","", IF(F75>93000,1,"")) | AF75: =IF(ISERROR(VLOOKUP(Y75,$E$2:$F$600,2, FALSE)),1,"") | AG75: =IF(ISERROR(VLOOKUP(E75,$Y$2:$Z$600,2,FALSE)),1,"") -> 1
E76: Bw Volans | F76: 84195 | G76: 54116 | H76: ballast | I76: Active | J76: 235115082 | K76: 9735660 | L76: Ferndale | M76: 46140.792 | N76: FALSE | Y76: =IFERROR(__xludf.DUMMYFUNCTION("""COMPUTED_VALUE"""),"Nv Aquamarine") -> Nv Aquamarine | AC76: =IFERROR(__xludf.DUMMYFUNCTION("""COMPUTED_VALUE"""),"Clipper Explorer") -> Clipper Explorer | AE76: =IF(E76="","", IF(F76>93000,1,"")) | AF76: =IF(ISERROR(VLOOKUP(Y76,$E$2:$F$600,2, FALSE)),1,"") | AG76: =IF(ISERROR(VLOOKUP(E76,$Y$2:$Z$600,2,FALSE)),1,"") -> 1
E77: Bw Yushi | F77: 83000 | G77: 51100 | H77: loaded | I77: Active | J77: 563101300 | K77: 9810044 | L77: Oiltank. Merak | M77: 46135.328 | N77: TRUE | Y77: =IFERROR(__xludf.DUMMYFUNCTION("""COMPUTED_VALUE"""),"Ocean Radiance") -> Ocean Radiance | AC77: =IFERROR(__xludf.DUMMYFUNCTION("""COMPUTED_VALUE"""),"Clipper Freeport") -> Clipper Freeport | AE77: =IF(E77="","", IF(F77>93000,1,"")) | AF77: =IF(ISERROR(VLOOKUP(Y77,$E$2:$F$600,2, FALSE)),1,"") | AG77: =IF(ISERROR(VLOOKUP(E77,$Y$2:$Z$600,2,FALSE)),1,"") -> 1
E78: Calluna Gas | F78: 84000 | G78: 55086 | H78: ballast | I78: Active | J78: 352001015 | K78: 9914058 | L78: Panama Canal | M78: 46136.958 | N78: FALSE | Y78: =IFERROR(__xludf.DUMMYFUNCTION("""COMPUTED_VALUE"""),"Orlando 1") -> Orlando 1 | AC78: =IFERROR(__xludf.DUMMYFUNCTION("""COMPUTED_VALUE"""),"Clipper Posh") -> Clipper Posh | AE78: =IF(E78="","", IF(F78>93000,1,"")) | AF78: =IF(ISERROR(VLOOKUP(Y78,$E$2:$F$600,2, FALSE)),1,"") | AG78: =IF(ISERROR(VLOOKUP(E78,$Y$2:$Z$600,2,FALSE)),1,"") -> 1
E79: Captain John Np | F79: 80595 | G79: 58691 | H79: ballast | I79: Active | J79: 255915947 | K79: 9347504 | L79: Houston | M79: 46141.708 | N79: FALSE | Y79: =IFERROR(__xludf.DUMMYFUNCTION("""COMPUTED_VALUE"""),"Pawan Putra") -> Pawan Putra | AC79: =IFERROR(__xludf.DUMMYFUNCTION("""COMPUTED_VALUE"""),"Clipper Quito") -> Clipper Quito | AE79: =IF(E79="","", IF(F79>93000,1,"")) | AF79: =IF(ISERROR(VLOOKUP(Y79,$E$2:$F$600,2, FALSE)),1,"") | AG79: =IF(ISERROR(VLOOKUP(E79,$Y$2:$Z$600,2,FALSE)),1,"") -> 1
E80: Captain Markos | F80: 84000 | G80: 54000 | H80: ballast | I80: Active | J80: 311001157 | K80: 9939917 | L80: Houston | M80: 46134.667 | N80: FALSE | Y80: =IFERROR(__xludf.DUMMYFUNCTION("""COMPUTED_VALUE"""),"Pinar Gas") -> Pinar Gas | AC80: =IFERROR(__xludf.DUMMYFUNCTION("""COMPUTED_VALUE"""),"Clipper Valiant") -> Clipper Valiant | AE80: =IF(E80="","", IF(F80>93000,1,"")) | AF80: =IF(ISERROR(VLOOKUP(Y80,$E$2:$F$600,2, FALSE)),1,"") | AG80: =IF(ISERROR(VLOOKUP(E80,$Y$2:$Z$600,2,FALSE)),1,"") -> 1
E81: Caravelle | F81: 84000 | G81: 54553 | H81: ballast | I81: Active | J81: 311000390 | K81: 9722807 | L81: PADD 3 | M81: 46168 | N81: FALSE | Y81: =IFERROR(__xludf.DUMMYFUNCTION("""COMPUTED_VALUE"""),"Pine Gas") -> Pine Gas | AC81: =IFERROR(__xludf.DUMMYFUNCTION("""COMPUTED_VALUE"""),"Clipper Vanguard") -> Clipper Vanguard | AE81: =IF(E81="","", IF(F81>93000,1,"")) | AF81: =IF(ISERROR(VLOOKUP(Y81,$E$2:$F$600,2, FALSE)),1,"") | AG81: =IF(ISERROR(VLOOKUP(E81,$Y$2:$Z$600,2,FALSE)),1,"") -> 1
E82: Celeste | F82: 75000 | G82: 54048 | H82: ballast | I82: Active | J82: 603922000 | K82: 9379404 | L82: Fujairah | M82: 46131.792 | N82: FALSE | Y82: =IFERROR(__xludf.DUMMYFUNCTION("""COMPUTED_VALUE"""),"Pyra") -> Pyra | AC82: =IFERROR(__xludf.DUMMYFUNCTION("""COMPUTED_VALUE"""),"Clipper Viking") -> Clipper Viking | AE82: =IF(E82="","", IF(F82>93000,1,"")) | AF82: =IF(ISERROR(VLOOKUP(Y82,$E$2:$F$600,2, FALSE)),1,"") | AG82: =IF(ISERROR(VLOOKUP(E82,$Y$2:$Z$600,2,FALSE)),1,"")
E83: Challenger | F83: 84000 | G83: 54553 | H83: loaded | I83: Active | J83: 311000393 | K83: 9722792 | L83: Valletta | M83: 46136.875 | N83: TRUE | Y83: =IFERROR(__xludf.DUMMYFUNCTION("""COMPUTED_VALUE"""),"Quantum Star") -> Quantum Star | AC83: =IFERROR(__xludf.DUMMYFUNCTION("""COMPUTED_VALUE"""),"Clipper Voyager") -> Clipper Voyager | AE83: =IF(E83="","", IF(F83>93000,1,"")) | AF83: =IF(ISERROR(VLOOKUP(Y83,$E$2:$F$600,2, FALSE)),1,"") | AG83: =IF(ISERROR(VLOOKUP(E83,$Y$2:$Z$600,2,FALSE)),1,"") -> 1
E84: Chang Xing Yuan | F84: 83000 | G84: 53688 | H84: loaded | I84: Active | J84: 414670000 | K84: 9710397 | L84: Guangzhou | M84: 46139.417 | N84: TRUE | Y84: =IFERROR(__xludf.DUMMYFUNCTION("""COMPUTED_VALUE"""),"Raine") -> Raine | AC84: =IFERROR(__xludf.DUMMYFUNCTION("""COMPUTED_VALUE"""),"Clipper Wilma") -> Clipper Wilma | AE84: =IF(E84="","", IF(F84>93000,1,"")) | AF84: =IF(ISERROR(VLOOKUP(Y84,$E$2:$F$600,2, FALSE)),1,"") | AG84: =IF(ISERROR(VLOOKUP(E84,$Y$2:$Z$600,2,FALSE)),1,"") -> 1
E85: Chaparral | F85: 84126 | G85: 54584 | H85: ballast | I85: Active | J85: 311000389 | K85: 9714393 | N85: FALSE | Y85: =IFERROR(__xludf.DUMMYFUNCTION("""COMPUTED_VALUE"""),"Reimei") -> Reimei | AC85: =IFERROR(__xludf.DUMMYFUNCTION("""COMPUTED_VALUE"""),"Cobra") -> Cobra | AE85: =IF(E85="","", IF(F85>93000,1,"")) | AF85: =IF(ISERROR(VLOOKUP(Y85,$E$2:$F$600,2, FALSE)),1,"") | AG85: =IF(ISERROR(VLOOKUP(E85,$Y$2:$Z$600,2,FALSE)),1,"") -> 1
E86: Cheyenne | F86: 84000 | G86: 54599 | H86: loaded | I86: Active | J86: 311000387 | K86: 9706504 | L86: Panama Canal | M86: 46132.542 | N86: TRUE | Y86: =IFERROR(__xludf.DUMMYFUNCTION("""COMPUTED_VALUE"""),"Rong Hao") -> Rong Hao | AC86: =IFERROR(__xludf.DUMMYFUNCTION("""COMPUTED_VALUE"""),"Comet") -> Comet | AE86: =IF(E86="","", IF(F86>93000,1,"")) | AF86: =IF(ISERROR(VLOOKUP(Y86,$E$2:$F$600,2, FALSE)),1,"") | AG86: =IF(ISERROR(VLOOKUP(E86,$Y$2:$Z$600,2,FALSE)),1,"") -> 1
E87: Clermont | F87: 84000 | G87: 54587 | H87: ballast | I87: Active | J87: 311000391 | K87: 9706487 | L87: Panama Canal | M87: 46139.625 | N87: FALSE | Y87: =IFERROR(__xludf.DUMMYFUNCTION("""COMPUTED_VALUE"""),"Sahyadri") -> Sahyadri | AC87: =IFERROR(__xludf.DUMMYFUNCTION("""COMPUTED_VALUE"""),"Commander") -> Commander | AE87: =IF(E87="","", IF(F87>93000,1,"")) | AF87: =IF(ISERROR(VLOOKUP(Y87,$E$2:$F$600,2, FALSE)),1,"") | AG87: =IF(ISERROR(VLOOKUP(E87,$Y$2:$Z$600,2,FALSE)),1,"") -> 1
E88: Clipper Explorer | F88: 80000 | G88: 50513 | H88: ballast | I88: Active | J88: 257968000 | K88: 9852949 | L88: PADD 3 | M88: 46152 | N88: FALSE | Y88: =IFERROR(__xludf.DUMMYFUNCTION("""COMPUTED_VALUE"""),"Salute") -> Salute | AC88: =IFERROR(__xludf.DUMMYFUNCTION("""COMPUTED_VALUE"""),"Commodore") -> Commodore | AE88: =IF(E88="","", IF(F88>93000,1,"")) | AF88: =IF(ISERROR(VLOOKUP(Y88,$E$2:$F$600,2, FALSE)),1,"") | AG88: =IF(ISERROR(VLOOKUP(E88,$Y$2:$Z$600,2,FALSE)),1,"") -> 1
E89: Clipper Freeport | F89: 78000 | G89: 50891 | H89: loaded | I89: Active | J89: 259104000 | K89: 9789154 | L89: Total Daesan Hanwha Refinery | M89: 46148.583 | N89: TRUE | Y89: =IFERROR(__xludf.DUMMYFUNCTION("""COMPUTED_VALUE"""),"Sarv Shakti") -> Sarv Shakti | AC89: =IFERROR(__xludf.DUMMYFUNCTION("""COMPUTED_VALUE"""),"Concorde") -> Concorde | AE89: =IF(E89="","", IF(F89>93000,1,"")) | AF89: =IF(ISERROR(VLOOKUP(Y89,$E$2:$F$600,2, FALSE)),1,"") | AG89: =IF(ISERROR(VLOOKUP(E89,$Y$2:$Z$600,2,FALSE)),1,"") -> 1
E90: Clipper Galiot | F90: 88000 | G90: 51497 | H90: underConstruction | I90: Under Construction | J90: 258233000 | K90: 1026817 | N90: FALSE | Y90: =IFERROR(__xludf.DUMMYFUNCTION("""COMPUTED_VALUE"""),"Sea Opera") -> Sea Opera | AC90: =IFERROR(__xludf.DUMMYFUNCTION("""COMPUTED_VALUE"""),"Constellation") -> Constellation | AE90: =IF(E90="","", IF(F90>93000,1,"")) | AF90: =IF(ISERROR(VLOOKUP(Y90,$E$2:$F$600,2, FALSE)),1,"") | AG90: =IF(ISERROR(VLOOKUP(E90,$Y$2:$Z$600,2,FALSE)),1,"")
E91: Clipper Galleon | F91: 88000 | G91: 51497 | H91: underConstruction | I91: Under Construction | J91: 257492850 | K91: 1026829 | N91: FALSE | Y91: =IFERROR(__xludf.DUMMYFUNCTION("""COMPUTED_VALUE"""),"Seabus") -> Seabus | AC91: =IFERROR(__xludf.DUMMYFUNCTION("""COMPUTED_VALUE"""),"Constitution") -> Constitution | AE91: =IF(E91="","", IF(F91>93000,1,"")) | AF91: =IF(ISERROR(VLOOKUP(Y91,$E$2:$F$600,2, FALSE)),1,"") | AG91: =IF(ISERROR(VLOOKUP(E91,$Y$2:$Z$600,2,FALSE)),1,"")
E92: Clipper Gannet | F92: 88000 | G92: 51497 | H92: underConstruction | I92: Under Construction | K92: 1032751 | N92: FALSE | Y92: =IFERROR(__xludf.DUMMYFUNCTION("""COMPUTED_VALUE"""),"Shivalik") -> Shivalik | AC92: =IFERROR(__xludf.DUMMYFUNCTION("""COMPUTED_VALUE"""),"Continental") -> Continental | AE92: =IF(E92="","", IF(F92>93000,1,"")) | AF92: =IF(ISERROR(VLOOKUP(Y92,$E$2:$F$600,2, FALSE)),1,"") | AG92: =IF(ISERROR(VLOOKUP(E92,$Y$2:$Z$600,2,FALSE)),1,"")
E93: Clipper Genesis | F93: 88000 | G93: 56844 | H93: underConstruction | I93: Under Construction | K93: 1048102 | N93: FALSE | Y93: =IFERROR(__xludf.DUMMYFUNCTION("""COMPUTED_VALUE"""),"Sia") -> Sia | AC93: =IFERROR(__xludf.DUMMYFUNCTION("""COMPUTED_VALUE"""),"Copernicus") -> Copernicus | AE93: =IF(E93="","", IF(F93>93000,1,"")) | AF93: =IF(ISERROR(VLOOKUP(Y93,$E$2:$F$600,2, FALSE)),1,"") | AG93: =IF(ISERROR(VLOOKUP(E93,$Y$2:$Z$600,2,FALSE)),1,"")
E94: Clipper Geneva | F94: 88000 | G94: 56844 | H94: underConstruction | I94: Under Construction | K94: 1048097 | N94: FALSE | Y94: =IFERROR(__xludf.DUMMYFUNCTION("""COMPUTED_VALUE"""),"Siona") -> Siona | AC94: =IFERROR(__xludf.DUMMYFUNCTION("""COMPUTED_VALUE"""),"Corfu Gas") -> Corfu Gas | AE94: =IF(E94="","", IF(F94>93000,1,"")) | AF94: =IF(ISERROR(VLOOKUP(Y94,$E$2:$F$600,2, FALSE)),1,"") | AG94: =IF(ISERROR(VLOOKUP(E94,$Y$2:$Z$600,2,FALSE)),1,"")
E95: Clipper Grace | F95: 88000 | G95: 51497 | H95: underConstruction | I95: Under Construction | K95: 1032763 | N95: FALSE | Y95: =IFERROR(__xludf.DUMMYFUNCTION("""COMPUTED_VALUE"""),"Sogl") -> Sogl | AC95: =IFERROR(__xludf.DUMMYFUNCTION("""COMPUTED_VALUE"""),"Corsair") -> Corsair | AE95: =IF(E95="","", IF(F95>93000,1,"")) | AF95: =IF(ISERROR(VLOOKUP(Y95,$E$2:$F$600,2, FALSE)),1,"") | AG95: =IF(ISERROR(VLOOKUP(E95,$Y$2:$Z$600,2,FALSE)),1,"")
E96: Clipper Guardian | F96: 88000 | G96: 51497 | H96: ballast | I96: Active | J96: 258220000 | K96: 1026805 | L96: Panama Canal | M96: 46139.042 | N96: FALSE | Y96: =IFERROR(__xludf.DUMMYFUNCTION("""COMPUTED_VALUE"""),"Tara Gas") -> Tara Gas | AC96: =IFERROR(__xludf.DUMMYFUNCTION("""COMPUTED_VALUE"""),"Corvette") -> Corvette | AE96: =IF(E96="","", IF(F96>93000,1,"")) | AF96: =IF(ISERROR(VLOOKUP(Y96,$E$2:$F$600,2, FALSE)),1,"") | AG96: =IF(ISERROR(VLOOKUP(E96,$Y$2:$Z$600,2,FALSE)),1,"")
E97: Clipper Posh | F97: 84000 | G97: 54999 | H97: loaded | I97: Active | J97: 257919000 | K97: 9656747 | N97: TRUE | Y97: =IFERROR(__xludf.DUMMYFUNCTION("""COMPUTED_VALUE"""),"The Gas Amelia") -> The Gas Amelia | AC97: =IFERROR(__xludf.DUMMYFUNCTION("""COMPUTED_VALUE"""),"Cougar") -> Cougar | AE97: =IF(E97="","", IF(F97>93000,1,"")) | AF97: =IF(ISERROR(VLOOKUP(Y97,$E$2:$F$600,2, FALSE)),1,"") | AG97: =IF(ISERROR(VLOOKUP(E97,$Y$2:$Z$600,2,FALSE)),1,"") -> 1
E98: Clipper Quito | F98: 84000 | G98: 55047 | H98: ballast | I98: Active | J98: 257928000 | K98: 9630755 | L98: Panama Canal | M98: 46134.75 | N98: FALSE | Y98: =IFERROR(__xludf.DUMMYFUNCTION("""COMPUTED_VALUE"""),"Tulip") -> Tulip | AC98: =IFERROR(__xludf.DUMMYFUNCTION("""COMPUTED_VALUE"""),"Cratis") -> Cratis | AE98: =IF(E98="","", IF(F98>93000,1,"")) | AF98: =IF(ISERROR(VLOOKUP(Y98,$E$2:$F$600,2, FALSE)),1,"") | AG98: =IF(ISERROR(VLOOKUP(E98,$Y$2:$Z$600,2,FALSE)),1,"") -> 1
E99: Clipper Valiant | F99: 84765 | G99: 50877 | H99: loaded | I99: Active | J99: 636018565 | K99: 9835173 | L99: Houston | M99: 46142.792 | N99: TRUE | Y99: =IFERROR(__xludf.DUMMYFUNCTION("""COMPUTED_VALUE"""),"Valano") -> Valano | AC99: =IFERROR(__xludf.DUMMYFUNCTION("""COMPUTED_VALUE"""),"Cresques") -> Cresques | AE99: =IF(E99="","", IF(F99>93000,1,"")) | AF99: =IF(ISERROR(VLOOKUP(Y99,$E$2:$F$600,2, FALSE)),1,"") | AG99: =IF(ISERROR(VLOOKUP(E99,$Y$2:$Z$600,2,FALSE)),1,"") -> 1
E100: Clipper Vanguard | F100: 78000 | G100: 50891 | H100: ballast | I100: Active | J100: 259138000 | K100: 9789166 | L100: Freeport Texas | M100: 46139.958 | N100: FALSE | Y100: =IFERROR(__xludf.DUMMYFUNCTION("""COMPUTED_VALUE"""),"Viet Dragon 68") -> Viet Dragon 68 | AC100: =IFERROR(__xludf.DUMMYFUNCTION("""COMPUTED_VALUE"""),"Cristobal") -> Cristobal | AE100: =IF(E100="","", IF(F100>93000,1,"")) | AF100: =IF(ISERROR(VLOOKUP(Y100,$E$2:$F$600,2, FALSE)),1,"") | AG100: =IF(ISERROR(VLOOKUP(E100,$Y$2:$Z$600,2,FALSE)),1,"") -> 1
...

Sheet 2) Tracker
K1: Laden | U1: What | V1: botan | Z1: With Waiting
A2: Vessel | B2: BLT | C2: CBM | D2: US | E2: Chinese | G2: Deck Tank | H2: Scrubber/Dual Fuel/Deck Tank | I2: Control | J2: AIS | K2: v Cape | L2: Position | M2: Open From | N2: Open To | P2: Notes: | Q2: Next loading: | R2: Voyage (no rate; + opts): | S2: Edited by: | T2: Updated | U2: Area | V2: AIS Location | W2: Date | X2: Status | Y2: ETA AG | Z2: ETA USG (P) | AA2: ETA USG (C) | AB2: ETA Bonny | AC2: Bethioua | AD2: ETA S'pore | AE2: ETA Darwin | AF2: ETA Yanbu | AG2: ETA AG | AH2: ETA AG 1 | AI2: ETA AG 2 | AJ2: ETA USG (P) | AK2: ETA USG1 | AL2: ETA USG2 | AM2: ETA USG (C) | AN2: ETA USG1 | AO2: ETA USG2 | AP2: ETA WAF | AQ2: ETA WAF1 | AR2: ETA WAF2 | AS2: ETA Bethouia | AT2: ETA Bethioua | AU2: ETA Bethioua | AV2: ETA WEST'PORT | AW2: ETA WEST'PORT 1 | AX2: ETA WEST'PORT 2 | AY2: ETA DARWIN | AZ2: ETA DARWIN1 | BA2: ETA DARWIN2 | BB2: ETA S'PORE | BC2: ETA SPORE1 | BD2: ETA SPORE2 | BE2: ETA P.Rupert | BF2: ETA P. Rupert 1 | BG2: ETA P. Rupert 2 | BH2: ETA Bonython | BI2: ETA Bonython | BJ2: ETA Yanbu | BK2: ETA Yanbu 1 | BL2: ETA Yanbu 2 | BM2: GOA Yanbu | BN2: ETA AG O | BO2: ETA USG O
A3: Astomos Venus | B3: 42460 | C3: 83000 | I3: AltaGas | J3: =IF(W3="","NO AIS",IF((W3-M3-1)>0,"Update","")) -> NO AIS | L3: Far East | M3: 46150 | N3: 46151 | P3: ex DD, ETA Ferndale 16 Apr | R3: Altagas 16-17 Apr Ferndale | S3: BR | T3: 46124 | U3: =IF(V3="","No AIS",VLOOKUP(V3,'Voyage days'!$A$3:$B$1480,2,FALSE)) -> No AIS | V3: =IF(VLOOKUP(A3,'1) Kpler'!$E$2:$P$1000,8, FALSE)="","",VLOOKUP(A3,'1) Kpler'!$E$2:$P$1000,8, FALSE)) | W3: =IF(VLOOKUP(A3,'1) Kpler'!$E$2:$P$1000,9,FALSE)="","",VLOOKUP(A3,'1) Kpler'!$E$2:$P$1000,9,FALSE)) | X3: =VLOOKUP(A3,'1) Kpler'!$E$2:$I$1000,4,FALSE) -> loaded | Y3: =AG3 -> 26-27 May | Z3: =AJ3 -> 08-09 Jun | AA3: =AM3 -> 15-16 Jun | AB3: =AP3 -> 07-08 Jun | AC3: =AS3 -> 13-14 Jun | AD3: =BB3 -> 16-17 May | AE3: =AY3 -> 16-17 May | AF3: =BJ3 -> 23-24 Jun | AG3: =IF(AH3="","",TEXT(AH3,"dd")&"-"&TEXT(AI3,"dd mmm")) -> 26-27 May | AH3: =IFERROR($M3+VLOOKUP($L3,'Voyage days'!$F$38:$H$89,3,FALSE),"") -> 46168 | AI3: =IFERROR(N3+VLOOKUP($L3,'Voyage days'!$F$38:$H$89,3,FALSE),"") -> 46169 | AJ3: =IF(AK3="","",TEXT(AK3,"dd")&"-"&TEXT(AL3,"dd mmm")) -> 08-09 Jun | AK3: =IFERROR($M3+VLOOKUP($L3,'Voyage days'!$F$94:$H$193,3,FALSE),"") -> 46181 | AL3: =IFERROR($N3+VLOOKUP($L3,'Voyage days'!$F$94:$H$193,3,FALSE),"") -> 46182 | AM3: =IF(AN3="","",TEXT(AN3,"dd")&"-"&TEXT(AO3,"dd mmm")) -> 15-16 Jun | AN3: =IFERROR($M3+VLOOKUP($L3,'Voyage days'!$F$203:$H$256,3,FALSE),"") -> 46188 | AO3: =IFERROR($N3+VLOOKUP($L3,'Voyage days'!$F$203:$H$256,3,FALSE),"") -> 46189 | AP3: =IF(AQ3="","",TEXT(AQ3,"dd")&"-"&TEXT(AR3,"dd mmm")) -> 07-08 Jun | AQ3: =IFERROR($M3+VLOOKUP($L3,'Voyage days'!$F$294:$H$377,3,FALSE),"") -> 46180 | AR3: =IFERROR($N3+VLOOKUP($L3,'Voyage days'!$F$294:$H$377,3,FALSE),"") -> 46181 | AS3: =IF(AT3="","",TEXT(AT3,"dd")&"-"&TEXT(AU3,"dd mmm")) -> 13-14 Jun | AT3: =IFERROR($M3+VLOOKUP($L3,'Voyage days'!$F$382:$H$446,3,FALSE),"") -> 46186 | AU3: =IFERROR($N3+VLOOKUP($L3,'Voyage days'!$F$382:$H$446,3,FALSE),"") -> 46187 | AV3: =IF(AW3="","",TEXT(AW3,"dd")&"-"&TEXT(AX3,"dd mmm")) -> 21-22 May | AW3: =IFERROR($M3+VLOOKUP($L3,'Voyage days'!$F$483:$H$538,3,FALSE),"") -> 46163 | AX3: =IFERROR($N3+VLOOKUP($L3,'Voyage days'!$F$483:$H$538,3,FALSE),"") -> 46164 | AY3: =IF(AZ3="","",TEXT(AZ3,"dd")&"-"&TEXT(BA3,"dd mmm")) -> 16-17 May | AZ3: =IFERROR($M3+VLOOKUP($L3,'Voyage days'!$F$540:$H$613,3,FALSE),"") -> 46158.25 | BA3: =IFERROR($N3+VLOOKUP($L3,'Voyage days'!$F$540:$H$613,3,FALSE),"") -> 46159.25 | BB3: =IF(BC3="","",TEXT(BC3,"dd")&"-"&TEXT(BD3,"dd mmm")) -> 16-17 May | BC3: =IFERROR($M3+VLOOKUP($L3,'Voyage days'!$F$448:$H$479,3,FALSE),"") -> 46158 | BD3: =IFERROR($N3+VLOOKUP($L3,'Voyage days'!$F$448:$H$479,3,FALSE),"") -> 46159 | BE3: =IF(BF3="","",TEXT(BF3,"dd")&"-"&TEXT(BG3,"dd mmm")) -> 19-20 May | BF3: =IFERROR($M3+VLOOKUP($L3,'Voyage days'!$F$620:$H$646,3,FALSE),"") -> 46161 | BG3: =IFERROR($N3+VLOOKUP($L3,'Voyage days'!$F$620:$H$646,3,FALSE),"") -> 46162 | BH3: =IF(BI3="","",TEXT(BI3,"dd")&"-"&TEXT(BL3,"dd mmm")) -> 16-24 Jun | BI3: =IFERROR($M3+VLOOKUP($L3,'Voyage days'!$F$702:$H$727,3,FALSE),"") -> 46158.25 | BJ3: =IF(BK3="","",TEXT(BK3,"dd")&"-"&TEXT(BL3,"dd mmm")) -> 23-24 Jun | BK3: =IFERROR($M3+VLOOKUP($L3,'Voyage days'!$F$807:$H$878,3,FALSE),"") -> 46196 | BL3: =IFERROR($N3+VLOOKUP($L3,'Voyage days'!$F$807:$H$878,3,FALSE),"") -> 46197 | BM3: =IFERROR($N3+VLOOKUP($L3,'Voyage days'!$F$807:$K$878,6,FALSE),"") -> 46171 | BN3: =if(L3="loads AG", IFERROR($M3+VLOOKUP($L3,'Voyage days'!$M$38:$O$38,3,FALSE),""),"") | BO3: =if(L3="loads USG", IFERROR($M3+VLOOKUP($L3,'Voyage days'!$L$203:$N$203,3,FALSE),""),"")
A4: Aurora Guardian | B4: 2026 | C4: 86665 | I4: AltaGas | J4: =IF(W4="","NO AIS",IF((W4-M4-1)>0,"Update","")) -> NO AIS | P4: New Build @ Japan | V4: =IF(VLOOKUP(A4,'1) Kpler'!$E$2:$P$1000,8, FALSE)="","",VLOOKUP(A4,'1) Kpler'!$E$2:$P$1000,8, FALSE)) | W4: =IF(VLOOKUP(A4,'1) Kpler'!$E$2:$P$1000,9,FALSE)="","",VLOOKUP(A4,'1) Kpler'!$E$2:$P$1000,9,FALSE)) | X4: =VLOOKUP(A4,'1) Kpler'!$E$2:$I$1000,4,FALSE) -> underConstruction | Y4: =AG4 | Z4: =AJ4 | AA4: =AM4 | AB4: =AP4 | AC4: =AS4 | AD4: =BB4 | AE4: =AY4 | AF4: =BJ4 | AG4: =IF(AH4="","",TEXT(AH4,"dd")&"-"&TEXT(AI4,"dd mmm")) | AH4: =IFERROR($M4+VLOOKUP($L4,'Voyage days'!$F$38:$H$89,3,FALSE),"") | AI4: =IFERROR(N4+VLOOKUP($L4,'Voyage days'!$F$38:$H$89,3,FALSE),"") | AJ4: =IF(AK4="","",TEXT(AK4,"dd")&"-"&TEXT(AL4,"dd mmm")) | AK4: =IFERROR($M4+VLOOKUP($L4,'Voyage days'!$F$94:$H$193,3,FALSE),"") | AL4: =IFERROR($N4+VLOOKUP($L4,'Voyage days'!$F$94:$H$193,3,FALSE),"") | AM4: =IF(AN4="","",TEXT(AN4,"dd")&"-"&TEXT(AO4,"dd mmm")) | AN4: =IFERROR($M4+VLOOKUP($L4,'Voyage days'!$F$203:$H$256,3,FALSE),"") | AO4: =IFERROR($N4+VLOOKUP($L4,'Voyage days'!$F$203:$H$256,3,FALSE),"") | AP4: =IF(AQ4="","",TEXT(AQ4,"dd")&"-"&TEXT(AR4,"dd mmm")) | AQ4: =IFERROR($M4+VLOOKUP($L4,'Voyage days'!$F$294:$H$377,3,FALSE),"") | AR4: =IFERROR($N4+VLOOKUP($L4,'Voyage days'!$F$294:$H$377,3,FALSE),"") | AS4: =IF(AT4="","",TEXT(AT4,"dd")&"-"&TEXT(AU4,"dd mmm")) | AT4: =IFERROR($M4+VLOOKUP($L4,'Voyage days'!$F$382:$H$446,3,FALSE),"") | AU4: =IFERROR($N4+VLOOKUP($L4,'Voyage days'!$F$382:$H$446,3,FALSE),"") | AV4: =IF(AW4="","",TEXT(AW4,"dd")&"-"&TEXT(AX4,"dd mmm")) | AW4: =IFERROR($M4+VLOOKUP($L4,'Voyage days'!$F$483:$H$538,3,FALSE),"") | AX4: =IFERROR($N4+VLOOKUP($L4,'Voyage days'!$F$483:$H$538,3,FALSE),"") | AY4: =IF(AZ4="","",TEXT(AZ4,"dd")&"-"&TEXT(BA4,"dd mmm")) | AZ4: =IFERROR($M4+VLOOKUP($L4,'Voyage days'!$F$540:$H$613,3,FALSE),"") | BA4: =IFERROR($N4+VLOOKUP($L4,'Voyage days'!$F$540:$H$613,3,FALSE),"") | BB4: =IF(BC4="","",TEXT(BC4,"dd")&"-"&TEXT(BD4,"dd mmm")) | BC4: =IFERROR($M4+VLOOKUP($L4,'Voyage days'!$F$448:$H$479,3,FALSE),"") | BD4: =IFERROR($N4+VLOOKUP($L4,'Voyage days'!$F$448:$H$479,3,FALSE),"") | BE4: =IF(BF4="","",TEXT(BF4,"dd")&"-"&TEXT(BG4,"dd mmm")) | BF4: =IFERROR($M4+VLOOKUP($L4,'Voyage days'!$F$620:$H$646,3,FALSE),"") | BG4: =IFERROR($N4+VLOOKUP($L4,'Voyage days'!$F$620:$H$646,3,FALSE),"") | BH4: =IF(BI4="","",TEXT(BI4,"dd")&"-"&TEXT(BL4,"dd mmm")) | BI4: =IFERROR($M4+VLOOKUP($L4,'Voyage days'!$F$702:$H$727,3,FALSE),"") | BJ4: =IF(BK4="","",TEXT(BK4,"dd")&"-"&TEXT(BL4,"dd mmm")) | BK4: =IFERROR($M4+VLOOKUP($L4,'Voyage days'!$F$807:$H$878,3,FALSE),"") | BL4: =IFERROR($N4+VLOOKUP($L4,'Voyage days'!$F$807:$H$878,3,FALSE),"") | BM4: =IFERROR($N4+VLOOKUP($L4,'Voyage days'!$F$807:$K$878,6,FALSE),"") | BN4: =if(L4="loads AG", IFERROR($M4+VLOOKUP($L4,'Voyage days'!$M$38:$O$38,3,FALSE),""),"") | BO4: =if(L4="loads USG", IFERROR($M4+VLOOKUP($L4,'Voyage days'!$L$203:$N$203,3,FALSE),""),"")
A5: Boreal Pioneer | B5: 2023 | C5: 91000 | I5: AltaGas | J5: =IF(W5="","NO AIS",IF((W5-M5-1)>0,"Update","")) | L5: Far East | M5: 46155 | N5: 46156 | P5: ETA Prince Rupert 23 Apr | R5: Altagas 23 Mar RIPET | S5: BR | T5: 46124 | U5: =IF(V5="","No AIS",VLOOKUP(V5,'Voyage days'!$A$3:$B$1480,2,FALSE)) -> +14 days to Far East | V5: =IF(VLOOKUP(A5,'1) Kpler'!$E$2:$P$1000,8, FALSE)="","",VLOOKUP(A5,'1) Kpler'!$E$2:$P$1000,8, FALSE)) -> RIPET | W5: =IF(VLOOKUP(A5,'1) Kpler'!$E$2:$P$1000,9,FALSE)="","",VLOOKUP(A5,'1) Kpler'!$E$2:$P$1000,9,FALSE)) -> 46135.125 | X5: =VLOOKUP(A5,'1) Kpler'!$E$2:$I$1000,4,FALSE) -> ballast | Y5: =AG5 -> 31-01 Jun | Z5: =AJ5 -> 13-14 Jun | AA5: =AM5 -> 20-21 Jun | AB5: =AP5 -> 12-13 Jun | AC5: =AS5 -> 18-19 Jun | AD5: =BB5 -> 21-22 May | AE5: =AY5 -> 21-22 May | AF5: =BJ5 -> 28-29 Jun | AG5: =IF(AH5="","",TEXT(AH5,"dd")&"-"&TEXT(AI5,"dd mmm")) -> 31-01 Jun | AH5: =IFERROR($M5+VLOOKUP($L5,'Voyage days'!$F$38:$H$89,3,FALSE),"") -> 46173 | AI5: =IFERROR(N5+VLOOKUP($L5,'Voyage days'!$F$38:$H$89,3,FALSE),"") -> 46174 | AJ5: =IF(AK5="","",TEXT(AK5,"dd")&"-"&TEXT(AL5,"dd mmm")) -> 13-14 Jun | AK5: =IFERROR($M5+VLOOKUP($L5,'Voyage days'!$F$94:$H$193,3,FALSE),"") -> 46186 | AL5: =IFERROR($N5+VLOOKUP($L5,'Voyage days'!$F$94:$H$193,3,FALSE),"") -> 46187 | AM5: =IF(AN5="","",TEXT(AN5,"dd")&"-"&TEXT(AO5,"dd mmm")) -> 20-21 Jun | AN5: =IFERROR($M5+VLOOKUP($L5,'Voyage days'!$F$203:$H$256,3,FALSE),"") -> 46193 | AO5: =IFERROR($N5+VLOOKUP($L5,'Voyage days'!$F$203:$H$256,3,FALSE),"") -> 46194 | AP5: =IF(AQ5="","",TEXT(AQ5,"dd")&"-"&TEXT(AR5,"dd mmm")) -> 12-13 Jun | AQ5: =IFERROR($M5+VLOOKUP($L5,'Voyage days'!$F$294:$H$377,3,FALSE),"") -> 46185 | AR5: =IFERROR($N5+VLOOKUP($L5,'Voyage days'!$F$294:$H$377,3,FALSE),"") -> 46186 | AS5: =IF(AT5="","",TEXT(AT5,"dd")&"-"&TEXT(AU5,"dd mmm")) -> 18-19 Jun | AT5: =IFERROR($M5+VLOOKUP($L5,'Voyage days'!$F$382:$H$446,3,FALSE),"") -> 46191 | AU5: =IFERROR($N5+VLOOKUP($L5,'Voyage days'!$F$382:$H$446,3,FALSE),"") -> 46192 | AV5: =IF(AW5="","",TEXT(AW5,"dd")&"-"&TEXT(AX5,"dd mmm")) -> 26-27 May | AW5: =IFERROR($M5+VLOOKUP($L5,'Voyage days'!$F$483:$H$538,3,FALSE),"") -> 46168 | AX5: =IFERROR($N5+VLOOKUP($L5,'Voyage days'!$F$483:$H$538,3,FALSE),"") -> 46169 | AY5: =IF(AZ5="","",TEXT(AZ5,"dd")&"-"&TEXT(BA5,"dd mmm")) -> 21-22 May | AZ5: =IFERROR($M5+VLOOKUP($L5,'Voyage days'!$F$540:$H$613,3,FALSE),"") -> 46163.25 | BA5: =IFERROR($N5+VLOOKUP($L5,'Voyage days'!$F$540:$H$613,3,FALSE),"") -> 46164.25 | BB5: =IF(BC5="","",TEXT(BC5,"dd")&"-"&TEXT(BD5,"dd mmm")) -> 21-22 May | BC5: =IFERROR($M5+VLOOKUP($L5,'Voyage days'!$F$448:$H$479,3,FALSE),"") -> 46163 | BD5: =IFERROR($N5+VLOOKUP($L5,'Voyage days'!$F$448:$H$479,3,FALSE),"") -> 46164 | BE5: =IF(BF5="","",TEXT(BF5,"dd")&"-"&TEXT(BG5,"dd mmm")) -> 24-25 May | BF5: =IFERROR($M5+VLOOKUP($L5,'Voyage days'!$F$620:$H$646,3,FALSE),"") -> 46166 | BG5: =IFERROR($N5+VLOOKUP($L5,'Voyage days'!$F$620:$H$646,3,FALSE),"") -> 46167 | BH5: =IF(BI5="","",TEXT(BI5,"dd")&"-"&TEXT(BL5,"dd mmm")) -> 21-29 Jun | BI5: =IFERROR($M5+VLOOKUP($L5,'Voyage days'!$F$702:$H$727,3,FALSE),"") -> 46163.25 | BJ5: =IF(BK5="","",TEXT(BK5,"dd")&"-"&TEXT(BL5,"dd mmm")) -> 28-29 Jun | BK5: =IFERROR($M5+VLOOKUP($L5,'Voyage days'!$F$807:$H$878,3,FALSE),"") -> 46201 | BL5: =IFERROR($N5+VLOOKUP($L5,'Voyage days'!$F$807:$H$878,3,FALSE),"") -> 46202 | BM5: =IFERROR($N5+VLOOKUP($L5,'Voyage days'!$F$807:$K$878,6,FALSE),"") -> 46176 | BN5: =if(L5="loads AG", IFERROR($M5+VLOOKUP($L5,'Voyage days'!$M$38:$O$38,3,FALSE),""),"") | BO5: =if(L5="loads USG", IFERROR($M5+VLOOKUP($L5,'Voyage days'!$L$203:$N$203,3,FALSE),""),"")
A6: Boreal Voyager | B6: 2024 | C6: 91000 | I6: AltaGas | J6: =IF(W6="","NO AIS",IF((W6-M6-1)>0,"Update","")) | L6: East China | M6: 46137 | N6: 46138 | P6: ETA Jiangyin 21 Apr | R6: Altagas 05 Apr RIPET | S6: BR | T6: 46124 | U6: =IF(V6="","No AIS",VLOOKUP(V6,'Voyage days'!$A$3:$B$1480,2,FALSE)) -> East China + 4 | V6: =IF(VLOOKUP(A6,'1) Kpler'!$E$2:$P$1000,8, FALSE)="","",VLOOKUP(A6,'1) Kpler'!$E$2:$P$1000,8, FALSE)) -> Wenzhou | W6: =IF(VLOOKUP(A6,'1) Kpler'!$E$2:$P$1000,9,FALSE)="","",VLOOKUP(A6,'1) Kpler'!$E$2:$P$1000,9,FALSE)) -> 46132.708 | X6: =VLOOKUP(A6,'1) Kpler'!$E$2:$I$1000,4,FALSE) -> loaded | Y6: =AG6 -> 12-13 May | Z6: =AJ6 -> 28-29 May | AA6: =AM6 -> 08-09 Jun | AB6: =AP6 -> 23-24 May | AC6: =AS6 -> 30-31 May | AD6: =BB6 -> 01-02 May | AE6: =AY6 -> 02-03 May | AF6: =BJ6 -> 08-09 Jun | AG6: =IF(AH6="","",TEXT(AH6,"dd")&"-"&TEXT(AI6,"dd mmm")) -> 12-13 May | AH6: =IFERROR($M6+VLOOKUP($L6,'Voyage days'!$F$38:$H$89,3,FALSE),"") -> 46154 | AI6: =IFERROR(N6+VLOOKUP($L6,'Voyage days'!$F$38:$H$89,3,FALSE),"") -> 46155 | AJ6: =IF(AK6="","",TEXT(AK6,"dd")&"-"&TEXT(AL6,"dd mmm")) -> 28-29 May | AK6: =IFERROR($M6+VLOOKUP($L6,'Voyage days'!$F$94:$H$193,3,FALSE),"") -> 46170 | AL6: =IFERROR($N6+VLOOKUP($L6,'Voyage days'!$F$94:$H$193,3,FALSE),"") -> 46171 | AM6: =IF(AN6="","",TEXT(AN6,"dd")&"-"&TEXT(AO6,"dd mmm")) -> 08-09 Jun | AN6: =IFERROR($M6+VLOOKUP($L6,'Voyage days'!$F$203:$H$256,3,FALSE),"") -> 46181 | AO6: =IFERROR($N6+VLOOKUP($L6,'Voyage days'!$F$203:$H$256,3,FALSE),"") -> 46182 | AP6: =IF(AQ6="","",TEXT(AQ6,"dd")&"-"&TEXT(AR6,"dd mmm")) -> 23-24 May | AQ6: =IFERROR($M6+VLOOKUP($L6,'Voyage days'!$F$294:$H$377,3,FALSE),"") -> 46165 | AR6: =IFERROR($N6+VLOOKUP($L6,'Voyage days'!$F$294:$H$377,3,FALSE),"") -> 46166 | AS6: =IF(AT6="","",TEXT(AT6,"dd")&"-"&TEXT(AU6,"dd mmm")) -> 30-31 May | AT6: =IFERROR($M6+VLOOKUP($L6,'Voyage days'!$F$382:$H$446,3,FALSE),"") -> 46172 | AU6: =IFERROR($N6+VLOOKUP($L6,'Voyage days'!$F$382:$H$446,3,FALSE),"") -> 46173 | AV6: =IF(AW6="","",TEXT(AW6,"dd")&"-"&TEXT(AX6,"dd mmm")) -> 09-10 May | AW6: =IFERROR($M6+VLOOKUP($L6,'Voyage days'!$F$483:$H$538,3,FALSE),"") -> 46151 | AX6: =IFERROR($N6+VLOOKUP($L6,'Voyage days'!$F$483:$H$538,3,FALSE),"") -> 46152 | AY6: =IF(AZ6="","",TEXT(AZ6,"dd")&"-"&TEXT(BA6,"dd mmm")) -> 02-03 May | AZ6: =IFERROR($M6+VLOOKUP($L6,'Voyage days'!$F$540:$H$613,3,FALSE),"") -> 46144.25 | BA6: =IFERROR($N6+VLOOKUP($L6,'Voyage days'!$F$540:$H$613,3,FALSE),"") -> 46145.25 | BB6: =IF(BC6="","",TEXT(BC6,"dd")&"-"&TEXT(BD6,"dd mmm")) -> 01-02 May | BC6: =IFERROR($M6+VLOOKUP($L6,'Voyage days'!$F$448:$H$479,3,FALSE),"") -> 46143 | BD6: =IFERROR($N6+VLOOKUP($L6,'Voyage days'!$F$448:$H$479,3,FALSE),"") -> 46144 | BE6: =IF(BF6="","",TEXT(BF6,"dd")&"-"&TEXT(BG6,"dd mmm")) -> 08-09 May | BF6: =IFERROR($M6+VLOOKUP($L6,'Voyage days'!$F$620:$H$646,3,FALSE),"") -> 46150 | BG6: =IFERROR($N6+VLOOKUP($L6,'Voyage days'!$F$620:$H$646,3,FALSE),"") -> 46151 | BH6: =IF(BI6="","",TEXT(BI6,"dd")&"-"&TEXT(BL6,"dd mmm")) -> 02-09 Jun | BI6: =IFERROR($M6+VLOOKUP($L6,'Voyage days'!$F$702:$H$727,3,FALSE),"") -> 46144.25 | BJ6: =IF(BK6="","",TEXT(BK6,"dd")&"-"&TEXT(BL6,"dd mmm")) -> 08-09 Jun | BK6: =IFERROR($M6+VLOOKUP($L6,'Voyage days'!$F$807:$H$878,3,FALSE),"") -> 46181 | BL6: =IFERROR($N6+VLOOKUP($L6,'Voyage days'!$F$807:$H$878,3,FALSE),"") -> 46182 | BM6: =IFERROR($N6+VLOOKUP($L6,'Voyage days'!$F$807:$K$878,6,FALSE),"") -> 46156 | BN6: =if(L6="loads AG", IFERROR($M6+VLOOKUP($L6,'Voyage days'!$M$38:$O$38,3,FALSE),""),"") | BO6: =if(L6="loads USG", IFERROR($M6+VLOOKUP($L6,'Voyage days'!$L$203:$N$203,3,FALSE),""),"")
A7: Gas Amethyst | B7: 2024 | C7: 86700 | H7: DF | I7: Astomos | J7: =IF(W7="","NO AIS",IF((W7-M7-1)>0,"Update","")) | L7: Japan | M7: 46152 | N7: 46153 | P7: ETA Nagoya 04 May | R7: Astomos 29-30 Mar Freeport | S7: BR | T7: 46124 | U7: =IF(V7="","No AIS",VLOOKUP(V7,'Voyage days'!$A$3:$B$1480,2,FALSE)) -> Japan + 6 | V7: =IF(VLOOKUP(A7,'1) Kpler'!$E$2:$P$1000,8, FALSE)="","",VLOOKUP(A7,'1) Kpler'!$E$2:$P$1000,8, FALSE)) -> Nagoya | W7: =IF(VLOOKUP(A7,'1) Kpler'!$E$2:$P$1000,9,FALSE)="","",VLOOKUP(A7,'1) Kpler'!$E$2:$P$1000,9,FALSE)) -> 46146.125 | X7: =VLOOKUP(A7,'1) Kpler'!$E$2:$I$1000,4,FALSE) -> loaded | Y7: =AG7 -> 28-29 May | Z7: =AJ7 -> 11-12 Jun | AA7: =AM7 -> 21-22 Jun | AB7: =AP7 -> 09-10 Jun | AC7: =AS7 -> 15-16 Jun | AD7: =BB7 -> 18-19 May | AE7: =AY7 -> 18-19 May | AF7: =BJ7 -> 25-26 Jun | AG7: =IF(AH7="","",TEXT(AH7,"dd")&"-"&TEXT(AI7,"dd mmm")) -> 28-29 May | AH7: =IFERROR($M7+VLOOKUP($L7,'Voyage days'!$F$38:$H$89,3,FALSE),"") -> 46170 | AI7: =IFERROR(N7+VLOOKUP($L7,'Voyage days'!$F$38:$H$89,3,FALSE),"") -> 46171 | AJ7: =IF(AK7="","",TEXT(AK7,"dd")&"-"&TEXT(AL7,"dd mmm")) -> 11-12 Jun | AK7: =IFERROR($M7+VLOOKUP($L7,'Voyage days'!$F$94:$H$193,3,FALSE),"") -> 46184 | AL7: =IFERROR($N7+VLOOKUP($L7,'Voyage days'!$F$94:$H$193,3,FALSE),"") -> 46185 | AM7: =IF(AN7="","",TEXT(AN7,"dd")&"-"&TEXT(AO7,"dd mmm")) -> 21-22 Jun | AN7: =IFERROR($M7+VLOOKUP($L7,'Voyage days'!$F$203:$H$256,3,FALSE),"") -> 46194 | AO7: =IFERROR($N7+VLOOKUP($L7,'Voyage days'!$F$203:$H$256,3,FALSE),"") -> 46195 | AP7: =IF(AQ7="","",TEXT(AQ7,"dd")&"-"&TEXT(AR7,"dd mmm")) -> 09-10 Jun | AQ7: =IFERROR($M7+VLOOKUP($L7,'Voyage days'!$F$294:$H$377,3,FALSE),"") -> 46182 | AR7: =IFERROR($N7+VLOOKUP($L7,'Voyage days'!$F$294:$H$377,3,FALSE),"") -> 46183 | AS7: =IF(AT7="","",TEXT(AT7,"dd")&"-"&TEXT(AU7,"dd mmm")) -> 15-16 Jun | AT7: =IFERROR($M7+VLOOKUP($L7,'Voyage days'!$F$382:$H$446,3,FALSE),"") -> 46188 | AU7: =IFERROR($N7+VLOOKUP($L7,'Voyage days'!$F$382:$H$446,3,FALSE),"") -> 46189 | AV7: =IF(AW7="","",TEXT(AW7,"dd")&"-"&TEXT(AX7,"dd mmm")) -> 23-24 May | AW7: =IFERROR($M7+VLOOKUP($L7,'Voyage days'!$F$483:$H$538,3,FALSE),"") -> 46165 | AX7: =IFERROR($N7+VLOOKUP($L7,'Voyage days'!$F$483:$H$538,3,FALSE),"") -> 46166 | AY7: =IF(AZ7="","",TEXT(AZ7,"dd")&"-"&TEXT(BA7,"dd mmm")) -> 18-19 May | AZ7: =IFERROR($M7+VLOOKUP($L7,'Voyage days'!$F$540:$H$613,3,FALSE),"") -> 46160.25 | BA7: =IFERROR($N7+VLOOKUP($L7,'Voyage days'!$F$540:$H$613,3,FALSE),"") -> 46161.25 | BB7: =IF(BC7="","",TEXT(BC7,"dd")&"-"&TEXT(BD7,"dd mmm")) -> 18-19 May | BC7: =IFERROR($M7+VLOOKUP($L7,'Voyage days'!$F$448:$H$479,3,FALSE),"") -> 46160 | BD7: =IFERROR($N7+VLOOKUP($L7,'Voyage days'!$F$448:$H$479,3,FALSE),"") -> 46161 | BE7: =IF(BF7="","",TEXT(BF7,"dd")&"-"&TEXT(BG7,"dd mmm")) -> 21-22 May | BF7: =IFERROR($M7+VLOOKUP($L7,'Voyage days'!$F$620:$H$646,3,FALSE),"") -> 46163 | BG7: =IFERROR($N7+VLOOKUP($L7,'Voyage days'!$F$620:$H$646,3,FALSE),"") -> 46164 | BH7: =IF(BI7="","",TEXT(BI7,"dd")&"-"&TEXT(BL7,"dd mmm")) -> 18-26 Jun | BI7: =IFERROR($M7+VLOOKUP($L7,'Voyage days'!$F$702:$H$727,3,FALSE),"") -> 46160.25 | BJ7: =IF(BK7="","",TEXT(BK7,"dd")&"-"&TEXT(BL7,"dd mmm")) -> 25-26 Jun | BK7: =IFERROR($M7+VLOOKUP($L7,'Voyage days'!$F$807:$H$878,3,FALSE),"") -> 46198 | BL7: =IFERROR($N7+VLOOKUP($L7,'Voyage days'!$F$807:$H$878,3,FALSE),"") -> 46199 | BM7: =IFERROR($N7+VLOOKUP($L7,'Voyage days'!$F$807:$K$878,6,FALSE),"") -> 46173 | BN7: =if(L7="loads AG", IFERROR($M7+VLOOKUP($L7,'Voyage days'!$M$38:$O$38,3,FALSE),""),"") | BO7: =if(L7="loads USG", IFERROR($M7+VLOOKUP($L7,'Voyage days'!$L$203:$N$203,3,FALSE),""),"")
A8: Gas Capricorn | B8: 37773 | C8: 78934 | I8: Astomos | J8: =IF(W8="","NO AIS",IF((W8-M8-1)>0,"Update","")) -> Update | L8: Cape ballast | M8: 46125 | N8: 46126 | P8: ETA USG 04 May via Cape | R8: Astomos 24-25 Jan Ras Laffan | S8: BR | T8: 46124 | U8: =IF(V8="","No AIS",VLOOKUP(V8,'Voyage days'!$A$3:$B$1480,2,FALSE)) -> USG | V8: =IF(VLOOKUP(A8,'1) Kpler'!$E$2:$P$1000,8, FALSE)="","",VLOOKUP(A8,'1) Kpler'!$E$2:$P$1000,8, FALSE)) -> Houston | W8: =IF(VLOOKUP(A8,'1) Kpler'!$E$2:$P$1000,9,FALSE)="","",VLOOKUP(A8,'1) Kpler'!$E$2:$P$1000,9,FALSE)) -> 46146.125 | X8: =VLOOKUP(A8,'1) Kpler'!$E$2:$I$1000,4,FALSE) -> ballast | Y8: =AG8 | Z8: =AJ8 | AA8: =AM8 -> 04-05 May | AB8: =AP8 -> 23-24 Apr | AC8: =AS8 -> 29-30 Apr | AD8: =BB8 -> 29-30 Apr | AE8: =AY8 | AF8: =BJ8 -> 06-07 May | AG8: =IF(AH8="","",TEXT(AH8,"dd")&"-"&TEXT(AI8,"dd mmm")) | AH8: =IFERROR($M8+VLOOKUP($L8,'Voyage days'!$F$38:$H$89,3,FALSE),"") | AI8: =IFERROR(N8+VLOOKUP($L8,'Voyage days'!$F$38:$H$89,3,FALSE),"") | AJ8: =IF(AK8="","",TEXT(AK8,"dd")&"-"&TEXT(AL8,"dd mmm")) | AK8: =IFERROR($M8+VLOOKUP($L8,'Voyage days'!$F$94:$H$193,3,FALSE),"") | AL8: =IFERROR($N8+VLOOKUP($L8,'Voyage days'!$F$94:$H$193,3,FALSE),"") | AM8: =IF(AN8="","",TEXT(AN8,"dd")&"-"&TEXT(AO8,"dd mmm")) -> 04-05 May | AN8: =IFERROR($M8+VLOOKUP($L8,'Voyage days'!$F$203:$H$256,3,FALSE),"") -> 46146 | AO8: =IFERROR($N8+VLOOKUP($L8,'Voyage days'!$F$203:$H$256,3,FALSE),"") -> 46147 | AP8: =IF(AQ8="","",TEXT(AQ8,"dd")&"-"&TEXT(AR8,"dd mmm")) -> 23-24 Apr | AQ8: =IFERROR($M8+VLOOKUP($L8,'Voyage days'!$F$294:$H$377,3,FALSE),"") -> 46135 | AR8: =IFERROR($N8+VLOOKUP($L8,'Voyage days'!$F$294:$H$377,3,FALSE),"") -> 46136 | AS8: =IF(AT8="","",TEXT(AT8,"dd")&"-"&TEXT(AU8,"dd mmm")) -> 29-30 Apr | AT8: =IFERROR($M8+VLOOKUP($L8,'Voyage days'!$F$382:$H$446,3,FALSE),"") -> 46141 | AU8: =IFERROR($N8+VLOOKUP($L8,'Voyage days'!$F$382:$H$446,3,FALSE),"") -> 46142 | AV8: =IF(AW8="","",TEXT(AW8,"dd")&"-"&TEXT(AX8,"dd mmm")) | AW8: =IFERROR($M8+VLOOKUP($L8,'Voyage days'!$F$483:$H$538,3,FALSE),"") | AX8: =IFERROR($N8+VLOOKUP($L8,'Voyage days'!$F$483:$H$538,3,FALSE),"") | AY8: =IF(AZ8="","",TEXT(AZ8,"dd")&"-"&TEXT(BA8,"dd mmm")) | AZ8: =IFERROR($M8+VLOOKUP($L8,'Voyage days'!$F$540:$H$613,3,FALSE),"") | BA8: =IFERROR($N8+VLOOKUP($L8,'Voyage days'!$F$540:$H$613,3,FALSE),"") | BB8: =IF(BC8="","",TEXT(BC8,"dd")&"-"&TEXT(BD8,"dd mmm")) -> 29-30 Apr | BC8: =IFERROR($M8+VLOOKUP($L8,'Voyage days'!$F$448:$H$479,3,FALSE),"") -> 46141 | BD8: =IFERROR($N8+VLOOKUP($L8,'Voyage days'!$F$448:$H$479,3,FALSE),"") -> 46142 | BE8: =IF(BF8="","",TEXT(BF8,"dd")&"-"&TEXT(BG8,"dd mmm")) | BF8: =IFERROR($M8+VLOOKUP($L8,'Voyage days'!$F$620:$H$646,3,FALSE),"") | BG8: =IFERROR($N8+VLOOKUP($L8,'Voyage days'!$F$620:$H$646,3,FALSE),"") | BH8: =IF(BI8="","",TEXT(BI8,"dd")&"-"&TEXT(BL8,"dd mmm")) | BI8: =IFERROR($M8+VLOOKUP($L8,'Voyage days'!$F$702:$H$727,3,FALSE),"") | BJ8: =IF(BK8="","",TEXT(BK8,"dd")&"-"&TEXT(BL8,"dd mmm")) -> 06-07 May | BK8: =IFERROR($M8+VLOOKUP($L8,'Voyage days'!$F$807:$H$878,3,FALSE),"") -> 46148 | BL8: =IFERROR($N8+VLOOKUP($L8,'Voyage days'!$F$807:$H$878,3,FALSE),"") -> 46149 | BM8: =IFERROR($N8+VLOOKUP($L8,'Voyage days'!$F$807:$K$878,6,FALSE),"") -> 46126 | BN8: =if(L8="loads AG", IFERROR($M8+VLOOKUP($L8,'Voyage days'!$M$38:$O$38,3,FALSE),""),"") | BO8: =if(L8="loads USG", IFERROR($M8+VLOOKUP($L8,'Voyage days'!$L$203:$N$203,3,FALSE),""),"")
A9: Kodaijisan | B9: 37895 | C9: 82000 | I9: Astomos | J9: =IF(W9="","NO AIS",IF((W9-M9-1)>0,"Update","")) -> NO AIS | L9: Honolulu | M9: 46124 | N9: 46125 | P9: ex DD, @ Honolulu 11 Apr | R9: Astomos 25-26 Dec Ras Laffan | S9: BR | T9: 46124 | U9: =IF(V9="","No AIS",VLOOKUP(V9,'Voyage days'!$A$3:$B$1480,2,FALSE)) -> No AIS | V9: =IF(VLOOKUP(A9,'1) Kpler'!$E$2:$P$1000,8, FALSE)="","",VLOOKUP(A9,'1) Kpler'!$E$2:$P$1000,8, FALSE)) | W9: =IF(VLOOKUP(A9,'1) Kpler'!$E$2:$P$1000,9,FALSE)="","",VLOOKUP(A9,'1) Kpler'!$E$2:$P$1000,9,FALSE)) | X9: =VLOOKUP(A9,'1) Kpler'!$E$2:$I$1000,4,FALSE) -> ballast | Y9: =AG9 | Z9: =AJ9 -> 29-30 Apr | AA9: =AM9 | AB9: =AP9 | AC9: =AS9 | AD9: =BB9 | AE9: =AY9 | AF9: =BJ9 | AG9: =IF(AH9="","",TEXT(AH9,"dd")&"-"&TEXT(AI9,"dd mmm")) | AH9: =IFERROR($M9+VLOOKUP($L9,'Voyage days'!$F$38:$H$89,3,FALSE),"") | AI9: =IFERROR(N9+VLOOKUP($L9,'Voyage days'!$F$38:$H$89,3,FALSE),"") | AJ9: =IF(AK9="","",TEXT(AK9,"dd")&"-"&TEXT(AL9,"dd mmm")) -> 29-30 Apr | AK9: =IFERROR($M9+VLOOKUP($L9,'Voyage days'!$F$94:$H$193,3,FALSE),"") -> 46141 | AL9: =IFERROR($N9+VLOOKUP($L9,'Voyage days'!$F$94:$H$193,3,FALSE),"") -> 46142 | AM9: =IF(AN9="","",TEXT(AN9,"dd")&"-"&TEXT(AO9,"dd mmm")) | AN9: =IFERROR($M9+VLOOKUP($L9,'Voyage days'!$F$203:$H$256,3,FALSE),"") | AO9: =IFERROR($N9+VLOOKUP($L9,'Voyage days'!$F$203:$H$256,3,FALSE),"") | AP9: =IF(AQ9="","",TEXT(AQ9,"dd")&"-"&TEXT(AR9,"dd mmm")) | AQ9: =IFERROR($M9+VLOOKUP($L9,'Voyage days'!$F$294:$H$377,3,FALSE),"") | AR9: =IFERROR($N9+VLOOKUP($L9,'Voyage days'!$F$294:$H$377,3,FALSE),"") | AS9: =IF(AT9="","",TEXT(AT9,"dd")&"-"&TEXT(AU9,"dd mmm")) | AT9: =IFERROR($M9+VLOOKUP($L9,'Voyage days'!$F$382:$H$446,3,FALSE),"") | AU9: =IFERROR($N9+VLOOKUP($L9,'Voyage days'!$F$382:$H$446,3,FALSE),"") | AV9: =IF(AW9="","",TEXT(AW9,"dd")&"-"&TEXT(AX9,"dd mmm")) | AW9: =IFERROR($M9+VLOOKUP($L9,'Voyage days'!$F$483:$H$538,3,FALSE),"") | AX9: =IFERROR($N9+VLOOKUP($L9,'Voyage days'!$F$483:$H$538,3,FALSE),"") | AY9: =IF(AZ9="","",TEXT(AZ9,"dd")&"-"&TEXT(BA9,"dd mmm")) | AZ9: =IFERROR($M9+VLOOKUP($L9,'Voyage days'!$F$540:$H$613,3,FALSE),"") | BA9: =IFERROR($N9+VLOOKUP($L9,'Voyage days'!$F$540:$H$613,3,FALSE),"") | BB9: =IF(BC9="","",TEXT(BC9,"dd")&"-"&TEXT(BD9,"dd mmm")) | BC9: =IFERROR($M9+VLOOKUP($L9,'Voyage days'!$F$448:$H$479,3,FALSE),"") | BD9: =IFERROR($N9+VLOOKUP($L9,'Voyage days'!$F$448:$H$479,3,FALSE),"") | BE9: =IF(BF9="","",TEXT(BF9,"dd")&"-"&TEXT(BG9,"dd mmm")) | BF9: =IFERROR($M9+VLOOKUP($L9,'Voyage days'!$F$620:$H$646,3,FALSE),"") | BG9: =IFERROR($N9+VLOOKUP($L9,'Voyage days'!$F$620:$H$646,3,FALSE),"") | BH9: =IF(BI9="","",TEXT(BI9,"dd")&"-"&TEXT(BL9,"dd mmm")) | BI9: =IFERROR($M9+VLOOKUP($L9,'Voyage days'!$F$702:$H$727,3,FALSE),"") | BJ9: =IF(BK9="","",TEXT(BK9,"dd")&"-"&TEXT(BL9,"dd mmm")) | BK9: =IFERROR($M9+VLOOKUP($L9,'Voyage days'!$F$807:$H$878,3,FALSE),"") | BL9: =IFERROR($N9+VLOOKUP($L9,'Voyage days'!$F$807:$H$878,3,FALSE),"") | BM9: =IFERROR($N9+VLOOKUP($L9,'Voyage days'!$F$807:$K$878,6,FALSE),"") | BN9: =if(L9="loads AG", IFERROR($M9+VLOOKUP($L9,'Voyage days'!$M$38:$O$38,3,FALSE),""),"") | BO9: =if(L9="loads USG", IFERROR($M9+VLOOKUP($L9,'Voyage days'!$L$203:$N$203,3,FALSE),""),"")
A10: Lantana Planet | B10: 2023 | C10: 84000 | H10: DF | I10: Astomos | J10: =IF(W10="","NO AIS",IF((W10-M10-1)>0,"Update","")) -> Update | L10: Balboa | M10: 46143 | N10: 46144 | P10: ETA Balboa 01 May | R10: Marathon 22-23 Feb Freeport | S10: BR | T10: 46124 | U10: =IF(V10="","No AIS",VLOOKUP(V10,'Voyage days'!$A$3:$B$1480,2,FALSE)) -> Panama | V10: =IF(VLOOKUP(A10,'1) Kpler'!$E$2:$P$1000,8, FALSE)="","",VLOOKUP(A10,'1) Kpler'!$E$2:$P$1000,8, FALSE)) -> Panama Canal | W10: =IF(VLOOKUP(A10,'1) Kpler'!$E$2:$P$1000,9,FALSE)="","",VLOOKUP(A10,'1) Kpler'!$E$2:$P$1000,9,FALSE)) -> 46145.708 | X10: =VLOOKUP(A10,'1) Kpler'!$E$2:$I$1000,4,FALSE) -> ballast | Y10: =AG10 | Z10: =AJ10 -> 12-13 May | AA10: =AM10 | AB10: =AP10 | AC10: =AS10 | AD10: =BB10 | AE10: =AY10 | AF10: =BJ10 | AG10: =IF(AH10="","",TEXT(AH10,"dd")&"-"&TEXT(AI10,"dd mmm")) | AH10: =IFERROR($M10+VLOOKUP($L10,'Voyage days'!$F$38:$H$89,3,FALSE),"") | AI10: =IFERROR(N10+VLOOKUP($L10,'Voyage days'!$F$38:$H$89,3,FALSE),"") | AJ10: =IF(AK10="","",TEXT(AK10,"dd")&"-"&TEXT(AL10,"dd mmm")) -> 12-13 May | AK10: =IFERROR($M10+VLOOKUP($L10,'Voyage days'!$F$94:$H$193,3,FALSE),"") -> 46154 | AL10: =IFERROR($N10+VLOOKUP($L10,'Voyage days'!$F$94:$H$193,3,FALSE),"") -> 46155 | AM10: =IF(AN10="","",TEXT(AN10,"dd")&"-"&TEXT(AO10,"dd mmm")) | AN10: =IFERROR($M10+VLOOKUP($L10,'Voyage days'!$F$203:$H$256,3,FALSE),"") | AO10: =IFERROR($N10+VLOOKUP($L10,'Voyage days'!$F$203:$H$256,3,FALSE),"") | AP10: =IF(AQ10="","",TEXT(AQ10,"dd")&"-"&TEXT(AR10,"dd mmm")) | AQ10: =IFERROR($M10+VLOOKUP($L10,'Voyage days'!$F$294:$H$377,3,FALSE),"") | AR10: =IFERROR($N10+VLOOKUP($L10,'Voyage days'!$F$294:$H$377,3,FALSE),"") | AS10: =IF(AT10="","",TEXT(AT10,"dd")&"-"&TEXT(AU10,"dd mmm")) | AT10: =IFERROR($M10+VLOOKUP($L10,'Voyage days'!$F$382:$H$446,3,FALSE),"") | AU10: =IFERROR($N10+VLOOKUP($L10,'Voyage days'!$F$382:$H$446,3,FALSE),"") | AV10: =IF(AW10="","",TEXT(AW10,"dd")&"-"&TEXT(AX10,"dd mmm")) | AW10: =IFERROR($M10+VLOOKUP($L10,'Voyage days'!$F$483:$H$538,3,FALSE),"") | AX10: =IFERROR($N10+VLOOKUP($L10,'Voyage days'!$F$483:$H$538,3,FALSE),"") | AY10: =IF(AZ10="","",TEXT(AZ10,"dd")&"-"&TEXT(BA10,"dd mmm")) | AZ10: =IFERROR($M10+VLOOKUP($L10,'Voyage days'!$F$540:$H$613,3,FALSE),"") | BA10: =IFERROR($N10+VLOOKUP($L10,'Voyage days'!$F$540:$H$613,3,FALSE),"") | BB10: =IF(BC10="","",TEXT(BC10,"dd")&"-"&TEXT(BD10,"dd mmm")) | BC10: =IFERROR($M10+VLOOKUP($L10,'Voyage days'!$F$448:$H$479,3,FALSE),"") | BD10: =IFERROR($N10+VLOOKUP($L10,'Voyage days'!$F$448:$H$479,3,FALSE),"") | BE10: =IF(BF10="","",TEXT(BF10,"dd")&"-"&TEXT(BG10,"dd mmm")) | BF10: =IFERROR($M10+VLOOKUP($L10,'Voyage days'!$F$620:$H$646,3,FALSE),"") | BG10: =IFERROR($N10+VLOOKUP($L10,'Voyage days'!$F$620:$H$646,3,FALSE),"") | BH10: =IF(BI10="","",TEXT(BI10,"dd")&"-"&TEXT(BL10,"dd mmm")) | BI10: =IFERROR($M10+VLOOKUP($L10,'Voyage days'!$F$702:$H$727,3,FALSE),"") | BJ10: =IF(BK10="","",TEXT(BK10,"dd")&"-"&TEXT(BL10,"dd mmm")) | BK10: =IFERROR($M10+VLOOKUP($L10,'Voyage days'!$F$807:$H$878,3,FALSE),"") | BL10: =IFERROR($N10+VLOOKUP($L10,'Voyage days'!$F$807:$H$878,3,FALSE),"") | BM10: =IFERROR($N10+VLOOKUP($L10,'Voyage days'!$F$807:$K$878,6,FALSE),"") | BN10: =if(L10="loads AG", IFERROR($M10+VLOOKUP($L10,'Voyage days'!$M$38:$O$38,3,FALSE),""),"") | BO10: =if(L10="loads USG", IFERROR($M10+VLOOKUP($L10,'Voyage days'!$L$203:$N$203,3,FALSE),""),"")
A11: Laurel Prime | B11: 43435 | C11: 83000 | I11: Astomos | J11: =IF(W11="","NO AIS",IF((W11-M11-1)>0,"Update","")) -> Update | L11: loads USG | M11: 46126 | N11: 46127 | P11: @ Houston anchorage 09 Apr, waiting to berth | R11: Exxon 09-10 Apr USG | S11: BR | T11: 46124 | U11: =IF(V11="","No AIS",VLOOKUP(V11,'Voyage days'!$A$3:$B$1480,2,FALSE)) -> Panama | V11: =IF(VLOOKUP(A11,'1) Kpler'!$E$2:$P$1000,8, FALSE)="","",VLOOKUP(A11,'1) Kpler'!$E$2:$P$1000,8, FALSE)) -> Panama Canal | W11: =IF(VLOOKUP(A11,'1) Kpler'!$E$2:$P$1000,9,FALSE)="","",VLOOKUP(A11,'1) Kpler'!$E$2:$P$1000,9,FALSE)) -> 46136.875 | X11: =VLOOKUP(A11,'1) Kpler'!$E$2:$I$1000,4,FALSE) -> loaded | Y11: =AG11 | Z11: =AJ11 -> 14-15 Apr | AA11: =AM11 -> 14-15 Apr | AB11: =AP11 | AC11: =AS11 -> 04-05 May | AD11: =BB11 | AE11: =AY11 | AF11: =BJ11 | AG11: =IF(AH11="","",TEXT(AH11,"dd")&"-"&TEXT(AI11,"dd mmm")) | AH11: =IFERROR($M11+VLOOKUP($L11,'Voyage days'!$F$38:$H$89,3,FALSE),"") | AI11: =IFERROR(N11+VLOOKUP($L11,'Voyage days'!$F$38:$H$89,3,FALSE),"") | AJ11: =IF(AK11="","",TEXT(AK11,"dd")&"-"&TEXT(AL11,"dd mmm")) -> 14-15 Apr | AK11: =IFERROR($M11+VLOOKUP($L11,'Voyage days'!$F$94:$H$193,3,FALSE),"") -> 46126 | AL11: =IFERROR($N11+VLOOKUP($L11,'Voyage days'!$F$94:$H$193,3,FALSE),"") -> 46127 | AM11: =IF(AN11="","",TEXT(AN11,"dd")&"-"&TEXT(AO11,"dd mmm")) -> 14-15 Apr | AN11: =IFERROR($M11+VLOOKUP($L11,'Voyage days'!$F$203:$H$256,3,FALSE),"") -> 46126 | AO11: =IFERROR($N11+VLOOKUP($L11,'Voyage days'!$F$203:$H$256,3,FALSE),"") -> 46127 | AP11: =IF(AQ11="","",TEXT(AQ11,"dd")&"-"&TEXT(AR11,"dd mmm")) | AQ11: =IFERROR($M11+VLOOKUP($L11,'Voyage days'!$F$294:$H$377,3,FALSE),"") | AR11: =IFERROR($N11+VLOOKUP($L11,'Voyage days'!$F$294:$H$377,3,FALSE),"") | AS11: =IF(AT11="","",TEXT(AT11,"dd")&"-"&TEXT(AU11,"dd mmm")) -> 04-05 May | AT11: =IFERROR($M11+VLOOKUP($L11,'Voyage days'!$F$382:$H$446,3,FALSE),"") -> 46146 | AU11: =IFERROR($N11+VLOOKUP($L11,'Voyage days'!$F$382:$H$446,3,FALSE),"") -> 46147 | AV11: =IF(AW11="","",TEXT(AW11,"dd")&"-"&TEXT(AX11,"dd mmm")) | AW11: =IFERROR($M11+VLOOKUP($L11,'Voyage days'!$F$483:$H$538,3,FALSE),"") | AX11: =IFERROR($N11+VLOOKUP($L11,'Voyage days'!$F$483:$H$538,3,FALSE),"") | AY11: =IF(AZ11="","",TEXT(AZ11,"dd")&"-"&TEXT(BA11,"dd mmm")) | AZ11: =IFERROR($M11+VLOOKUP($L11,'Voyage days'!$F$540:$H$613,3,FALSE),"") | BA11: =IFERROR($N11+VLOOKUP($L11,'Voyage days'!$F$540:$H$613,3,FALSE),"") | BB11: =IF(BC11="","",TEXT(BC11,"dd")&"-"&TEXT(BD11,"dd mmm")) | BC11: =IFERROR($M11+VLOOKUP($L11,'Voyage days'!$F$448:$H$479,3,FALSE),"") | BD11: =IFERROR($N11+VLOOKUP($L11,'Voyage days'!$F$448:$H$479,3,FALSE),"") | BE11: =IF(BF11="","",TEXT(BF11,"dd")&"-"&TEXT(BG11,"dd mmm")) | BF11: =IFERROR($M11+VLOOKUP($L11,'Voyage days'!$F$620:$H$646,3,FALSE),"") | BG11: =IFERROR($N11+VLOOKUP($L11,'Voyage days'!$F$620:$H$646,3,FALSE),"") | BH11: =IF(BI11="","",TEXT(BI11,"dd")&"-"&TEXT(BL11,"dd mmm")) | BI11: =IFERROR($M11+VLOOKUP($L11,'Voyage days'!$F$702:$H$727,3,FALSE),"") | BJ11: =IF(BK11="","",TEXT(BK11,"dd")&"-"&TEXT(BL11,"dd mmm")) | BK11: =IFERROR($M11+VLOOKUP($L11,'Voyage days'!$F$807:$H$878,3,FALSE),"") | BL11: =IFERROR($N11+VLOOKUP($L11,'Voyage days'!$F$807:$H$878,3,FALSE),"") | BM11: =IFERROR($N11+VLOOKUP($L11,'Voyage days'!$F$807:$K$878,6,FALSE),"") | BN11: =if(L11="loads AG", IFERROR($M11+VLOOKUP($L11,'Voyage days'!$M$38:$O$38,3,FALSE),""),"") | BO11: =if(L11="loads USG", IFERROR($M11+VLOOKUP($L11,'Voyage days'!$L$203:$N$203,3,FALSE),""),"") -> 46158
A12: Legend Prosperity | B12: 42370 | C12: 83000 | I12: Astomos | J12: =IF(W12="","NO AIS",IF((W12-M12-1)>0,"Update","")) | L12: Japan | M12: 46138 | N12: 46139 | P12: ETA 1st port Sodegaura 20 Apr | R12: Astomos 18-19 Mar Enterprise | S12: BR | T12: 46124 | U12: =IF(V12="","No AIS",VLOOKUP(V12,'Voyage days'!$A$3:$B$1480,2,FALSE)) -> Japan + 6 | V12: =IF(VLOOKUP(A12,'1) Kpler'!$E$2:$P$1000,8, FALSE)="","",VLOOKUP(A12,'1) Kpler'!$E$2:$P$1000,8, FALSE)) -> Chiba | W12: =IF(VLOOKUP(A12,'1) Kpler'!$E$2:$P$1000,9,FALSE)="","",VLOOKUP(A12,'1) Kpler'!$E$2:$P$1000,9,FALSE)) -> 46133.354 | X12: =VLOOKUP(A12,'1) Kpler'!$E$2:$I$1000,4,FALSE) -> loaded | Y12: =AG12 -> 14-15 May | Z12: =AJ12 -> 28-29 May | AA12: =AM12 -> 07-08 Jun | AB12: =AP12 -> 26-27 May | AC12: =AS12 -> 01-02 Jun | AD12: =BB12 -> 04-05 May | AE12: =AY12 -> 04-05 May | AF12: =BJ12 -> 11-12 Jun | AG12: =IF(AH12="","",TEXT(AH12,"dd")&"-"&TEXT(AI12,"dd mmm")) -> 14-15 May | AH12: =IFERROR($M12+VLOOKUP($L12,'Voyage days'!$F$38:$H$89,3,FALSE),"") -> 46156 | AI12: =IFERROR(N12+VLOOKUP($L12,'Voyage days'!$F$38:$H$89,3,FALSE),"") -> 46157 | AJ12: =IF(AK12="","",TEXT(AK12,"dd")&"-"&TEXT(AL12,"dd mmm")) -> 28-29 May | AK12: =IFERROR($M12+VLOOKUP($L12,'Voyage days'!$F$94:$H$193,3,FALSE),"") -> 46170 | AL12: =IFERROR($N12+VLOOKUP($L12,'Voyage days'!$F$94:$H$193,3,FALSE),"") -> 46171 | AM12: =IF(AN12="","",TEXT(AN12,"dd")&"-"&TEXT(AO12,"dd mmm")) -> 07-08 Jun | AN12: =IFERROR($M12+VLOOKUP($L12,'Voyage days'!$F$203:$H$256,3,FALSE),"") -> 46180 | AO12: =IFERROR($N12+VLOOKUP($L12,'Voyage days'!$F$203:$H$256,3,FALSE),"") -> 46181 | AP12: =IF(AQ12="","",TEXT(AQ12,"dd")&"-"&TEXT(AR12,"dd mmm")) -> 26-27 May | AQ12: =IFERROR($M12+VLOOKUP($L12,'Voyage days'!$F$294:$H$377,3,FALSE),"") -> 46168 | AR12: =IFERROR($N12+VLOOKUP($L12,'Voyage days'!$F$294:$H$377,3,FALSE),"") -> 46169 | AS12: =IF(AT12="","",TEXT(AT12,"dd")&"-"&TEXT(AU12,"dd mmm")) -> 01-02 Jun | AT12: =IFERROR($M12+VLOOKUP($L12,'Voyage days'!$F$382:$H$446,3,FALSE),"") -> 46174 | AU12: =IFERROR($N12+VLOOKUP($L12,'Voyage days'!$F$382:$H$446,3,FALSE),"") -> 46175 | AV12: =IF(AW12="","",TEXT(AW12,"dd")&"-"&TEXT(AX12,"dd mmm")) -> 09-10 May | AW12: =IFERROR($M12+VLOOKUP($L12,'Voyage days'!$F$483:$H$538,3,FALSE),"") -> 46151 | AX12: =IFERROR($N12+VLOOKUP($L12,'Voyage days'!$F$483:$H$538,3,FALSE),"") -> 46152 | AY12: =IF(AZ12="","",TEXT(AZ12,"dd")&"-"&TEXT(BA12,"dd mmm")) -> 04-05 May | AZ12: =IFERROR($M12+VLOOKUP($L12,'Voyage days'!$F$540:$H$613,3,FALSE),"") -> 46146.25 | BA12: =IFERROR($N12+VLOOKUP($L12,'Voyage days'!$F$540:$H$613,3,FALSE),"") -> 46147.25 | BB12: =IF(BC12="","",TEXT(BC12,"dd")&"-"&TEXT(BD12,"dd mmm")) -> 04-05 May | BC12: =IFERROR($M12+VLOOKUP($L12,'Voyage days'!$F$448:$H$479,3,FALSE),"") -> 46146 | BD12: =IFERROR($N12+VLOOKUP($L12,'Voyage days'!$F$448:$H$479,3,FALSE),"") -> 46147 | BE12: =IF(BF12="","",TEXT(BF12,"dd")&"-"&TEXT(BG12,"dd mmm")) -> 07-08 May | BF12: =IFERROR($M12+VLOOKUP($L12,'Voyage days'!$F$620:$H$646,3,FALSE),"") -> 46149 | BG12: =IFERROR($N12+VLOOKUP($L12,'Voyage days'!$F$620:$H$646,3,FALSE),"") -> 46150 | BH12: =IF(BI12="","",TEXT(BI12,"dd")&"-"&TEXT(BL12,"dd mmm")) -> 04-12 Jun | BI12: =IFERROR($M12+VLOOKUP($L12,'Voyage days'!$F$702:$H$727,3,FALSE),"") -> 46146.25 | BJ12: =IF(BK12="","",TEXT(BK12,"dd")&"-"&TEXT(BL12,"dd mmm")) -> 11-12 Jun | BK12: =IFERROR($M12+VLOOKUP($L12,'Voyage days'!$F$807:$H$878,3,FALSE),"") -> 46184 | BL12: =IFERROR($N12+VLOOKUP($L12,'Voyage days'!$F$807:$H$878,3,FALSE),"") -> 46185 | BM12: =IFERROR($N12+VLOOKUP($L12,'Voyage days'!$F$807:$K$878,6,FALSE),"") -> 46159 | BN12: =if(L12="loads AG", IFERROR($M12+VLOOKUP($L12,'Voyage days'!$M$38:$O$38,3,FALSE),""),"") | BO12: =if(L12="loads USG", IFERROR($M12+VLOOKUP($L12,'Voyage days'!$L$203:$N$203,3,FALSE),""),"")
A13: Leto Providence | B13: 37981 | C13: 78908 | I13: Astomos | J13: =IF(W13="","NO AIS",IF((W13-M13-1)>0,"Update","")) -> Update | L13: loads USG | M13: 46125 | N13: 46126 | P13: @ Nederland 12 Apr, still loading | R13: Astomos 09-10 Apr Nederland | S13: BR | T13: 46124 | U13: =IF(V13="","No AIS",VLOOKUP(V13,'Voyage days'!$A$3:$B$1480,2,FALSE)) -> Indo + 4 | V13: =IF(VLOOKUP(A13,'1) Kpler'!$E$2:$P$1000,8, FALSE)="","",VLOOKUP(A13,'1) Kpler'!$E$2:$P$1000,8, FALSE)) -> Pupuk Ammonia | W13: =IF(VLOOKUP(A13,'1) Kpler'!$E$2:$P$1000,9,FALSE)="","",VLOOKUP(A13,'1) Kpler'!$E$2:$P$1000,9,FALSE)) -> 46166.125 | X13: =VLOOKUP(A13,'1) Kpler'!$E$2:$I$1000,4,FALSE) -> loaded | Y13: =AG13 | Z13: =AJ13 -> 13-14 Apr | AA13: =AM13 -> 13-14 Apr | AB13: =AP13 | AC13: =AS13 -> 03-04 May | AD13: =BB13 | AE13: =AY13 | AF13: =BJ13 | AG13: =IF(AH13="","",TEXT(AH13,"dd")&"-"&TEXT(AI13,"dd mmm")) | AH13: =IFERROR($M13+VLOOKUP($L13,'Voyage days'!$F$38:$H$89,3,FALSE),"") | AI13: =IFERROR(N13+VLOOKUP($L13,'Voyage days'!$F$38:$H$89,3,FALSE),"") | AJ13: =IF(AK13="","",TEXT(AK13,"dd")&"-"&TEXT(AL13,"dd mmm")) -> 13-14 Apr | AK13: =IFERROR($M13+VLOOKUP($L13,'Voyage days'!$F$94:$H$193,3,FALSE),"") -> 46125 | AL13: =IFERROR($N13+VLOOKUP($L13,'Voyage days'!$F$94:$H$193,3,FALSE),"") -> 46126 | AM13: =IF(AN13="","",TEXT(AN13,"dd")&"-"&TEXT(AO13,"dd mmm")) -> 13-14 Apr | AN13: =IFERROR($M13+VLOOKUP($L13,'Voyage days'!$F$203:$H$256,3,FALSE),"") -> 46125 | AO13: =IFERROR($N13+VLOOKUP($L13,'Voyage days'!$F$203:$H$256,3,FALSE),"") -> 46126 | AP13: =IF(AQ13="","",TEXT(AQ13,"dd")&"-"&TEXT(AR13,"dd mmm")) | AQ13: =IFERROR($M13+VLOOKUP($L13,'Voyage days'!$F$294:$H$377,3,FALSE),"") | AR13: =IFERROR($N13+VLOOKUP($L13,'Voyage days'!$F$294:$H$377,3,FALSE),"") | AS13: =IF(AT13="","",TEXT(AT13,"dd")&"-"&TEXT(AU13,"dd mmm")) -> 03-04 May | AT13: =IFERROR($M13+VLOOKUP($L13,'Voyage days'!$F$382:$H$446,3,FALSE),"") -> 46145 | AU13: =IFERROR($N13+VLOOKUP($L13,'Voyage days'!$F$382:$H$446,3,FALSE),"") -> 46146 | AV13: =IF(AW13="","",TEXT(AW13,"dd")&"-"&TEXT(AX13,"dd mmm")) | AW13: =IFERROR($M13+VLOOKUP($L13,'Voyage days'!$F$483:$H$538,3,FALSE),"") | AX13: =IFERROR($N13+VLOOKUP($L13,'Voyage days'!$F$483:$H$538,3,FALSE),"") | AY13: =IF(AZ13="","",TEXT(AZ13,"dd")&"-"&TEXT(BA13,"dd mmm")) | AZ13: =IFERROR($M13+VLOOKUP($L13,'Voyage days'!$F$540:$H$613,3,FALSE),"") | BA13: =IFERROR($N13+VLOOKUP($L13,'Voyage days'!$F$540:$H$613,3,FALSE),"") | BB13: =IF(BC13="","",TEXT(BC13,"dd")&"-"&TEXT(BD13,"dd mmm")) | BC13: =IFERROR($M13+VLOOKUP($L13,'Voyage days'!$F$448:$H$479,3,FALSE),"") | BD13: =IFERROR($N13+VLOOKUP($L13,'Voyage days'!$F$448:$H$479,3,FALSE),"") | BE13: =IF(BF13="","",TEXT(BF13,"dd")&"-"&TEXT(BG13,"dd mmm")) | BF13: =IFERROR($M13+VLOOKUP($L13,'Voyage days'!$F$620:$H$646,3,FALSE),"") | BG13: =IFERROR($N13+VLOOKUP($L13,'Voyage days'!$F$620:$H$646,3,FALSE),"") | BH13: =IF(BI13="","",TEXT(BI13,"dd")&"-"&TEXT(BL13,"dd mmm")) | BI13: =IFERROR($M13+VLOOKUP($L13,'Voyage days'!$F$702:$H$727,3,FALSE),"") | BJ13: =IF(BK13="","",TEXT(BK13,"dd")&"-"&TEXT(BL13,"dd mmm")) | BK13: =IFERROR($M13+VLOOKUP($L13,'Voyage days'!$F$807:$H$878,3,FALSE),"") | BL13: =IFERROR($N13+VLOOKUP($L13,'Voyage days'!$F$807:$H$878,3,FALSE),"") | BM13: =IFERROR($N13+VLOOKUP($L13,'Voyage days'!$F$807:$K$878,6,FALSE),"") | BN13: =if(L13="loads AG", IFERROR($M13+VLOOKUP($L13,'Voyage days'!$M$38:$O$38,3,FALSE),""),"") | BO13: =if(L13="loads USG", IFERROR($M13+VLOOKUP($L13,'Voyage days'!$L$203:$N$203,3,FALSE),""),"") -> 46157
A14: Liberty Pathfinder | B14: 2024 | C14: 86700 | I14: Astomos | J14: =IF(W14="","NO AIS",IF((W14-M14-1)>0,"Update","")) -> NO AIS | L14: Japan | M14: 46133 | N14: 46134 | P14: ETA 1st port Sakai 15 Apr | R14: Astomos 25-26 Mar Dampier | S14: BR | T14: 46124 | U14: =IF(V14="","No AIS",VLOOKUP(V14,'Voyage days'!$A$3:$B$1480,2,FALSE)) -> No AIS | V14: =IF(VLOOKUP(A14,'1) Kpler'!$E$2:$P$1000,8, FALSE)="","",VLOOKUP(A14,'1) Kpler'!$E$2:$P$1000,8, FALSE)) | W14: =IF(VLOOKUP(A14,'1) Kpler'!$E$2:$P$1000,9,FALSE)="","",VLOOKUP(A14,'1) Kpler'!$E$2:$P$1000,9,FALSE)) | X14: =VLOOKUP(A14,'1) Kpler'!$E$2:$I$1000,4,FALSE) -> ballast | Y14: =AG14 -> 09-10 May | Z14: =AJ14 -> 23-24 May | AA14: =AM14 -> 02-03 Jun | AB14: =AP14 -> 21-22 May | AC14: =AS14 -> 27-28 May | AD14: =BB14 -> 29-30 Apr | AE14: =AY14 -> 29-30 Apr | AF14: =BJ14 -> 06-07 Jun | AG14: =IF(AH14="","",TEXT(AH14,"dd")&"-"&TEXT(AI14,"dd mmm")) -> 09-10 May | AH14: =IFERROR($M14+VLOOKUP($L14,'Voyage days'!$F$38:$H$89,3,FALSE),"") -> 46151 | AI14: =IFERROR(N14+VLOOKUP($L14,'Voyage days'!$F$38:$H$89,3,FALSE),"") -> 46152 | AJ14: =IF(AK14="","",TEXT(AK14,"dd")&"-"&TEXT(AL14,"dd mmm")) -> 23-24 May | AK14: =IFERROR($M14+VLOOKUP($L14,'Voyage days'!$F$94:$H$193,3,FALSE),"") -> 46165 | AL14: =IFERROR($N14+VLOOKUP($L14,'Voyage days'!$F$94:$H$193,3,FALSE),"") -> 46166 | AM14: =IF(AN14="","",TEXT(AN14,"dd")&"-"&TEXT(AO14,"dd mmm")) -> 02-03 Jun | AN14: =IFERROR($M14+VLOOKUP($L14,'Voyage days'!$F$203:$H$256,3,FALSE),"") -> 46175 | AO14: =IFERROR($N14+VLOOKUP($L14,'Voyage days'!$F$203:$H$256,3,FALSE),"") -> 46176 | AP14: =IF(AQ14="","",TEXT(AQ14,"dd")&"-"&TEXT(AR14,"dd mmm")) -> 21-22 May | AQ14: =IFERROR($M14+VLOOKUP($L14,'Voyage days'!$F$294:$H$377,3,FALSE),"") -> 46163 | AR14: =IFERROR($N14+VLOOKUP($L14,'Voyage days'!$F$294:$H$377,3,FALSE),"") -> 46164 | AS14: =IF(AT14="","",TEXT(AT14,"dd")&"-"&TEXT(AU14,"dd mmm")) -> 27-28 May | AT14: =IFERROR($M14+VLOOKUP($L14,'Voyage days'!$F$382:$H$446,3,FALSE),"") -> 46169 | AU14: =IFERROR($N14+VLOOKUP($L14,'Voyage days'!$F$382:$H$446,3,FALSE),"") -> 46170 | AV14: =IF(AW14="","",TEXT(AW14,"dd")&"-"&TEXT(AX14,"dd mmm")) -> 04-05 May | AW14: =IFERROR($M14+VLOOKUP($L14,'Voyage days'!$F$483:$H$538,3,FALSE),"") -> 46146 | AX14: =IFERROR($N14+VLOOKUP($L14,'Voyage days'!$F$483:$H$538,3,FALSE),"") -> 46147 | AY14: =IF(AZ14="","",TEXT(AZ14,"dd")&"-"&TEXT(BA14,"dd mmm")) -> 29-30 Apr | AZ14: =IFERROR($M14+VLOOKUP($L14,'Voyage days'!$F$540:$H$613,3,FALSE),"") -> 46141.25 | BA14: =IFERROR($N14+VLOOKUP($L14,'Voyage days'!$F$540:$H$613,3,FALSE),"") -> 46142.25 | BB14: =IF(BC14="","",TEXT(BC14,"dd")&"-"&TEXT(BD14,"dd mmm")) -> 29-30 Apr | BC14: =IFERROR($M14+VLOOKUP($L14,'Voyage days'!$F$448:$H$479,3,FALSE),"") -> 46141 | BD14: =IFERROR($N14+VLOOKUP($L14,'Voyage days'!$F$448:$H$479,3,FALSE),"") -> 46142 | BE14: =IF(BF14="","",TEXT(BF14,"dd")&"-"&TEXT(BG14,"dd mmm")) -> 02-03 May | BF14: =IFERROR($M14+VLOOKUP($L14,'Voyage days'!$F$620:$H$646,3,FALSE),"") -> 46144 | BG14: =IFERROR($N14+VLOOKUP($L14,'Voyage days'!$F$620:$H$646,3,FALSE),"") -> 46145 | BH14: =IF(BI14="","",TEXT(BI14,"dd")&"-"&TEXT(BL14,"dd mmm")) -> 29-07 Jun | BI14: =IFERROR($M14+VLOOKUP($L14,'Voyage days'!$F$702:$H$727,3,FALSE),"") -> 46141.25 | BJ14: =IF(BK14="","",TEXT(BK14,"dd")&"-"&TEXT(BL14,"dd mmm")) -> 06-07 Jun | BK14: =IFERROR($M14+VLOOKUP($L14,'Voyage days'!$F$807:$H$878,3,FALSE),"") -> 46179 | BL14: =IFERROR($N14+VLOOKUP($L14,'Voyage days'!$F$807:$H$878,3,FALSE),"") -> 46180 | BM14: =IFERROR($N14+VLOOKUP($L14,'Voyage days'!$F$807:$K$878,6,FALSE),"") -> 46154 | BN14: =if(L14="loads AG", IFERROR($M14+VLOOKUP($L14,'Voyage days'!$M$38:$O$38,3,FALSE),""),"") | BO14: =if(L14="loads USG", IFERROR($M14+VLOOKUP($L14,'Voyage days'!$L$203:$N$203,3,FALSE),""),"")
A15: Lily Promenade | B15: 2019 | C15: 83000 | H15: S | I15: Astomos | J15: =IF(W15="","NO AIS",IF((W15-M15-1)>0,"Update","")) | L15: Far East | M15: 46147 | N15: 46151 | P15: ETA RIPET 14 Apr | R15: Astomos 15-16 Apr RIPET | S15: BR | T15: 46124 | U15: =IF(V15="","No AIS",VLOOKUP(V15,'Voyage days'!$A$3:$B$1480,2,FALSE)) -> East China + 4 | V15: =IF(VLOOKUP(A15,'1) Kpler'!$E$2:$P$1000,8, FALSE)="","",VLOOKUP(A15,'1) Kpler'!$E$2:$P$1000,8, FALSE)) -> Taixing | W15: =IF(VLOOKUP(A15,'1) Kpler'!$E$2:$P$1000,9,FALSE)="","",VLOOKUP(A15,'1) Kpler'!$E$2:$P$1000,9,FALSE)) -> 46143.5 | X15: =VLOOKUP(A15,'1) Kpler'!$E$2:$I$1000,4,FALSE) -> loaded | Y15: =AG15 -> 23-27 May | Z15: =AJ15 -> 05-09 Jun | AA15: =AM15 -> 12-16 Jun | AB15: =AP15 -> 04-08 Jun | AC15: =AS15 -> 10-14 Jun | AD15: =BB15 -> 13-17 May | AE15: =AY15 -> 13-17 May | AF15: =BJ15 -> 20-24 Jun | AG15: =IF(AH15="","",TEXT(AH15,"dd")&"-"&TEXT(AI15,"dd mmm")) -> 23-27 May | AH15: =IFERROR($M15+VLOOKUP($L15,'Voyage days'!$F$38:$H$89,3,FALSE),"") -> 46165 | AI15: =IFERROR(N15+VLOOKUP($L15,'Voyage days'!$F$38:$H$89,3,FALSE),"") -> 46169 | AJ15: =IF(AK15="","",TEXT(AK15,"dd")&"-"&TEXT(AL15,"dd mmm")) -> 05-09 Jun | AK15: =IFERROR($M15+VLOOKUP($L15,'Voyage days'!$F$94:$H$193,3,FALSE),"") -> 46178 | AL15: =IFERROR($N15+VLOOKUP($L15,'Voyage days'!$F$94:$H$193,3,FALSE),"") -> 46182 | AM15: =IF(AN15="","",TEXT(AN15,"dd")&"-"&TEXT(AO15,"dd mmm")) -> 12-16 Jun | AN15: =IFERROR($M15+VLOOKUP($L15,'Voyage days'!$F$203:$H$256,3,FALSE),"") -> 46185 | AO15: =IFERROR($N15+VLOOKUP($L15,'Voyage days'!$F$203:$H$256,3,FALSE),"") -> 46189 | AP15: =IF(AQ15="","",TEXT(AQ15,"dd")&"-"&TEXT(AR15,"dd mmm")) -> 04-08 Jun | AQ15: =IFERROR($M15+VLOOKUP($L15,'Voyage days'!$F$294:$H$377,3,FALSE),"") -> 46177 | AR15: =IFERROR($N15+VLOOKUP($L15,'Voyage days'!$F$294:$H$377,3,FALSE),"") -> 46181 | AS15: =IF(AT15="","",TEXT(AT15,"dd")&"-"&TEXT(AU15,"dd mmm")) -> 10-14 Jun | AT15: =IFERROR($M15+VLOOKUP($L15,'Voyage days'!$F$382:$H$446,3,FALSE),"") -> 46183 | AU15: =IFERROR($N15+VLOOKUP($L15,'Voyage days'!$F$382:$H$446,3,FALSE),"") -> 46187 | AV15: =IF(AW15="","",TEXT(AW15,"dd")&"-"&TEXT(AX15,"dd mmm")) -> 18-22 May | AW15: =IFERROR($M15+VLOOKUP($L15,'Voyage days'!$F$483:$H$538,3,FALSE),"") -> 46160 | AX15: =IFERROR($N15+VLOOKUP($L15,'Voyage days'!$F$483:$H$538,3,FALSE),"") -> 46164 | AY15: =IF(AZ15="","",TEXT(AZ15,"dd")&"-"&TEXT(BA15,"dd mmm")) -> 13-17 May | AZ15: =IFERROR($M15+VLOOKUP($L15,'Voyage days'!$F$540:$H$613,3,FALSE),"") -> 46155.25 | BA15: =IFERROR($N15+VLOOKUP($L15,'Voyage days'!$F$540:$H$613,3,FALSE),"") -> 46159.25 | BB15: =IF(BC15="","",TEXT(BC15,"dd")&"-"&TEXT(BD15,"dd mmm")) -> 13-17 May | BC15: =IFERROR($M15+VLOOKUP($L15,'Voyage days'!$F$448:$H$479,3,FALSE),"") -> 46155 | BD15: =IFERROR($N15+VLOOKUP($L15,'Voyage days'!$F$448:$H$479,3,FALSE),"") -> 46159 | BE15: =IF(BF15="","",TEXT(BF15,"dd")&"-"&TEXT(BG15,"dd mmm")) -> 16-20 May | BF15: =IFERROR($M15+VLOOKUP($L15,'Voyage days'!$F$620:$H$646,3,FALSE),"") -> 46158 | BG15: =IFERROR($N15+VLOOKUP($L15,'Voyage days'!$F$620:$H$646,3,FALSE),"") -> 46162 | BH15: =IF(BI15="","",TEXT(BI15,"dd")&"-"&TEXT(BL15,"dd mmm")) -> 13-24 Jun | BI15: =IFERROR($M15+VLOOKUP($L15,'Voyage days'!$F$702:$H$727,3,FALSE),"") -> 46155.25 | BJ15: =IF(BK15="","",TEXT(BK15,"dd")&"-"&TEXT(BL15,"dd mmm")) -> 20-24 Jun | BK15: =IFERROR($M15+VLOOKUP($L15,'Voyage days'!$F$807:$H$878,3,FALSE),"") -> 46193 | BL15: =IFERROR($N15+VLOOKUP($L15,'Voyage days'!$F$807:$H$878,3,FALSE),"") -> 46197 | BM15: =IFERROR($N15+VLOOKUP($L15,'Voyage days'!$F$807:$K$878,6,FALSE),"") -> 46171 | BN15: =if(L15="loads AG", IFERROR($M15+VLOOKUP($L15,'Voyage days'!$M$38:$O$38,3,FALSE),""),"") | BO15: =if(L15="loads USG", IFERROR($M15+VLOOKUP($L15,'Voyage days'!$L$203:$N$203,3,FALSE),""),"")
A16: Luna Pathfinder | B16: 2025 | C16: 86920 | H16: S | I16: Astomos | J16: =IF(W16="","NO AIS",IF((W16-M16-1)>0,"Update","")) -> Update | L16: Balboa | M16: 46125 | N16: 46126 | P16: ETA Balboa 13 Apr | R16: Petredec 29-30 Apr USG | S16: BR | T16: 46124 | U16: =IF(V16="","No AIS",VLOOKUP(V16,'Voyage days'!$A$3:$B$1480,2,FALSE)) -> USG | V16: =IF(VLOOKUP(A16,'1) Kpler'!$E$2:$P$1000,8, FALSE)="","",VLOOKUP(A16,'1) Kpler'!$E$2:$P$1000,8, FALSE)) -> Houston | W16: =IF(VLOOKUP(A16,'1) Kpler'!$E$2:$P$1000,9,FALSE)="","",VLOOKUP(A16,'1) Kpler'!$E$2:$P$1000,9,FALSE)) -> 46133 | X16: =VLOOKUP(A16,'1) Kpler'!$E$2:$I$1000,4,FALSE) -> ballast | Y16: =AG16 | Z16: =AJ16 -> 24-25 Apr | AA16: =AM16 | AB16: =AP16 | AC16: =AS16 | AD16: =BB16 | AE16: =AY16 | AF16: =BJ16 | AG16: =IF(AH16="","",TEXT(AH16,"dd")&"-"&TEXT(AI16,"dd mmm")) | AH16: =IFERROR($M16+VLOOKUP($L16,'Voyage days'!$F$38:$H$89,3,FALSE),"") | AI16: =IFERROR(N16+VLOOKUP($L16,'Voyage days'!$F$38:$H$89,3,FALSE),"") | AJ16: =IF(AK16="","",TEXT(AK16,"dd")&"-"&TEXT(AL16,"dd mmm")) -> 24-25 Apr | AK16: =IFERROR($M16+VLOOKUP($L16,'Voyage days'!$F$94:$H$193,3,FALSE),"") -> 46136 | AL16: =IFERROR($N16+VLOOKUP($L16,'Voyage days'!$F$94:$H$193,3,FALSE),"") -> 46137 | AM16: =IF(AN16="","",TEXT(AN16,"dd")&"-"&TEXT(AO16,"dd mmm")) | AN16: =IFERROR($M16+VLOOKUP($L16,'Voyage days'!$F$203:$H$256,3,FALSE),"") | AO16: =IFERROR($N16+VLOOKUP($L16,'Voyage days'!$F$203:$H$256,3,FALSE),"") | AP16: =IF(AQ16="","",TEXT(AQ16,"dd")&"-"&TEXT(AR16,"dd mmm")) | AQ16: =IFERROR($M16+VLOOKUP($L16,'Voyage days'!$F$294:$H$377,3,FALSE),"") | AR16: =IFERROR($N16+VLOOKUP($L16,'Voyage days'!$F$294:$H$377,3,FALSE),"") | AS16: =IF(AT16="","",TEXT(AT16,"dd")&"-"&TEXT(AU16,"dd mmm")) | AT16: =IFERROR($M16+VLOOKUP($L16,'Voyage days'!$F$382:$H$446,3,FALSE),"") | AU16: =IFERROR($N16+VLOOKUP($L16,'Voyage days'!$F$382:$H$446,3,FALSE),"") | AV16: =IF(AW16="","",TEXT(AW16,"dd")&"-"&TEXT(AX16,"dd mmm")) | AW16: =IFERROR($M16+VLOOKUP($L16,'Voyage days'!$F$483:$H$538,3,FALSE),"") | AX16: =IFERROR($N16+VLOOKUP($L16,'Voyage days'!$F$483:$H$538,3,FALSE),"") | AY16: =IF(AZ16="","",TEXT(AZ16,"dd")&"-"&TEXT(BA16,"dd mmm")) | AZ16: =IFERROR($M16+VLOOKUP($L16,'Voyage days'!$F$540:$H$613,3,FALSE),"") | BA16: =IFERROR($N16+VLOOKUP($L16,'Voyage days'!$F$540:$H$613,3,FALSE),"") | BB16: =IF(BC16="","",TEXT(BC16,"dd")&"-"&TEXT(BD16,"dd mmm")) | BC16: =IFERROR($M16+VLOOKUP($L16,'Voyage days'!$F$448:$H$479,3,FALSE),"") | BD16: =IFERROR($N16+VLOOKUP($L16,'Voyage days'!$F$448:$H$479,3,FALSE),"") | BE16: =IF(BF16="","",TEXT(BF16,"dd")&"-"&TEXT(BG16,"dd mmm")) | BF16: =IFERROR($M16+VLOOKUP($L16,'Voyage days'!$F$620:$H$646,3,FALSE),"") | BG16: =IFERROR($N16+VLOOKUP($L16,'Voyage days'!$F$620:$H$646,3,FALSE),"") | BH16: =IF(BI16="","",TEXT(BI16,"dd")&"-"&TEXT(BL16,"dd mmm")) | BI16: =IFERROR($M16+VLOOKUP($L16,'Voyage days'!$F$702:$H$727,3,FALSE),"") | BJ16: =IF(BK16="","",TEXT(BK16,"dd")&"-"&TEXT(BL16,"dd mmm")) | BK16: =IFERROR($M16+VLOOKUP($L16,'Voyage days'!$F$807:$H$878,3,FALSE),"") | BL16: =IFERROR($N16+VLOOKUP($L16,'Voyage days'!$F$807:$H$878,3,FALSE),"") | BM16: =IFERROR($N16+VLOOKUP($L16,'Voyage days'!$F$807:$K$878,6,FALSE),"") | BN16: =if(L16="loads AG", IFERROR($M16+VLOOKUP($L16,'Voyage days'!$M$38:$O$38,3,FALSE),""),"") | BO16: =if(L16="loads USG", IFERROR($M16+VLOOKUP($L16,'Voyage days'!$L$203:$N$203,3,FALSE),""),"")
A17: Nadeshiko Gas | B17: 41275 | C17: 80000 | I17: Astomos | J17: =IF(W17="","NO AIS",IF((W17-M17-1)>0,"Update","")) | L17: loads USG | M17: 46158 | N17: 46159 | P17: ETA Port Louis 12 Apr | R17: Vitol 16-17 May USG | S17: BR | T17: 46124 | U17: =IF(V17="","No AIS",VLOOKUP(V17,'Voyage days'!$A$3:$B$1480,2,FALSE)) -> Cape (as proxy) | V17: =IF(VLOOKUP(A17,'1) Kpler'!$E$2:$P$1000,8, FALSE)="","",VLOOKUP(A17,'1) Kpler'!$E$2:$P$1000,8, FALSE)) -> Port Elizabeth | W17: =IF(VLOOKUP(A17,'1) Kpler'!$E$2:$P$1000,9,FALSE)="","",VLOOKUP(A17,'1) Kpler'!$E$2:$P$1000,9,FALSE)) -> 46133.292 | X17: =VLOOKUP(A17,'1) Kpler'!$E$2:$I$1000,4,FALSE) -> ballast | Y17: =AG17 | Z17: =AJ17 -> 16-17 May | AA17: =AM17 -> 16-17 May | AB17: =AP17 | AC17: =AS17 -> 05-06 Jun | AD17: =BB17 | AE17: =AY17 | AF17: =BJ17 | AG17: =IF(AH17="","",TEXT(AH17,"dd")&"-"&TEXT(AI17,"dd mmm")) | AH17: =IFERROR($M17+VLOOKUP($L17,'Voyage days'!$F$38:$H$89,3,FALSE),"") | AI17: =IFERROR(N17+VLOOKUP($L17,'Voyage days'!$F$38:$H$89,3,FALSE),"") | AJ17: =IF(AK17="","",TEXT(AK17,"dd")&"-"&TEXT(AL17,"dd mmm")) -> 16-17 May | AK17: =IFERROR($M17+VLOOKUP($L17,'Voyage days'!$F$94:$H$193,3,FALSE),"") -> 46158 | AL17: =IFERROR($N17+VLOOKUP($L17,'Voyage days'!$F$94:$H$193,3,FALSE),"") -> 46159 | AM17: =IF(AN17="","",TEXT(AN17,"dd")&"-"&TEXT(AO17,"dd mmm")) -> 16-17 May | AN17: =IFERROR($M17+VLOOKUP($L17,'Voyage days'!$F$203:$H$256,3,FALSE),"") -> 46158 | AO17: =IFERROR($N17+VLOOKUP($L17,'Voyage days'!$F$203:$H$256,3,FALSE),"") -> 46159 | AP17: =IF(AQ17="","",TEXT(AQ17,"dd")&"-"&TEXT(AR17,"dd mmm")) | AQ17: =IFERROR($M17+VLOOKUP($L17,'Voyage days'!$F$294:$H$377,3,FALSE),"") | AR17: =IFERROR($N17+VLOOKUP($L17,'Voyage days'!$F$294:$H$377,3,FALSE),"") | AS17: =IF(AT17="","",TEXT(AT17,"dd")&"-"&TEXT(AU17,"dd mmm")) -> 05-06 Jun | AT17: =IFERROR($M17+VLOOKUP($L17,'Voyage days'!$F$382:$H$446,3,FALSE),"") -> 46178 | AU17: =IFERROR($N17+VLOOKUP($L17,'Voyage days'!$F$382:$H$446,3,FALSE),"") -> 46179 | AV17: =IF(AW17="","",TEXT(AW17,"dd")&"-"&TEXT(AX17,"dd mmm")) | AW17: =IFERROR($M17+VLOOKUP($L17,'Voyage days'!$F$483:$H$538,3,FALSE),"") | AX17: =IFERROR($N17+VLOOKUP($L17,'Voyage days'!$F$483:$H$538,3,FALSE),"") | AY17: =IF(AZ17="","",TEXT(AZ17,"dd")&"-"&TEXT(BA17,"dd mmm")) | AZ17: =IFERROR($M17+VLOOKUP($L17,'Voyage days'!$F$540:$H$613,3,FALSE),"") | BA17: =IFERROR($N17+VLOOKUP($L17,'Voyage days'!$F$540:$H$613,3,FALSE),"") | BB17: =IF(BC17="","",TEXT(BC17,"dd")&"-"&TEXT(BD17,"dd mmm")) | BC17: =IFERROR($M17+VLOOKUP($L17,'Voyage days'!$F$448:$H$479,3,FALSE),"") | BD17: =IFERROR($N17+VLOOKUP($L17,'Voyage days'!$F$448:$H$479,3,FALSE),"") | BE17: =IF(BF17="","",TEXT(BF17,"dd")&"-"&TEXT(BG17,"dd mmm")) | BF17: =IFERROR($M17+VLOOKUP($L17,'Voyage days'!$F$620:$H$646,3,FALSE),"") | BG17: =IFERROR($N17+VLOOKUP($L17,'Voyage days'!$F$620:$H$646,3,FALSE),"") | BH17: =IF(BI17="","",TEXT(BI17,"dd")&"-"&TEXT(BL17,"dd mmm")) | BI17: =IFERROR($M17+VLOOKUP($L17,'Voyage days'!$F$702:$H$727,3,FALSE),"") | BJ17: =IF(BK17="","",TEXT(BK17,"dd")&"-"&TEXT(BL17,"dd mmm")) | BK17: =IFERROR($M17+VLOOKUP($L17,'Voyage days'!$F$807:$H$878,3,FALSE),"") | BL17: =IFERROR($N17+VLOOKUP($L17,'Voyage days'!$F$807:$H$878,3,FALSE),"") | BM17: =IFERROR($N17+VLOOKUP($L17,'Voyage days'!$F$807:$K$878,6,FALSE),"") | BN17: =if(L17="loads AG", IFERROR($M17+VLOOKUP($L17,'Voyage days'!$M$38:$O$38,3,FALSE),""),"") | BO17: =if(L17="loads USG", IFERROR($M17+VLOOKUP($L17,'Voyage days'!$L$203:$N$203,3,FALSE),""),"") -> 46190
A18: Ns Frontier | B18: 42675 | C18: 82200 | I18: Astomos | J18: =IF(W18="","NO AIS",IF((W18-M18-1)>0,"Update","")) -> Update | L18: loads USG | M18: 46125 | N18: 46126 | P18: @ Houston anchorage 09 Apr, waiting to berth | R18: MB Energy 11-12 Jan Enterprise | S18: BR | T18: 46124 | U18: =IF(V18="","No AIS",VLOOKUP(V18,'Voyage days'!$A$3:$B$1480,2,FALSE)) -> Indo + 4 (STS) | V18: =IF(VLOOKUP(A18,'1) Kpler'!$E$2:$P$1000,8, FALSE)="","",VLOOKUP(A18,'1) Kpler'!$E$2:$P$1000,8, FALSE)) -> Kalbut | W18: =IF(VLOOKUP(A18,'1) Kpler'!$E$2:$P$1000,9,FALSE)="","",VLOOKUP(A18,'1) Kpler'!$E$2:$P$1000,9,FALSE)) -> 46171.001 | X18: =VLOOKUP(A18,'1) Kpler'!$E$2:$I$1000,4,FALSE) -> loaded | Y18: =AG18 | Z18: =AJ18 -> 13-14 Apr | AA18: =AM18 -> 13-14 Apr | AB18: =AP18 | AC18: =AS18 -> 03-04 May | AD18: =BB18 | AE18: =AY18 | AF18: =BJ18 | AG18: =IF(AH18="","",TEXT(AH18,"dd")&"-"&TEXT(AI18,"dd mmm")) | AH18: =IFERROR($M18+VLOOKUP($L18,'Voyage days'!$F$38:$H$89,3,FALSE),"") | AI18: =IFERROR(N18+VLOOKUP($L18,'Voyage days'!$F$38:$H$89,3,FALSE),"") | AJ18: =IF(AK18="","",TEXT(AK18,"dd")&"-"&TEXT(AL18,"dd mmm")) -> 13-14 Apr | AK18: =IFERROR($M18+VLOOKUP($L18,'Voyage days'!$F$94:$H$193,3,FALSE),"") -> 46125 | AL18: =IFERROR($N18+VLOOKUP($L18,'Voyage days'!$F$94:$H$193,3,FALSE),"") -> 46126 | AM18: =IF(AN18="","",TEXT(AN18,"dd")&"-"&TEXT(AO18,"dd mmm")) -> 13-14 Apr | AN18: =IFERROR($M18+VLOOKUP($L18,'Voyage days'!$F$203:$H$256,3,FALSE),"") -> 46125 | AO18: =IFERROR($N18+VLOOKUP($L18,'Voyage days'!$F$203:$H$256,3,FALSE),"") -> 46126 | AP18: =IF(AQ18="","",TEXT(AQ18,"dd")&"-"&TEXT(AR18,"dd mmm")) | AQ18: =IFERROR($M18+VLOOKUP($L18,'Voyage days'!$F$294:$H$377,3,FALSE),"") | AR18: =IFERROR($N18+VLOOKUP($L18,'Voyage days'!$F$294:$H$377,3,FALSE),"") | AS18: =IF(AT18="","",TEXT(AT18,"dd")&"-"&TEXT(AU18,"dd mmm")) -> 03-04 May | AT18: =IFERROR($M18+VLOOKUP($L18,'Voyage days'!$F$382:$H$446,3,FALSE),"") -> 46145 | AU18: =IFERROR($N18+VLOOKUP($L18,'Voyage days'!$F$382:$H$446,3,FALSE),"") -> 46146 | AV18: =IF(AW18="","",TEXT(AW18,"dd")&"-"&TEXT(AX18,"dd mmm")) | AW18: =IFERROR($M18+VLOOKUP($L18,'Voyage days'!$F$483:$H$538,3,FALSE),"") | AX18: =IFERROR($N18+VLOOKUP($L18,'Voyage days'!$F$483:$H$538,3,FALSE),"") | AY18: =IF(AZ18="","",TEXT(AZ18,"dd")&"-"&TEXT(BA18,"dd mmm")) | AZ18: =IFERROR($M18+VLOOKUP($L18,'Voyage days'!$F$540:$H$613,3,FALSE),"") | BA18: =IFERROR($N18+VLOOKUP($L18,'Voyage days'!$F$540:$H$613,3,FALSE),"") | BB18: =IF(BC18="","",TEXT(BC18,"dd")&"-"&TEXT(BD18,"dd mmm")) | BC18: =IFERROR($M18+VLOOKUP($L18,'Voyage days'!$F$448:$H$479,3,FALSE),"") | BD18: =IFERROR($N18+VLOOKUP($L18,'Voyage days'!$F$448:$H$479,3,FALSE),"") | BE18: =IF(BF18="","",TEXT(BF18,"dd")&"-"&TEXT(BG18,"dd mmm")) | BF18: =IFERROR($M18+VLOOKUP($L18,'Voyage days'!$F$620:$H$646,3,FALSE),"") | BG18: =IFERROR($N18+VLOOKUP($L18,'Voyage days'!$F$620:$H$646,3,FALSE),"") | BH18: =IF(BI18="","",TEXT(BI18,"dd")&"-"&TEXT(BL18,"dd mmm")) | BI18: =IFERROR($M18+VLOOKUP($L18,'Voyage days'!$F$702:$H$727,3,FALSE),"") | BJ18: =IF(BK18="","",TEXT(BK18,"dd")&"-"&TEXT(BL18,"dd mmm")) | BK18: =IFERROR($M18+VLOOKUP($L18,'Voyage days'!$F$807:$H$878,3,FALSE),"") | BL18: =IFERROR($N18+VLOOKUP($L18,'Voyage days'!$F$807:$H$878,3,FALSE),"") | BM18: =IFERROR($N18+VLOOKUP($L18,'Voyage days'!$F$807:$K$878,6,FALSE),"") | BN18: =if(L18="loads AG", IFERROR($M18+VLOOKUP($L18,'Voyage days'!$M$38:$O$38,3,FALSE),""),"") | BO18: =if(L18="loads USG", IFERROR($M18+VLOOKUP($L18,'Voyage days'!$L$203:$N$203,3,FALSE),""),"") -> 46157
A19: Sumire Gas | B19: 42459 | C19: 82200 | I19: Nep-Asto-NSU-Itochu | J19: =IF(W19="","NO AIS",IF((W19-M19-1)>0,"Update","")) -> Update | L19: Singapore ballast | M19: 46127 | N19: 46128 | O19: R? | P19: ex DD, ETA Singapore 15 Apr | R19: Inpex 17-18 Feb Darwin | S19: BR | T19: 46124 | U19: =IF(V19="","No AIS",VLOOKUP(V19,'Voyage days'!$A$3:$B$1480,2,FALSE)) -> USG | V19: =IF(VLOOKUP(A19,'1) Kpler'!$E$2:$P$1000,8, FALSE)="","",VLOOKUP(A19,'1) Kpler'!$E$2:$P$1000,8, FALSE)) -> Houston | W19: =IF(VLOOKUP(A19,'1) Kpler'!$E$2:$P$1000,9,FALSE)="","",VLOOKUP(A19,'1) Kpler'!$E$2:$P$1000,9,FALSE)) -> 46163.354 | X19: =VLOOKUP(A19,'1) Kpler'!$E$2:$I$1000,4,FALSE) -> ballast | Y19: =AG19 -> 25-26 Apr | Z19: =AJ19 -> 18-19 May | AA19: =AM19 -> 19-20 May | AB19: =AP19 -> 05-06 May | AC19: =AS19 -> 13-14 May | AD19: =BB19 -> 15-16 Apr | AE19: =AY19 -> 20-21 Apr | AF19: =BJ19 -> 22-23 May | AG19: =IF(AH19="","",TEXT(AH19,"dd")&"-"&TEXT(AI19,"dd mmm")) -> 25-26 Apr | AH19: =IFERROR($M19+VLOOKUP($L19,'Voyage days'!$F$38:$H$89,3,FALSE),"") -> 46137 | AI19: =IFERROR(N19+VLOOKUP($L19,'Voyage days'!$F$38:$H$89,3,FALSE),"") -> 46138 | AJ19: =IF(AK19="","",TEXT(AK19,"dd")&"-"&TEXT(AL19,"dd mmm")) -> 18-19 May | AK19: =IFERROR($M19+VLOOKUP($L19,'Voyage days'!$F$94:$H$193,3,FALSE),"") -> 46160 | AL19: =IFERROR($N19+VLOOKUP($L19,'Voyage days'!$F$94:$H$193,3,FALSE),"") -> 46161 | AM19: =IF(AN19="","",TEXT(AN19,"dd")&"-"&TEXT(AO19,"dd mmm")) -> 19-20 May | AN19: =IFERROR($M19+VLOOKUP($L19,'Voyage days'!$F$203:$H$256,3,FALSE),"") -> 46161 | AO19: =IFERROR($N19+VLOOKUP($L19,'Voyage days'!$F$203:$H$256,3,FALSE),"") -> 46162 | AP19: =IF(AQ19="","",TEXT(AQ19,"dd")&"-"&TEXT(AR19,"dd mmm")) -> 05-06 May | AQ19: =IFERROR($M19+VLOOKUP($L19,'Voyage days'!$F$294:$H$377,3,FALSE),"") -> 46147 | AR19: =IFERROR($N19+VLOOKUP($L19,'Voyage days'!$F$294:$H$377,3,FALSE),"") -> 46148 | AS19: =IF(AT19="","",TEXT(AT19,"dd")&"-"&TEXT(AU19,"dd mmm")) -> 13-14 May | AT19: =IFERROR($M19+VLOOKUP($L19,'Voyage days'!$F$382:$H$446,3,FALSE),"") -> 46155 | AU19: =IFERROR($N19+VLOOKUP($L19,'Voyage days'!$F$382:$H$446,3,FALSE),"") -> 46156 | AV19: =IF(AW19="","",TEXT(AW19,"dd")&"-"&TEXT(AX19,"dd mmm")) -> 26-27 Apr | AW19: =IFERROR($M19+VLOOKUP($L19,'Voyage days'!$F$483:$H$538,3,FALSE),"") -> 46138 | AX19: =IFERROR($N19+VLOOKUP($L19,'Voyage days'!$F$483:$H$538,3,FALSE),"") -> 46139 | AY19: =IF(AZ19="","",TEXT(AZ19,"dd")&"-"&TEXT(BA19,"dd mmm")) -> 20-21 Apr | AZ19: =IFERROR($M19+VLOOKUP($L19,'Voyage days'!$F$540:$H$613,3,FALSE),"") -> 46132.25 | BA19: =IFERROR($N19+VLOOKUP($L19,'Voyage days'!$F$540:$H$613,3,FALSE),"") -> 46133.25 | BB19: =IF(BC19="","",TEXT(BC19,"dd")&"-"&TEXT(BD19,"dd mmm")) -> 15-16 Apr | BC19: =IFERROR($M19+VLOOKUP($L19,'Voyage days'!$F$448:$H$479,3,FALSE),"") -> 46127 | BD19: =IFERROR($N19+VLOOKUP($L19,'Voyage days'!$F$448:$H$479,3,FALSE),"") -> 46128 | BE19: =IF(BF19="","",TEXT(BF19,"dd")&"-"&TEXT(BG19,"dd mmm")) | BF19: =IFERROR($M19+VLOOKUP($L19,'Voyage days'!$F$620:$H$646,3,FALSE),"") | BG19: =IFERROR($N19+VLOOKUP($L19,'Voyage days'!$F$620:$H$646,3,FALSE),"") | BH19: =IF(BI19="","",TEXT(BI19,"dd")&"-"&TEXT(BL19,"dd mmm")) -> 25-23 May | BI19: =IFERROR($M19+VLOOKUP($L19,'Voyage days'!$F$702:$H$727,3,FALSE),"") -> 46137 | BJ19: =IF(BK19="","",TEXT(BK19,"dd")&"-"&TEXT(BL19,"dd mmm")) -> 22-23 May | BK19: =IFERROR($M19+VLOOKUP($L19,'Voyage days'!$F$807:$H$878,3,FALSE),"") -> 46164 | BL19: =IFERROR($N19+VLOOKUP($L19,'Voyage days'!$F$807:$H$878,3,FALSE),"") -> 46165 | BM19: =IFERROR($N19+VLOOKUP($L19,'Voyage days'!$F$807:$K$878,6,FALSE),"") -> 46141 | BN19: =if(L19="loads AG", IFERROR($M19+VLOOKUP($L19,'Voyage days'!$M$38:$O$38,3,FALSE),""),"") | BO19: =if(L19="loads USG", IFERROR($M19+VLOOKUP($L19,'Voyage days'!$L$203:$N$203,3,FALSE),""),"")
A20: Al Maryah | B20: 2008 | C20: 84000 | I20: AGT>ATL 60-90days | J20: =IF(W20="","NO AIS",IF((W20-M20-1)>0,"Update","")) -> NO AIS | L20: South China | M20: 46132 | N20: 46133 | P20: ATC short TC, ETA South China 18 Apr | R20: ATC End Mar Yanbu (short TC) | S20: BR | T20: 46124 | U20: =IF(V20="","No AIS",VLOOKUP(V20,'Voyage days'!$A$3:$B$1480,2,FALSE)) -> No AIS | V20: =IF(VLOOKUP(A20,'1) Kpler'!$E$2:$P$1000,8, FALSE)="","",VLOOKUP(A20,'1) Kpler'!$E$2:$P$1000,8, FALSE)) | W20: =IF(VLOOKUP(A20,'1) Kpler'!$E$2:$P$1000,9,FALSE)="","",VLOOKUP(A20,'1) Kpler'!$E$2:$P$1000,9,FALSE)) | X20: =VLOOKUP(A20,'1) Kpler'!$E$2:$I$1000,4,FALSE) -> ballast | Y20: =AG20 -> 05-06 May | Z20: =AJ20 -> 27-28 May | AA20: =AM20 -> 01-02 Jun | AB20: =AP20 -> 16-17 May | AC20: =AS20 -> 23-24 May | AD20: =BB20 -> 24-25 Apr | AE20: =AY20 -> 26-27 Apr | AF20: =BJ20 -> 01-02 Jun | AG20: =IF(AH20="","",TEXT(AH20,"dd")&"-"&TEXT(AI20,"dd mmm")) -> 05-06 May | AH20: =IFERROR($M20+VLOOKUP($L20,'Voyage days'!$F$38:$H$89,3,FALSE),"") -> 46147 | AI20: =IFERROR(N20+VLOOKUP($L20,'Voyage days'!$F$38:$H$89,3,FALSE),"") -> 46148 | AJ20: =IF(AK20="","",TEXT(AK20,"dd")&"-"&TEXT(AL20,"dd mmm")) -> 27-28 May | AK20: =IFERROR($M20+VLOOKUP($L20,'Voyage days'!$F$94:$H$193,3,FALSE),"") -> 46169 | AL20: =IFERROR($N20+VLOOKUP($L20,'Voyage days'!$F$94:$H$193,3,FALSE),"") -> 46170 | AM20: =IF(AN20="","",TEXT(AN20,"dd")&"-"&TEXT(AO20,"dd mmm")) -> 01-02 Jun | AN20: =IFERROR($M20+VLOOKUP($L20,'Voyage days'!$F$203:$H$256,3,FALSE),"") -> 46174 | AO20: =IFERROR($N20+VLOOKUP($L20,'Voyage days'!$F$203:$H$256,3,FALSE),"") -> 46175 | AP20: =IF(AQ20="","",TEXT(AQ20,"dd")&"-"&TEXT(AR20,"dd mmm")) -> 16-17 May | AQ20: =IFERROR($M20+VLOOKUP($L20,'Voyage days'!$F$294:$H$377,3,FALSE),"") -> 46158 | AR20: =IFERROR($N20+VLOOKUP($L20,'Voyage days'!$F$294:$H$377,3,FALSE),"") -> 46159 | AS20: =IF(AT20="","",TEXT(AT20,"dd")&"-"&TEXT(AU20,"dd mmm")) -> 23-24 May | AT20: =IFERROR($M20+VLOOKUP($L20,'Voyage days'!$F$382:$H$446,3,FALSE),"") -> 46165 | AU20: =IFERROR($N20+VLOOKUP($L20,'Voyage days'!$F$382:$H$446,3,FALSE),"") -> 46166 | AV20: =IF(AW20="","",TEXT(AW20,"dd")&"-"&TEXT(AX20,"dd mmm")) -> 04-05 May | AW20: =IFERROR($M20+VLOOKUP($L20,'Voyage days'!$F$483:$H$538,3,FALSE),"") -> 46146 | AX20: =IFERROR($N20+VLOOKUP($L20,'Voyage days'!$F$483:$H$538,3,FALSE),"") -> 46147 | AY20: =IF(AZ20="","",TEXT(AZ20,"dd")&"-"&TEXT(BA20,"dd mmm")) -> 26-27 Apr | AZ20: =IFERROR($M20+VLOOKUP($L20,'Voyage days'!$F$540:$H$613,3,FALSE),"") -> 46138.75 | BA20: =IFERROR($N20+VLOOKUP($L20,'Voyage days'!$F$540:$H$613,3,FALSE),"") -> 46139.75 | BB20: =IF(BC20="","",TEXT(BC20,"dd")&"-"&TEXT(BD20,"dd mmm")) -> 24-25 Apr | BC20: =IFERROR($M20+VLOOKUP($L20,'Voyage days'!$F$448:$H$479,3,FALSE),"") -> 46136 | BD20: =IFERROR($N20+VLOOKUP($L20,'Voyage days'!$F$448:$H$479,3,FALSE),"") -> 46137 | BE20: =IF(BF20="","",TEXT(BF20,"dd")&"-"&TEXT(BG20,"dd mmm")) | BF20: =IFERROR($M20+VLOOKUP($L20,'Voyage days'!$F$620:$H$646,3,FALSE),"") | BG20: =IFERROR($N20+VLOOKUP($L20,'Voyage days'!$F$620:$H$646,3,FALSE),"") | BH20: =IF(BI20="","",TEXT(BI20,"dd")&"-"&TEXT(BL20,"dd mmm")) -> 26-02 Jun | BI20: =IFERROR($M20+VLOOKUP($L20,'Voyage days'!$F$702:$H$727,3,FALSE),"") -> 46138.75 | BJ20: =IF(BK20="","",TEXT(BK20,"dd")&"-"&TEXT(BL20,"dd mmm")) -> 01-02 Jun | BK20: =IFERROR($M20+VLOOKUP($L20,'Voyage days'!$F$807:$H$878,3,FALSE),"") -> 46174 | BL20: =IFERROR($N20+VLOOKUP($L20,'Voyage days'!$F$807:$H$878,3,FALSE),"") -> 46175 | BM20: =IFERROR($N20+VLOOKUP($L20,'Voyage days'!$F$807:$K$878,6,FALSE),"") -> 46150 | BN20: =if(L20="loads AG", IFERROR($M20+VLOOKUP($L20,'Voyage days'!$M$38:$O$38,3,FALSE),""),"") | BO20: =if(L20="loads USG", IFERROR($M20+VLOOKUP($L20,'Voyage days'!$L$203:$N$203,3,FALSE),""),"")
A21: Berge Nantong | B21: 2006 | C21: 82244 | E21: C | I21: AGT | J21: =IF(W21="","NO AIS",IF((W21-M21-1)>0,"Update","")) -> Update | L21: Port Louis ballast | M21: 46118 | N21: 46119 | O21: R | P21: sailed 27 Mar, ETA USG 02 May via Cape | R21: AGT 25 Feb Ruwais | S21: BR | T21: 46124 | U21: =IF(V21="","No AIS",VLOOKUP(V21,'Voyage days'!$A$3:$B$1480,2,FALSE)) -> USG | V21: =IF(VLOOKUP(A21,'1) Kpler'!$E$2:$P$1000,8, FALSE)="","",VLOOKUP(A21,'1) Kpler'!$E$2:$P$1000,8, FALSE)) -> Houston | W21: =IF(VLOOKUP(A21,'1) Kpler'!$E$2:$P$1000,9,FALSE)="","",VLOOKUP(A21,'1) Kpler'!$E$2:$P$1000,9,FALSE)) -> 46144.5 | X21: =VLOOKUP(A21,'1) Kpler'!$E$2:$I$1000,4,FALSE) -> ballast | Y21: =AG21 | Z21: =AJ21 | AA21: =AM21 -> 02-03 May | AB21: =AP21 -> 19-20 Apr | AC21: =AS21 -> 28-29 Apr | AD21: =BB21 | AE21: =AY21 | AF21: =BJ21 -> 03-04 May | AG21: =IF(AH21="","",TEXT(AH21,"dd")&"-"&TEXT(AI21,"dd mmm")) | AH21: =IFERROR($M21+VLOOKUP($L21,'Voyage days'!$F$38:$H$89,3,FALSE),"") | AI21: =IFERROR(N21+VLOOKUP($L21,'Voyage days'!$F$38:$H$89,3,FALSE),"") | AJ21: =IF(AK21="","",TEXT(AK21,"dd")&"-"&TEXT(AL21,"dd mmm")) | AK21: =IFERROR($M21+VLOOKUP($L21,'Voyage days'!$F$94:$H$193,3,FALSE),"") | AL21: =IFERROR($N21+VLOOKUP($L21,'Voyage days'!$F$94:$H$193,3,FALSE),"") | AM21: =IF(AN21="","",TEXT(AN21,"dd")&"-"&TEXT(AO21,"dd mmm")) -> 02-03 May | AN21: =IFERROR($M21+VLOOKUP($L21,'Voyage days'!$F$203:$H$256,3,FALSE),"") -> 46144 | AO21: =IFERROR($N21+VLOOKUP($L21,'Voyage days'!$F$203:$H$256,3,FALSE),"") -> 46145 | AP21: =IF(AQ21="","",TEXT(AQ21,"dd")&"-"&TEXT(AR21,"dd mmm")) -> 19-20 Apr | AQ21: =IFERROR($M21+VLOOKUP($L21,'Voyage days'!$F$294:$H$377,3,FALSE),"") -> 46131 | AR21: =IFERROR($N21+VLOOKUP($L21,'Voyage days'!$F$294:$H$377,3,FALSE),"") -> 46132 | AS21: =IF(AT21="","",TEXT(AT21,"dd")&"-"&TEXT(AU21,"dd mmm")) -> 28-29 Apr | AT21: =IFERROR($M21+VLOOKUP($L21,'Voyage days'!$F$382:$H$446,3,FALSE),"") -> 46140 | AU21: =IFERROR($N21+VLOOKUP($L21,'Voyage days'!$F$382:$H$446,3,FALSE),"") -> 46141 | AV21: =IF(AW21="","",TEXT(AW21,"dd")&"-"&TEXT(AX21,"dd mmm")) | AW21: =IFERROR($M21+VLOOKUP($L21,'Voyage days'!$F$483:$H$538,3,FALSE),"") | AX21: =IFERROR($N21+VLOOKUP($L21,'Voyage days'!$F$483:$H$538,3,FALSE),"") | AY21: =IF(AZ21="","",TEXT(AZ21,"dd")&"-"&TEXT(BA21,"dd mmm")) | AZ21: =IFERROR($M21+VLOOKUP($L21,'Voyage days'!$F$540:$H$613,3,FALSE),"") | BA21: =IFERROR($N21+VLOOKUP($L21,'Voyage days'!$F$540:$H$613,3,FALSE),"") | BB21: =IF(BC21="","",TEXT(BC21,"dd")&"-"&TEXT(BD21,"dd mmm")) | BC21: =IFERROR($M21+VLOOKUP($L21,'Voyage days'!$F$448:$H$479,3,FALSE),"") | BD21: =IFERROR($N21+VLOOKUP($L21,'Voyage days'!$F$448:$H$479,3,FALSE),"") | BE21: =IF(BF21="","",TEXT(BF21,"dd")&"-"&TEXT(BG21,"dd mmm")) | BF21: =IFERROR($M21+VLOOKUP($L21,'Voyage days'!$F$620:$H$646,3,FALSE),"") | BG21: =IFERROR($N21+VLOOKUP($L21,'Voyage days'!$F$620:$H$646,3,FALSE),"") | BH21: =IF(BI21="","",TEXT(BI21,"dd")&"-"&TEXT(BL21,"dd mmm")) | BI21: =IFERROR($M21+VLOOKUP($L21,'Voyage days'!$F$702:$H$727,3,FALSE),"") | BJ21: =IF(BK21="","",TEXT(BK21,"dd")&"-"&TEXT(BL21,"dd mmm")) -> 03-04 May | BK21: =IFERROR($M21+VLOOKUP($L21,'Voyage days'!$F$807:$H$878,3,FALSE),"") -> 46145 | BL21: =IFERROR($N21+VLOOKUP($L21,'Voyage days'!$F$807:$H$878,3,FALSE),"") -> 46146 | BM21: =IFERROR($N21+VLOOKUP($L21,'Voyage days'!$F$807:$K$878,6,FALSE),"") -> 46119 | BN21: =if(L21="loads AG", IFERROR($M21+VLOOKUP($L21,'Voyage days'!$M$38:$O$38,3,FALSE),""),"") | BO21: =if(L21="loads USG", IFERROR($M21+VLOOKUP($L21,'Voyage days'!$L$203:$N$203,3,FALSE),""),"")
A22: BW Kizoku | B22: 2019 | C22: 83325 | H22: S | I22: AGT | J22: =IF(W22="","NO AIS",IF((W22-M22-1)>0,"Update","")) -> Update | L22: loads USG | M22: 46125 | N22: 46126 | P22: @ Galveston lighterage 11 Apr | R22: Wanhua 13-14 Apr Nederland | S22: BR | T22: 46124 | U22: =IF(V22="","No AIS",VLOOKUP(V22,'Voyage days'!$A$3:$B$1480,2,FALSE)) -> Panama | V22: =IF(VLOOKUP(A22,'1) Kpler'!$E$2:$P$1000,8, FALSE)="","",VLOOKUP(A22,'1) Kpler'!$E$2:$P$1000,8, FALSE)) -> Panama Canal | W22: =IF(VLOOKUP(A22,'1) Kpler'!$E$2:$P$1000,9,FALSE)="","",VLOOKUP(A22,'1) Kpler'!$E$2:$P$1000,9,FALSE)) -> 46133.5 | X22: =VLOOKUP(A22,'1) Kpler'!$E$2:$I$1000,4,FALSE) -> loaded | Y22: =AG22 | Z22: =AJ22 -> 13-14 Apr | AA22: =AM22 -> 13-14 Apr | AB22: =AP22 | AC22: =AS22 -> 03-04 May | AD22: =BB22 | AE22: =AY22 | AF22: =BJ22 | AG22: =IF(AH22="","",TEXT(AH22,"dd")&"-"&TEXT(AI22,"dd mmm")) | AH22: =IFERROR($M22+VLOOKUP($L22,'Voyage days'!$F$38:$H$89,3,FALSE),"") | AI22: =IFERROR(N22+VLOOKUP($L22,'Voyage days'!$F$38:$H$89,3,FALSE),"") | AJ22: =IF(AK22="","",TEXT(AK22,"dd")&"-"&TEXT(AL22,"dd mmm")) -> 13-14 Apr | AK22: =IFERROR($M22+VLOOKUP($L22,'Voyage days'!$F$94:$H$193,3,FALSE),"") -> 46125 | AL22: =IFERROR($N22+VLOOKUP($L22,'Voyage days'!$F$94:$H$193,3,FALSE),"") -> 46126 | AM22: =IF(AN22="","",TEXT(AN22,"dd")&"-"&TEXT(AO22,"dd mmm")) -> 13-14 Apr | AN22: =IFERROR($M22+VLOOKUP($L22,'Voyage days'!$F$203:$H$256,3,FALSE),"") -> 46125 | AO22: =IFERROR($N22+VLOOKUP($L22,'Voyage days'!$F$203:$H$256,3,FALSE),"") -> 46126 | AP22: =IF(AQ22="","",TEXT(AQ22,"dd")&"-"&TEXT(AR22,"dd mmm")) | AQ22: =IFERROR($M22+VLOOKUP($L22,'Voyage days'!$F$294:$H$377,3,FALSE),"") | AR22: =IFERROR($N22+VLOOKUP($L22,'Voyage days'!$F$294:$H$377,3,FALSE),"") | AS22: =IF(AT22="","",TEXT(AT22,"dd")&"-"&TEXT(AU22,"dd mmm")) -> 03-04 May | AT22: =IFERROR($M22+VLOOKUP($L22,'Voyage days'!$F$382:$H$446,3,FALSE),"") -> 46145 | AU22: =IFERROR($N22+VLOOKUP($L22,'Voyage days'!$F$382:$H$446,3,FALSE),"") -> 46146 | AV22: =IF(AW22="","",TEXT(AW22,"dd")&"-"&TEXT(AX22,"dd mmm")) | AW22: =IFERROR($M22+VLOOKUP($L22,'Voyage days'!$F$483:$H$538,3,FALSE),"") | AX22: =IFERROR($N22+VLOOKUP($L22,'Voyage days'!$F$483:$H$538,3,FALSE),"") | AY22: =IF(AZ22="","",TEXT(AZ22,"dd")&"-"&TEXT(BA22,"dd mmm")) | AZ22: =IFERROR($M22+VLOOKUP($L22,'Voyage days'!$F$540:$H$613,3,FALSE),"") | BA22: =IFERROR($N22+VLOOKUP($L22,'Voyage days'!$F$540:$H$613,3,FALSE),"") | BB22: =IF(BC22="","",TEXT(BC22,"dd")&"-"&TEXT(BD22,"dd mmm")) | BC22: =IFERROR($M22+VLOOKUP($L22,'Voyage days'!$F$448:$H$479,3,FALSE),"") | BD22: =IFERROR($N22+VLOOKUP($L22,'Voyage days'!$F$448:$H$479,3,FALSE),"") | BE22: =IF(BF22="","",TEXT(BF22,"dd")&"-"&TEXT(BG22,"dd mmm")) | BF22: =IFERROR($M22+VLOOKUP($L22,'Voyage days'!$F$620:$H$646,3,FALSE),"") | BG22: =IFERROR($N22+VLOOKUP($L22,'Voyage days'!$F$620:$H$646,3,FALSE),"") | BH22: =IF(BI22="","",TEXT(BI22,"dd")&"-"&TEXT(BL22,"dd mmm")) | BI22: =IFERROR($M22+VLOOKUP($L22,'Voyage days'!$F$702:$H$727,3,FALSE),"") | BJ22: =IF(BK22="","",TEXT(BK22,"dd")&"-"&TEXT(BL22,"dd mmm")) | BK22: =IFERROR($M22+VLOOKUP($L22,'Voyage days'!$F$807:$H$878,3,FALSE),"") | BL22: =IFERROR($N22+VLOOKUP($L22,'Voyage days'!$F$807:$H$878,3,FALSE),"") | BM22: =IFERROR($N22+VLOOKUP($L22,'Voyage days'!$F$807:$K$878,6,FALSE),"") | BN22: =if(L22="loads AG", IFERROR($M22+VLOOKUP($L22,'Voyage days'!$M$38:$O$38,3,FALSE),""),"") | BO22: =if(L22="loads USG", IFERROR($M22+VLOOKUP($L22,'Voyage days'!$L$203:$N$203,3,FALSE),""),"") -> 46157
A23: Corfu Gas | B23: 2025 | C23: 88000 | E23: C | H23: DF | I23: AGT | J23: =IF(W23="","NO AIS",IF((W23-M23-1)>0,"Update","")) -> Update | L23: loads USG | M23: 46127 | N23: 46128 | P23: drifting USG 06 Apr, waiting to berth | R23: BASF 15-16 Apr Freeport | S23: BR | T23: 46124 | U23: =IF(V23="","No AIS",VLOOKUP(V23,'Voyage days'!$A$3:$B$1480,2,FALSE)) -> Panama | V23: =IF(VLOOKUP(A23,'1) Kpler'!$E$2:$P$1000,8, FALSE)="","",VLOOKUP(A23,'1) Kpler'!$E$2:$P$1000,8, FALSE)) -> Panama Canal | W23: =IF(VLOOKUP(A23,'1) Kpler'!$E$2:$P$1000,9,FALSE)="","",VLOOKUP(A23,'1) Kpler'!$E$2:$P$1000,9,FALSE)) -> 46135.25 | X23: =VLOOKUP(A23,'1) Kpler'!$E$2:$I$1000,4,FALSE) -> loaded | Y23: =AG23 | Z23: =AJ23 -> 15-16 Apr | AA23: =AM23 -> 15-16 Apr | AB23: =AP23 | AC23: =AS23 -> 05-06 May | AD23: =BB23 | AE23: =AY23 | AF23: =BJ23 | AG23: =IF(AH23="","",TEXT(AH23,"dd")&"-"&TEXT(AI23,"dd mmm")) | AH23: =IFERROR($M23+VLOOKUP($L23,'Voyage days'!$F$38:$H$89,3,FALSE),"") | AI23: =IFERROR(N23+VLOOKUP($L23,'Voyage days'!$F$38:$H$89,3,FALSE),"") | AJ23: =IF(AK23="","",TEXT(AK23,"dd")&"-"&TEXT(AL23,"dd mmm")) -> 15-16 Apr | AK23: =IFERROR($M23+VLOOKUP($L23,'Voyage days'!$F$94:$H$193,3,FALSE),"") -> 46127 | AL23: =IFERROR($N23+VLOOKUP($L23,'Voyage days'!$F$94:$H$193,3,FALSE),"") -> 46128 | AM23: =IF(AN23="","",TEXT(AN23,"dd")&"-"&TEXT(AO23,"dd mmm")) -> 15-16 Apr | AN23: =IFERROR($M23+VLOOKUP($L23,'Voyage days'!$F$203:$H$256,3,FALSE),"") -> 46127 | AO23: =IFERROR($N23+VLOOKUP($L23,'Voyage days'!$F$203:$H$256,3,FALSE),"") -> 46128 | AP23: =IF(AQ23="","",TEXT(AQ23,"dd")&"-"&TEXT(AR23,"dd mmm")) | AQ23: =IFERROR($M23+VLOOKUP($L23,'Voyage days'!$F$294:$H$377,3,FALSE),"") | AR23: =IFERROR($N23+VLOOKUP($L23,'Voyage days'!$F$294:$H$377,3,FALSE),"") | AS23: =IF(AT23="","",TEXT(AT23,"dd")&"-"&TEXT(AU23,"dd mmm")) -> 05-06 May | AT23: =IFERROR($M23+VLOOKUP($L23,'Voyage days'!$F$382:$H$446,3,FALSE),"") -> 46147 | AU23: =IFERROR($N23+VLOOKUP($L23,'Voyage days'!$F$382:$H$446,3,FALSE),"") -> 46148 | AV23: =IF(AW23="","",TEXT(AW23,"dd")&"-"&TEXT(AX23,"dd mmm")) | AW23: =IFERROR($M23+VLOOKUP($L23,'Voyage days'!$F$483:$H$538,3,FALSE),"") | AX23: =IFERROR($N23+VLOOKUP($L23,'Voyage days'!$F$483:$H$538,3,FALSE),"") | AY23: =IF(AZ23="","",TEXT(AZ23,"dd")&"-"&TEXT(BA23,"dd mmm")) | AZ23: =IFERROR($M23+VLOOKUP($L23,'Voyage days'!$F$540:$H$613,3,FALSE),"") | BA23: =IFERROR($N23+VLOOKUP($L23,'Voyage days'!$F$540:$H$613,3,FALSE),"") | BB23: =IF(BC23="","",TEXT(BC23,"dd")&"-"&TEXT(BD23,"dd mmm")) | BC23: =IFERROR($M23+VLOOKUP($L23,'Voyage days'!$F$448:$H$479,3,FALSE),"") | BD23: =IFERROR($N23+VLOOKUP($L23,'Voyage days'!$F$448:$H$479,3,FALSE),"") | BE23: =IF(BF23="","",TEXT(BF23,"dd")&"-"&TEXT(BG23,"dd mmm")) | BF23: =IFERROR($M23+VLOOKUP($L23,'Voyage days'!$F$620:$H$646,3,FALSE),"") | BG23: =IFERROR($N23+VLOOKUP($L23,'Voyage days'!$F$620:$H$646,3,FALSE),"") | BH23: =IF(BI23="","",TEXT(BI23,"dd")&"-"&TEXT(BL23,"dd mmm")) | BI23: =IFERROR($M23+VLOOKUP($L23,'Voyage days'!$F$702:$H$727,3,FALSE),"") | BJ23: =IF(BK23="","",TEXT(BK23,"dd")&"-"&TEXT(BL23,"dd mmm")) | BK23: =IFERROR($M23+VLOOKUP($L23,'Voyage days'!$F$807:$H$878,3,FALSE),"") | BL23: =IFERROR($N23+VLOOKUP($L23,'Voyage days'!$F$807:$H$878,3,FALSE),"") | BM23: =IFERROR($N23+VLOOKUP($L23,'Voyage days'!$F$807:$K$878,6,FALSE),"") | BN23: =if(L23="loads AG", IFERROR($M23+VLOOKUP($L23,'Voyage days'!$M$38:$O$38,3,FALSE),""),"") | BO23: =if(L23="loads USG", IFERROR($M23+VLOOKUP($L23,'Voyage days'!$L$203:$N$203,3,FALSE),""),"") -> 46159
A24: Crystal River | B24: 42938 | C24: 82200 | I24: Astomos > AGT | J24: =IF(W24="","NO AIS",IF((W24-M24-1)>0,"Update","")) | L24: loads USG | M24: 46151 | N24: 46152 | P24: ETA Singapore 15 Apr | R24: AGT own cargo early May | S24: BR | T24: 46124 | U24: =IF(V24="","No AIS",VLOOKUP(V24,'Voyage days'!$A$3:$B$1480,2,FALSE)) -> Galle +2 | V24: =IF(VLOOKUP(A24,'1) Kpler'!$E$2:$P$1000,8, FALSE)="","",VLOOKUP(A24,'1) Kpler'!$E$2:$P$1000,8, FALSE)) -> Galle | W24: =IF(VLOOKUP(A24,'1) Kpler'!$E$2:$P$1000,9,FALSE)="","",VLOOKUP(A24,'1) Kpler'!$E$2:$P$1000,9,FALSE)) -> 46135.958 | X24: =VLOOKUP(A24,'1) Kpler'!$E$2:$I$1000,4,FALSE) -> ballast | Y24: =AG24 | Z24: =AJ24 -> 09-10 May | AA24: =AM24 -> 09-10 May | AB24: =AP24 | AC24: =AS24 -> 29-30 May | AD24: =BB24 | AE24: =AY24 | AF24: =BJ24 | AG24: =IF(AH24="","",TEXT(AH24,"dd")&"-"&TEXT(AI24,"dd mmm")) | AH24: =IFERROR($M24+VLOOKUP($L24,'Voyage days'!$F$38:$H$89,3,FALSE),"") | AI24: =IFERROR(N24+VLOOKUP($L24,'Voyage days'!$F$38:$H$89,3,FALSE),"") | AJ24: =IF(AK24="","",TEXT(AK24,"dd")&"-"&TEXT(AL24,"dd mmm")) -> 09-10 May | AK24: =IFERROR($M24+VLOOKUP($L24,'Voyage days'!$F$94:$H$193,3,FALSE),"") -> 46151 | AL24: =IFERROR($N24+VLOOKUP($L24,'Voyage days'!$F$94:$H$193,3,FALSE),"") -> 46152 | AM24: =IF(AN24="","",TEXT(AN24,"dd")&"-"&TEXT(AO24,"dd mmm")) -> 09-10 May | AN24: =IFERROR($M24+VLOOKUP($L24,'Voyage days'!$F$203:$H$256,3,FALSE),"") -> 46151 | AO24: =IFERROR($N24+VLOOKUP($L24,'Voyage days'!$F$203:$H$256,3,FALSE),"") -> 46152 | AP24: =IF(AQ24="","",TEXT(AQ24,"dd")&"-"&TEXT(AR24,"dd mmm")) | AQ24: =IFERROR($M24+VLOOKUP($L24,'Voyage days'!$F$294:$H$377,3,FALSE),"") | AR24: =IFERROR($N24+VLOOKUP($L24,'Voyage days'!$F$294:$H$377,3,FALSE),"") | AS24: =IF(AT24="","",TEXT(AT24,"dd")&"-"&TEXT(AU24,"dd mmm")) -> 29-30 May | AT24: =IFERROR($M24+VLOOKUP($L24,'Voyage days'!$F$382:$H$446,3,FALSE),"") -> 46171 | AU24: =IFERROR($N24+VLOOKUP($L24,'Voyage days'!$F$382:$H$446,3,FALSE),"") -> 46172 | AV24: =IF(AW24="","",TEXT(AW24,"dd")&"-"&TEXT(AX24,"dd mmm")) | AW24: =IFERROR($M24+VLOOKUP($L24,'Voyage days'!$F$483:$H$538,3,FALSE),"") | AX24: =IFERROR($N24+VLOOKUP($L24,'Voyage days'!$F$483:$H$538,3,FALSE),"") | AY24: =IF(AZ24="","",TEXT(AZ24,"dd")&"-"&TEXT(BA24,"dd mmm")) | AZ24: =IFERROR($M24+VLOOKUP($L24,'Voyage days'!$F$540:$H$613,3,FALSE),"") | BA24: =IFERROR($N24+VLOOKUP($L24,'Voyage days'!$F$540:$H$613,3,FALSE),"") | BB24: =IF(BC24="","",TEXT(BC24,"dd")&"-"&TEXT(BD24,"dd mmm")) | BC24: =IFERROR($M24+VLOOKUP($L24,'Voyage days'!$F$448:$H$479,3,FALSE),"") | BD24: =IFERROR($N24+VLOOKUP($L24,'Voyage days'!$F$448:$H$479,3,FALSE),"") | BE24: =IF(BF24="","",TEXT(BF24,"dd")&"-"&TEXT(BG24,"dd mmm")) | BF24: =IFERROR($M24+VLOOKUP($L24,'Voyage days'!$F$620:$H$646,3,FALSE),"") | BG24: =IFERROR($N24+VLOOKUP($L24,'Voyage days'!$F$620:$H$646,3,FALSE),"") | BH24: =IF(BI24="","",TEXT(BI24,"dd")&"-"&TEXT(BL24,"dd mmm")) | BI24: =IFERROR($M24+VLOOKUP($L24,'Voyage days'!$F$702:$H$727,3,FALSE),"") | BJ24: =IF(BK24="","",TEXT(BK24,"dd")&"-"&TEXT(BL24,"dd mmm")) | BK24: =IFERROR($M24+VLOOKUP($L24,'Voyage days'!$F$807:$H$878,3,FALSE),"") | BL24: =IFERROR($N24+VLOOKUP($L24,'Voyage days'!$F$807:$H$878,3,FALSE),"") | BM24: =IFERROR($N24+VLOOKUP($L24,'Voyage days'!$F$807:$K$878,6,FALSE),"") | BN24: =if(L24="loads AG", IFERROR($M24+VLOOKUP($L24,'Voyage days'!$M$38:$O$38,3,FALSE),""),"") | BO24: =if(L24="loads USG", IFERROR($M24+VLOOKUP($L24,'Voyage days'!$L$203:$N$203,3,FALSE),""),"") -> 46183
A25: Maple Gas | B25: 43556 | C25: 82200 | I25: AGT | J25: =IF(W25="","NO AIS",IF((W25-M25-1)>0,"Update","")) | L25: Korea | M25: 46145 | N25: 46146 | P25: ETA 1st port Ulsan 30 Apr | R25: AGT 26 Mar Enterprise | S25: BR | T25: 46124 | U25: =IF(V25="","No AIS",VLOOKUP(V25,'Voyage days'!$A$3:$B$1480,2,FALSE)) -> Korea + 4 | V25: =IF(VLOOKUP(A25,'1) Kpler'!$E$2:$P$1000,8, FALSE)="","",VLOOKUP(A25,'1) Kpler'!$E$2:$P$1000,8, FALSE)) -> Ulsan | W25: =IF(VLOOKUP(A25,'1) Kpler'!$E$2:$P$1000,9,FALSE)="","",VLOOKUP(A25,'1) Kpler'!$E$2:$P$1000,9,FALSE)) -> 46142.042 | X25: =VLOOKUP(A25,'1) Kpler'!$E$2:$I$1000,4,FALSE) -> loaded | Y25: =AG25 -> 21-22 May | Z25: =AJ25 -> 06-07 Jun | AA25: =AM25 -> 13-14 Jun | AB25: =AP25 -> 01-02 Jun | AC25: =AS25 -> 07-08 Jun | AD25: =BB25 -> 10-11 May | AE25: =AY25 -> 11-12 May | AF25: =BJ25 -> 17-18 Jun | AG25: =IF(AH25="","",TEXT(AH25,"dd")&"-"&TEXT(AI25,"dd mmm")) -> 21-22 May | AH25: =IFERROR($M25+VLOOKUP($L25,'Voyage days'!$F$38:$H$89,3,FALSE),"") -> 46163 | AI25: =IFERROR(N25+VLOOKUP($L25,'Voyage days'!$F$38:$H$89,3,FALSE),"") -> 46164 | AJ25: =IF(AK25="","",TEXT(AK25,"dd")&"-"&TEXT(AL25,"dd mmm")) -> 06-07 Jun | AK25: =IFERROR($M25+VLOOKUP($L25,'Voyage days'!$F$94:$H$193,3,FALSE),"") -> 46179 | AL25: =IFERROR($N25+VLOOKUP($L25,'Voyage days'!$F$94:$H$193,3,FALSE),"") -> 46180 | AM25: =IF(AN25="","",TEXT(AN25,"dd")&"-"&TEXT(AO25,"dd mmm")) -> 13-14 Jun | AN25: =IFERROR($M25+VLOOKUP($L25,'Voyage days'!$F$203:$H$256,3,FALSE),"") -> 46186 | AO25: =IFERROR($N25+VLOOKUP($L25,'Voyage days'!$F$203:$H$256,3,FALSE),"") -> 46187 | AP25: =IF(AQ25="","",TEXT(AQ25,"dd")&"-"&TEXT(AR25,"dd mmm")) -> 01-02 Jun | AQ25: =IFERROR($M25+VLOOKUP($L25,'Voyage days'!$F$294:$H$377,3,FALSE),"") -> 46174 | AR25: =IFERROR($N25+VLOOKUP($L25,'Voyage days'!$F$294:$H$377,3,FALSE),"") -> 46175 | AS25: =IF(AT25="","",TEXT(AT25,"dd")&"-"&TEXT(AU25,"dd mmm")) -> 07-08 Jun | AT25: =IFERROR($M25+VLOOKUP($L25,'Voyage days'!$F$382:$H$446,3,FALSE),"") -> 46180 | AU25: =IFERROR($N25+VLOOKUP($L25,'Voyage days'!$F$382:$H$446,3,FALSE),"") -> 46181 | AV25: =IF(AW25="","",TEXT(AW25,"dd")&"-"&TEXT(AX25,"dd mmm")) -> 17-18 May | AW25: =IFERROR($M25+VLOOKUP($L25,'Voyage days'!$F$483:$H$538,3,FALSE),"") -> 46159 | AX25: =IFERROR($N25+VLOOKUP($L25,'Voyage days'!$F$483:$H$538,3,FALSE),"") -> 46160 | AY25: =IF(AZ25="","",TEXT(AZ25,"dd")&"-"&TEXT(BA25,"dd mmm")) -> 11-12 May | AZ25: =IFERROR($M25+VLOOKUP($L25,'Voyage days'!$F$540:$H$613,3,FALSE),"") -> 46153 | BA25: =IFERROR($N25+VLOOKUP($L25,'Voyage days'!$F$540:$H$613,3,FALSE),"") -> 46154 | BB25: =IF(BC25="","",TEXT(BC25,"dd")&"-"&TEXT(BD25,"dd mmm")) -> 10-11 May | BC25: =IFERROR($M25+VLOOKUP($L25,'Voyage days'!$F$448:$H$479,3,FALSE),"") -> 46152 | BD25: =IFERROR($N25+VLOOKUP($L25,'Voyage days'!$F$448:$H$479,3,FALSE),"") -> 46153 | BE25: =IF(BF25="","",TEXT(BF25,"dd")&"-"&TEXT(BG25,"dd mmm")) -> 14-15 May | BF25: =IFERROR($M25+VLOOKUP($L25,'Voyage days'!$F$620:$H$646,3,FALSE),"") -> 46156 | BG25: =IFERROR($N25+VLOOKUP($L25,'Voyage days'!$F$620:$H$646,3,FALSE),"") -> 46157 | BH25: =IF(BI25="","",TEXT(BI25,"dd")&"-"&TEXT(BL25,"dd mmm")) -> 11-18 Jun | BI25: =IFERROR($M25+VLOOKUP($L25,'Voyage days'!$F$702:$H$727,3,FALSE),"") -> 46153 | BJ25: =IF(BK25="","",TEXT(BK25,"dd")&"-"&TEXT(BL25,"dd mmm")) -> 17-18 Jun | BK25: =IFERROR($M25+VLOOKUP($L25,'Voyage days'!$F$807:$H$878,3,FALSE),"") -> 46190 | BL25: =IFERROR($N25+VLOOKUP($L25,'Voyage days'!$F$807:$H$878,3,FALSE),"") -> 46191 | BM25: =IFERROR($N25+VLOOKUP($L25,'Voyage days'!$F$807:$K$878,6,FALSE),"") -> 46165 | BN25: =if(L25="loads AG", IFERROR($M25+VLOOKUP($L25,'Voyage days'!$M$38:$O$38,3,FALSE),""),"") | BO25: =if(L25="loads USG", IFERROR($M25+VLOOKUP($L25,'Voyage days'!$L$203:$N$203,3,FALSE),""),"")
A26: Lupinus Planet | B26: 2022 | C26: 84000 | H26: DF | I26: AGT | J26: =IF(W26="","NO AIS",IF((W26-M26-1)>0,"Update","")) -> Update | L26: loads USG | M26: 46129 | N26: 46131 | P26: ETA USG 17 Apr via Cape | R26: AGT 17-18 Apr USG | S26: BR | T26: 46124 | U26: =IF(V26="","No AIS",VLOOKUP(V26,'Voyage days'!$A$3:$B$1480,2,FALSE)) -> USG | V26: =IF(VLOOKUP(A26,'1) Kpler'!$E$2:$P$1000,8, FALSE)="","",VLOOKUP(A26,'1) Kpler'!$E$2:$P$1000,8, FALSE)) -> Houston | W26: =IF(VLOOKUP(A26,'1) Kpler'!$E$2:$P$1000,9,FALSE)="","",VLOOKUP(A26,'1) Kpler'!$E$2:$P$1000,9,FALSE)) -> 46131.833 | X26: =VLOOKUP(A26,'1) Kpler'!$E$2:$I$1000,4,FALSE) -> ballast | Y26: =AG26 | Z26: =AJ26 -> 17-19 Apr | AA26: =AM26 -> 17-19 Apr | AB26: =AP26 | AC26: =AS26 -> 07-09 May | AD26: =BB26 | AE26: =AY26 | AF26: =BJ26 | AG26: =IF(AH26="","",TEXT(AH26,"dd")&"-"&TEXT(AI26,"dd mmm")) | AH26: =IFERROR($M26+VLOOKUP($L26,'Voyage days'!$F$38:$H$89,3,FALSE),"") | AI26: =IFERROR(N26+VLOOKUP($L26,'Voyage days'!$F$38:$H$89,3,FALSE),"") | AJ26: =IF(AK26="","",TEXT(AK26,"dd")&"-"&TEXT(AL26,"dd mmm")) -> 17-19 Apr | AK26: =IFERROR($M26+VLOOKUP($L26,'Voyage days'!$F$94:$H$193,3,FALSE),"") -> 46129 | AL26: =IFERROR($N26+VLOOKUP($L26,'Voyage days'!$F$94:$H$193,3,FALSE),"") -> 46131 | AM26: =IF(AN26="","",TEXT(AN26,"dd")&"-"&TEXT(AO26,"dd mmm")) -> 17-19 Apr | AN26: =IFERROR($M26+VLOOKUP($L26,'Voyage days'!$F$203:$H$256,3,FALSE),"") -> 46129 | AO26: =IFERROR($N26+VLOOKUP($L26,'Voyage days'!$F$203:$H$256,3,FALSE),"") -> 46131 | AP26: =IF(AQ26="","",TEXT(AQ26,"dd")&"-"&TEXT(AR26,"dd mmm")) | AQ26: =IFERROR($M26+VLOOKUP($L26,'Voyage days'!$F$294:$H$377,3,FALSE),"") | AR26: =IFERROR($N26+VLOOKUP($L26,'Voyage days'!$F$294:$H$377,3,FALSE),"") | AS26: =IF(AT26="","",TEXT(AT26,"dd")&"-"&TEXT(AU26,"dd mmm")) -> 07-09 May | AT26: =IFERROR($M26+VLOOKUP($L26,'Voyage days'!$F$382:$H$446,3,FALSE),"") -> 46149 | AU26: =IFERROR($N26+VLOOKUP($L26,'Voyage days'!$F$382:$H$446,3,FALSE),"") -> 46151 | AV26: =IF(AW26="","",TEXT(AW26,"dd")&"-"&TEXT(AX26,"dd mmm")) | AW26: =IFERROR($M26+VLOOKUP($L26,'Voyage days'!$F$483:$H$538,3,FALSE),"") | AX26: =IFERROR($N26+VLOOKUP($L26,'Voyage days'!$F$483:$H$538,3,FALSE),"") | AY26: =IF(AZ26="","",TEXT(AZ26,"dd")&"-"&TEXT(BA26,"dd mmm")) | AZ26: =IFERROR($M26+VLOOKUP($L26,'Voyage days'!$F$540:$H$613,3,FALSE),"") | BA26: =IFERROR($N26+VLOOKUP($L26,'Voyage days'!$F$540:$H$613,3,FALSE),"") | BB26: =IF(BC26="","",TEXT(BC26,"dd")&"-"&TEXT(BD26,"dd mmm")) | BC26: =IFERROR($M26+VLOOKUP($L26,'Voyage days'!$F$448:$H$479,3,FALSE),"") | BD26: =IFERROR($N26+VLOOKUP($L26,'Voyage days'!$F$448:$H$479,3,FALSE),"") | BE26: =IF(BF26="","",TEXT(BF26,"dd")&"-"&TEXT(BG26,"dd mmm")) | BF26: =IFERROR($M26+VLOOKUP($L26,'Voyage days'!$F$620:$H$646,3,FALSE),"") | BG26: =IFERROR($N26+VLOOKUP($L26,'Voyage days'!$F$620:$H$646,3,FALSE),"") | BH26: =IF(BI26="","",TEXT(BI26,"dd")&"-"&TEXT(BL26,"dd mmm")) | BI26: =IFERROR($M26+VLOOKUP($L26,'Voyage days'!$F$702:$H$727,3,FALSE),"") | BJ26: =IF(BK26="","",TEXT(BK26,"dd")&"-"&TEXT(BL26,"dd mmm")) | BK26: =IFERROR($M26+VLOOKUP($L26,'Voyage days'!$F$807:$H$878,3,FALSE),"") | BL26: =IFERROR($N26+VLOOKUP($L26,'Voyage days'!$F$807:$H$878,3,FALSE),"") | BM26: =IFERROR($N26+VLOOKUP($L26,'Voyage days'!$F$807:$K$878,6,FALSE),"") | BN26: =if(L26="loads AG", IFERROR($M26+VLOOKUP($L26,'Voyage days'!$M$38:$O$38,3,FALSE),""),"") | BO26: =if(L26="loads USG", IFERROR($M26+VLOOKUP($L26,'Voyage days'!$L$203:$N$203,3,FALSE),""),"") -> 46161
A27: Zante Gas | B27: 2025 | C27: 88000 | E27: C | I27: AGT | J27: =IF(W27="","NO AIS",IF((W27-M27-1)>0,"Update","")) | L27: loads USG | M27: 46150 | N27: 46151 | P27: ETA Balboa 29 Apr | R27: Exxon 08-09 May USG | S27: BR | T27: 46124 | U27: =IF(V27="","No AIS",VLOOKUP(V27,'Voyage days'!$A$3:$B$1480,2,FALSE)) -> USG | V27: =IF(VLOOKUP(A27,'1) Kpler'!$E$2:$P$1000,8, FALSE)="","",VLOOKUP(A27,'1) Kpler'!$E$2:$P$1000,8, FALSE)) -> PADD 3 | W27: =IF(VLOOKUP(A27,'1) Kpler'!$E$2:$P$1000,9,FALSE)="","",VLOOKUP(A27,'1) Kpler'!$E$2:$P$1000,9,FALSE)) -> 46150 | X27: =VLOOKUP(A27,'1) Kpler'!$E$2:$I$1000,4,FALSE) -> ballast | Y27: =AG27 | Z27: =AJ27 -> 08-09 May | AA27: =AM27 -> 08-09 May | AB27: =AP27 | AC27: =AS27 -> 28-29 May | AD27: =BB27 | AE27: =AY27 | AF27: =BJ27 | AG27: =IF(AH27="","",TEXT(AH27,"dd")&"-"&TEXT(AI27,"dd mmm")) | AH27: =IFERROR($M27+VLOOKUP($L27,'Voyage days'!$F$38:$H$89,3,FALSE),"") | AI27: =IFERROR(N27+VLOOKUP($L27,'Voyage days'!$F$38:$H$89,3,FALSE),"") | AJ27: =IF(AK27="","",TEXT(AK27,"dd")&"-"&TEXT(AL27,"dd mmm")) -> 08-09 May | AK27: =IFERROR($M27+VLOOKUP($L27,'Voyage days'!$F$94:$H$193,3,FALSE),"") -> 46150 | AL27: =IFERROR($N27+VLOOKUP($L27,'Voyage days'!$F$94:$H$193,3,FALSE),"") -> 46151 | AM27: =IF(AN27="","",TEXT(AN27,"dd")&"-"&TEXT(AO27,"dd mmm")) -> 08-09 May | AN27: =IFERROR($M27+VLOOKUP($L27,'Voyage days'!$F$203:$H$256,3,FALSE),"") -> 46150 | AO27: =IFERROR($N27+VLOOKUP($L27,'Voyage days'!$F$203:$H$256,3,FALSE),"") -> 46151 | AP27: =IF(AQ27="","",TEXT(AQ27,"dd")&"-"&TEXT(AR27,"dd mmm")) | AQ27: =IFERROR($M27+VLOOKUP($L27,'Voyage days'!$F$294:$H$377,3,FALSE),"") | AR27: =IFERROR($N27+VLOOKUP($L27,'Voyage days'!$F$294:$H$377,3,FALSE),"") | AS27: =IF(AT27="","",TEXT(AT27,"dd")&"-"&TEXT(AU27,"dd mmm")) -> 28-29 May | AT27: =IFERROR($M27+VLOOKUP($L27,'Voyage days'!$F$382:$H$446,3,FALSE),"") -> 46170 | AU27: =IFERROR($N27+VLOOKUP($L27,'Voyage days'!$F$382:$H$446,3,FALSE),"") -> 46171 | AV27: =IF(AW27="","",TEXT(AW27,"dd")&"-"&TEXT(AX27,"dd mmm")) | AW27: =IFERROR($M27+VLOOKUP($L27,'Voyage days'!$F$483:$H$538,3,FALSE),"") | AX27: =IFERROR($N27+VLOOKUP($L27,'Voyage days'!$F$483:$H$538,3,FALSE),"") | AY27: =IF(AZ27="","",TEXT(AZ27,"dd")&"-"&TEXT(BA27,"dd mmm")) | AZ27: =IFERROR($M27+VLOOKUP($L27,'Voyage days'!$F$540:$H$613,3,FALSE),"") | BA27: =IFERROR($N27+VLOOKUP($L27,'Voyage days'!$F$540:$H$613,3,FALSE),"") | BB27: =IF(BC27="","",TEXT(BC27,"dd")&"-"&TEXT(BD27,"dd mmm")) | BC27: =IFERROR($M27+VLOOKUP($L27,'Voyage days'!$F$448:$H$479,3,FALSE),"") | BD27: =IFERROR($N27+VLOOKUP($L27,'Voyage days'!$F$448:$H$479,3,FALSE),"") | BE27: =IF(BF27="","",TEXT(BF27,"dd")&"-"&TEXT(BG27,"dd mmm")) | BF27: =IFERROR($M27+VLOOKUP($L27,'Voyage days'!$F$620:$H$646,3,FALSE),"") | BG27: =IFERROR($N27+VLOOKUP($L27,'Voyage days'!$F$620:$H$646,3,FALSE),"") | BH27: =IF(BI27="","",TEXT(BI27,"dd")&"-"&TEXT(BL27,"dd mmm")) | BI27: =IFERROR($M27+VLOOKUP($L27,'Voyage days'!$F$702:$H$727,3,FALSE),"") | BJ27: =IF(BK27="","",TEXT(BK27,"dd")&"-"&TEXT(BL27,"dd mmm")) | BK27: =IFERROR($M27+VLOOKUP($L27,'Voyage days'!$F$807:$H$878,3,FALSE),"") | BL27: =IFERROR($N27+VLOOKUP($L27,'Voyage days'!$F$807:$H$878,3,FALSE),"") | BM27: =IFERROR($N27+VLOOKUP($L27,'Voyage days'!$F$807:$K$878,6,FALSE),"") | BN27: =if(L27="loads AG", IFERROR($M27+VLOOKUP($L27,'Voyage days'!$M$38:$O$38,3,FALSE),""),"") | BO27: =if(L27="loads USG", IFERROR($M27+VLOOKUP($L27,'Voyage days'!$L$203:$N$203,3,FALSE),""),"") -> 46182
A28: Ayame | B28: 40298 | C28: 83270 | I28: ATC | J28: =IF(W28="","NO AIS",IF((W28-M28-1)>0,"Update","")) -> NO AIS | L28: Turkey | M28: 46125 | N28: 46126 | O28: eu | P28: @ Dortyol 07 Apr | R28: ATC 01-02 Apr Yanbu | S28: BR | T28: 46124 | U28: =IF(V28="","No AIS",VLOOKUP(V28,'Voyage days'!$A$3:$B$1480,2,FALSE)) -> No AIS | V28: =IF(VLOOKUP(A28,'1) Kpler'!$E$2:$P$1000,8, FALSE)="","",VLOOKUP(A28,'1) Kpler'!$E$2:$P$1000,8, FALSE)) | W28: =IF(VLOOKUP(A28,'1) Kpler'!$E$2:$P$1000,9,FALSE)="","",VLOOKUP(A28,'1) Kpler'!$E$2:$P$1000,9,FALSE)) | X28: =VLOOKUP(A28,'1) Kpler'!$E$2:$I$1000,4,FALSE) -> ballast | Y28: =AG28 -> 23-24 Apr | Z28: =AJ28 -> 27-28 Apr | AA28: =AM28 -> 03-04 May | AB28: =AP28 -> 28-29 Apr | AC28: =AS28 -> 18-19 Apr | AD28: =BB28 | AE28: =AY28 | AF28: =BJ28 -> 17-18 Apr | AG28: =IF(AH28="","",TEXT(AH28,"dd")&"-"&TEXT(AI28,"dd mmm")) -> 23-24 Apr | AH28: =IFERROR($M28+VLOOKUP($L28,'Voyage days'!$F$38:$H$89,3,FALSE),"") -> 46135 | AI28: =IFERROR(N28+VLOOKUP($L28,'Voyage days'!$F$38:$H$89,3,FALSE),"") -> 46136 | AJ28: =IF(AK28="","",TEXT(AK28,"dd")&"-"&TEXT(AL28,"dd mmm")) -> 27-28 Apr | AK28: =IFERROR($M28+VLOOKUP($L28,'Voyage days'!$F$94:$H$193,3,FALSE),"") -> 46139 | AL28: =IFERROR($N28+VLOOKUP($L28,'Voyage days'!$F$94:$H$193,3,FALSE),"") -> 46140 | AM28: =IF(AN28="","",TEXT(AN28,"dd")&"-"&TEXT(AO28,"dd mmm")) -> 03-04 May | AN28: =IFERROR($M28+VLOOKUP($L28,'Voyage days'!$F$203:$H$256,3,FALSE),"") -> 46145 | AO28: =IFERROR($N28+VLOOKUP($L28,'Voyage days'!$F$203:$H$256,3,FALSE),"") -> 46146 | AP28: =IF(AQ28="","",TEXT(AQ28,"dd")&"-"&TEXT(AR28,"dd mmm")) -> 28-29 Apr | AQ28: =IFERROR($M28+VLOOKUP($L28,'Voyage days'!$F$294:$H$377,3,FALSE),"") -> 46140 | AR28: =IFERROR($N28+VLOOKUP($L28,'Voyage days'!$F$294:$H$377,3,FALSE),"") -> 46141 | AS28: =IF(AT28="","",TEXT(AT28,"dd")&"-"&TEXT(AU28,"dd mmm")) -> 18-19 Apr | AT28: =IFERROR($M28+VLOOKUP($L28,'Voyage days'!$F$382:$H$446,3,FALSE),"") -> 46130 | AU28: =IFERROR($N28+VLOOKUP($L28,'Voyage days'!$F$382:$H$446,3,FALSE),"") -> 46131 | AV28: =IF(AW28="","",TEXT(AW28,"dd")&"-"&TEXT(AX28,"dd mmm")) | AW28: =IFERROR($M28+VLOOKUP($L28,'Voyage days'!$F$483:$H$538,3,FALSE),"") | AX28: =IFERROR($N28+VLOOKUP($L28,'Voyage days'!$F$483:$H$538,3,FALSE),"") | AY28: =IF(AZ28="","",TEXT(AZ28,"dd")&"-"&TEXT(BA28,"dd mmm")) | AZ28: =IFERROR($M28+VLOOKUP($L28,'Voyage days'!$F$540:$H$613,3,FALSE),"") | BA28: =IFERROR($N28+VLOOKUP($L28,'Voyage days'!$F$540:$H$613,3,FALSE),"") | BB28: =IF(BC28="","",TEXT(BC28,"dd")&"-"&TEXT(BD28,"dd mmm")) | BC28: =IFERROR($M28+VLOOKUP($L28,'Voyage days'!$F$448:$H$479,3,FALSE),"") | BD28: =IFERROR($N28+VLOOKUP($L28,'Voyage days'!$F$448:$H$479,3,FALSE),"") | BE28: =IF(BF28="","",TEXT(BF28,"dd")&"-"&TEXT(BG28,"dd mmm")) | BF28: =IFERROR($M28+VLOOKUP($L28,'Voyage days'!$F$620:$H$646,3,FALSE),"") | BG28: =IFERROR($N28+VLOOKUP($L28,'Voyage days'!$F$620:$H$646,3,FALSE),"") | BH28: =IF(BI28="","",TEXT(BI28,"dd")&"-"&TEXT(BL28,"dd mmm")) | BI28: =IFERROR($M28+VLOOKUP($L28,'Voyage days'!$F$702:$H$727,3,FALSE),"") | BJ28: =IF(BK28="","",TEXT(BK28,"dd")&"-"&TEXT(BL28,"dd mmm")) -> 17-18 Apr | BK28: =IFERROR($M28+VLOOKUP($L28,'Voyage days'!$F$807:$H$878,3,FALSE),"") -> 46129 | BL28: =IFERROR($N28+VLOOKUP($L28,'Voyage days'!$F$807:$H$878,3,FALSE),"") -> 46130 | BM28: =IFERROR($N28+VLOOKUP($L28,'Voyage days'!$F$807:$K$878,6,FALSE),"") -> 46126 | BN28: =if(L28="loads AG", IFERROR($M28+VLOOKUP($L28,'Voyage days'!$M$38:$O$38,3,FALSE),""),"") | BO28: =if(L28="loads USG", IFERROR($M28+VLOOKUP($L28,'Voyage days'!$L$203:$N$203,3,FALSE),""),"")
A29: BW Tucana | B29: 42479 | C29: 84113 | H29: DF | I29: BW > ATC | J29: =IF(W29="","NO AIS",IF((W29-M29-1)>0,"Update","")) -> Update | L29: loads USG | M29: 46124 | N29: 46125 | P29: @ Houston anchorage 10 Apr, waiting to berth | R29: ATC 10-11 Apr USG | S29: BR | T29: 46124 | U29: =IF(V29="","No AIS",VLOOKUP(V29,'Voyage days'!$A$3:$B$1480,2,FALSE)) -> Panama | V29: =IF(VLOOKUP(A29,'1) Kpler'!$E$2:$P$1000,8, FALSE)="","",VLOOKUP(A29,'1) Kpler'!$E$2:$P$1000,8, FALSE)) -> Cristobal Light. | W29: =IF(VLOOKUP(A29,'1) Kpler'!$E$2:$P$1000,9,FALSE)="","",VLOOKUP(A29,'1) Kpler'!$E$2:$P$1000,9,FALSE)) -> 46134.25 | X29: =VLOOKUP(A29,'1) Kpler'!$E$2:$I$1000,4,FALSE) -> loaded | Y29: =AG29 | Z29: =AJ29 -> 12-13 Apr | AA29: =AM29 -> 12-13 Apr | AB29: =AP29 | AC29: =AS29 -> 02-03 May | AD29: =BB29 | AE29: =AY29 | AF29: =BJ29 | AG29: =IF(AH29="","",TEXT(AH29,"dd")&"-"&TEXT(AI29,"dd mmm")) | AH29: =IFERROR($M29+VLOOKUP($L29,'Voyage days'!$F$38:$H$89,3,FALSE),"") | AI29: =IFERROR(N29+VLOOKUP($L29,'Voyage days'!$F$38:$H$89,3,FALSE),"") | AJ29: =IF(AK29="","",TEXT(AK29,"dd")&"-"&TEXT(AL29,"dd mmm")) -> 12-13 Apr | AK29: =IFERROR($M29+VLOOKUP($L29,'Voyage days'!$F$94:$H$193,3,FALSE),"") -> 46124 | AL29: =IFERROR($N29+VLOOKUP($L29,'Voyage days'!$F$94:$H$193,3,FALSE),"") -> 46125 | AM29: =IF(AN29="","",TEXT(AN29,"dd")&"-"&TEXT(AO29,"dd mmm")) -> 12-13 Apr | AN29: =IFERROR($M29+VLOOKUP($L29,'Voyage days'!$F$203:$H$256,3,FALSE),"") -> 46124 | AO29: =IFERROR($N29+VLOOKUP($L29,'Voyage days'!$F$203:$H$256,3,FALSE),"") -> 46125 | AP29: =IF(AQ29="","",TEXT(AQ29,"dd")&"-"&TEXT(AR29,"dd mmm")) | AQ29: =IFERROR($M29+VLOOKUP($L29,'Voyage days'!$F$294:$H$377,3,FALSE),"") | AR29: =IFERROR($N29+VLOOKUP($L29,'Voyage days'!$F$294:$H$377,3,FALSE),"") | AS29: =IF(AT29="","",TEXT(AT29,"dd")&"-"&TEXT(AU29,"dd mmm")) -> 02-03 May | AT29: =IFERROR($M29+VLOOKUP($L29,'Voyage days'!$F$382:$H$446,3,FALSE),"") -> 46144 | AU29: =IFERROR($N29+VLOOKUP($L29,'Voyage days'!$F$382:$H$446,3,FALSE),"") -> 46145 | AV29: =IF(AW29="","",TEXT(AW29,"dd")&"-"&TEXT(AX29,"dd mmm")) | AW29: =IFERROR($M29+VLOOKUP($L29,'Voyage days'!$F$483:$H$538,3,FALSE),"") | AX29: =IFERROR($N29+VLOOKUP($L29,'Voyage days'!$F$483:$H$538,3,FALSE),"") | AY29: =IF(AZ29="","",TEXT(AZ29,"dd")&"-"&TEXT(BA29,"dd mmm")) | AZ29: =IFERROR($M29+VLOOKUP($L29,'Voyage days'!$F$540:$H$613,3,FALSE),"") | BA29: =IFERROR($N29+VLOOKUP($L29,'Voyage days'!$F$540:$H$613,3,FALSE),"") | BB29: =IF(BC29="","",TEXT(BC29,"dd")&"-"&TEXT(BD29,"dd mmm")) | BC29: =IFERROR($M29+VLOOKUP($L29,'Voyage days'!$F$448:$H$479,3,FALSE),"") | BD29: =IFERROR($N29+VLOOKUP($L29,'Voyage days'!$F$448:$H$479,3,FALSE),"") | BE29: =IF(BF29="","",TEXT(BF29,"dd")&"-"&TEXT(BG29,"dd mmm")) | BF29: =IFERROR($M29+VLOOKUP($L29,'Voyage days'!$F$620:$H$646,3,FALSE),"") | BG29: =IFERROR($N29+VLOOKUP($L29,'Voyage days'!$F$620:$H$646,3,FALSE),"") | BH29: =IF(BI29="","",TEXT(BI29,"dd")&"-"&TEXT(BL29,"dd mmm")) | BI29: =IFERROR($M29+VLOOKUP($L29,'Voyage days'!$F$702:$H$727,3,FALSE),"") | BJ29: =IF(BK29="","",TEXT(BK29,"dd")&"-"&TEXT(BL29,"dd mmm")) | BK29: =IFERROR($M29+VLOOKUP($L29,'Voyage days'!$F$807:$H$878,3,FALSE),"") | BL29: =IFERROR($N29+VLOOKUP($L29,'Voyage days'!$F$807:$H$878,3,FALSE),"") | BM29: =IFERROR($N29+VLOOKUP($L29,'Voyage days'!$F$807:$K$878,6,FALSE),"") | BN29: =if(L29="loads AG", IFERROR($M29+VLOOKUP($L29,'Voyage days'!$M$38:$O$38,3,FALSE),""),"") | BO29: =if(L29="loads USG", IFERROR($M29+VLOOKUP($L29,'Voyage days'!$L$203:$N$203,3,FALSE),""),"") -> 46156
A30: Eiger Explorer | B30: 43617 | C30: 80000 | H30: S | I30: ATC | J30: =IF(W30="","NO AIS",IF((W30-M30-1)>0,"Update","")) | L30: loads USG | M30: 46135 | N30: 46136 | O30: eu | P30: ETA Nederland 22 Apr | Q30: c3 / c4 in deck tanks | R30: Naftomar 23-24 Apr USG | S30: BR | T30: 46124 | U30: =IF(V30="","No AIS",VLOOKUP(V30,'Voyage days'!$A$3:$B$1480,2,FALSE)) -> USG | V30: =IF(VLOOKUP(A30,'1) Kpler'!$E$2:$P$1000,8, FALSE)="","",VLOOKUP(A30,'1) Kpler'!$E$2:$P$1000,8, FALSE)) -> Energy Transfer Nederland | W30: =IF(VLOOKUP(A30,'1) Kpler'!$E$2:$P$1000,9,FALSE)="","",VLOOKUP(A30,'1) Kpler'!$E$2:$P$1000,9,FALSE)) -> 46133.833 | X30: =VLOOKUP(A30,'1) Kpler'!$E$2:$I$1000,4,FALSE) -> ballast | Y30: =AG30 | Z30: =AJ30 -> 23-24 Apr | AA30: =AM30 -> 23-24 Apr | AB30: =AP30 | AC30: =AS30 -> 13-14 May | AD30: =BB30 | AE30: =AY30 | AF30: =BJ30 | AG30: =IF(AH30="","",TEXT(AH30,"dd")&"-"&TEXT(AI30,"dd mmm")) | AH30: =IFERROR($M30+VLOOKUP($L30,'Voyage days'!$F$38:$H$89,3,FALSE),"") | AI30: =IFERROR(N30+VLOOKUP($L30,'Voyage days'!$F$38:$H$89,3,FALSE),"") | AJ30: =IF(AK30="","",TEXT(AK30,"dd")&"-"&TEXT(AL30,"dd mmm")) -> 23-24 Apr | AK30: =IFERROR($M30+VLOOKUP($L30,'Voyage days'!$F$94:$H$193,3,FALSE),"") -> 46135 | AL30: =IFERROR($N30+VLOOKUP($L30,'Voyage days'!$F$94:$H$193,3,FALSE),"") -> 46136 | AM30: =IF(AN30="","",TEXT(AN30,"dd")&"-"&TEXT(AO30,"dd mmm")) -> 23-24 Apr | AN30: =IFERROR($M30+VLOOKUP($L30,'Voyage days'!$F$203:$H$256,3,FALSE),"") -> 46135 | AO30: =IFERROR($N30+VLOOKUP($L30,'Voyage days'!$F$203:$H$256,3,FALSE),"") -> 46136 | AP30: =IF(AQ30="","",TEXT(AQ30,"dd")&"-"&TEXT(AR30,"dd mmm")) | AQ30: =IFERROR($M30+VLOOKUP($L30,'Voyage days'!$F$294:$H$377,3,FALSE),"") | AR30: =IFERROR($N30+VLOOKUP($L30,'Voyage days'!$F$294:$H$377,3,FALSE),"") | AS30: =IF(AT30="","",TEXT(AT30,"dd")&"-"&TEXT(AU30,"dd mmm")) -> 13-14 May | AT30: =IFERROR($M30+VLOOKUP($L30,'Voyage days'!$F$382:$H$446,3,FALSE),"") -> 46155 | AU30: =IFERROR($N30+VLOOKUP($L30,'Voyage days'!$F$382:$H$446,3,FALSE),"") -> 46156 | AV30: =IF(AW30="","",TEXT(AW30,"dd")&"-"&TEXT(AX30,"dd mmm")) | AW30: =IFERROR($M30+VLOOKUP($L30,'Voyage days'!$F$483:$H$538,3,FALSE),"") | AX30: =IFERROR($N30+VLOOKUP($L30,'Voyage days'!$F$483:$H$538,3,FALSE),"") | AY30: =IF(AZ30="","",TEXT(AZ30,"dd")&"-"&TEXT(BA30,"dd mmm")) | AZ30: =IFERROR($M30+VLOOKUP($L30,'Voyage days'!$F$540:$H$613,3,FALSE),"") | BA30: =IFERROR($N30+VLOOKUP($L30,'Voyage days'!$F$540:$H$613,3,FALSE),"") | BB30: =IF(BC30="","",TEXT(BC30,"dd")&"-"&TEXT(BD30,"dd mmm")) | BC30: =IFERROR($M30+VLOOKUP($L30,'Voyage days'!$F$448:$H$479,3,FALSE),"") | BD30: =IFERROR($N30+VLOOKUP($L30,'Voyage days'!$F$448:$H$479,3,FALSE),"") | BE30: =IF(BF30="","",TEXT(BF30,"dd")&"-"&TEXT(BG30,"dd mmm")) | BF30: =IFERROR($M30+VLOOKUP($L30,'Voyage days'!$F$620:$H$646,3,FALSE),"") | BG30: =IFERROR($N30+VLOOKUP($L30,'Voyage days'!$F$620:$H$646,3,FALSE),"") | BH30: =IF(BI30="","",TEXT(BI30,"dd")&"-"&TEXT(BL30,"dd mmm")) | BI30: =IFERROR($M30+VLOOKUP($L30,'Voyage days'!$F$702:$H$727,3,FALSE),"") | BJ30: =IF(BK30="","",TEXT(BK30,"dd")&"-"&TEXT(BL30,"dd mmm")) | BK30: =IFERROR($M30+VLOOKUP($L30,'Voyage days'!$F$807:$H$878,3,FALSE),"") | BL30: =IFERROR($N30+VLOOKUP($L30,'Voyage days'!$F$807:$H$878,3,FALSE),"") | BM30: =IFERROR($N30+VLOOKUP($L30,'Voyage days'!$F$807:$K$878,6,FALSE),"") | BN30: =if(L30="loads AG", IFERROR($M30+VLOOKUP($L30,'Voyage days'!$M$38:$O$38,3,FALSE),""),"") | BO30: =if(L30="loads USG", IFERROR($M30+VLOOKUP($L30,'Voyage days'!$L$203:$N$203,3,FALSE),""),"") -> 46167
A31: Gas Libra | B31: 2018 | C31: 84196 | E31: C | G31: DT | H31: DF | I31: ATC | J31: =IF(W31="","NO AIS",IF((W31-M31-1)>0,"Update","")) -> Update | L31: loads USG | M31: 46125 | N31: 46126 | O31: eu | P31: @ Houston anchorage 08 Apr, waiting to berth | R31: Dow 10-11 Apr USG | S31: BR | T31: 46124 | U31: =IF(V31="","No AIS",VLOOKUP(V31,'Voyage days'!$A$3:$B$1480,2,FALSE)) -> Eu + 4 | V31: =IF(VLOOKUP(A31,'1) Kpler'!$E$2:$P$1000,8, FALSE)="","",VLOOKUP(A31,'1) Kpler'!$E$2:$P$1000,8, FALSE)) -> Terneuzen | W31: =IF(VLOOKUP(A31,'1) Kpler'!$E$2:$P$1000,9,FALSE)="","",VLOOKUP(A31,'1) Kpler'!$E$2:$P$1000,9,FALSE)) -> 46142.114 | X31: =VLOOKUP(A31,'1) Kpler'!$E$2:$I$1000,4,FALSE) -> loaded | Y31: =AG31 | Z31: =AJ31 -> 13-14 Apr | AA31: =AM31 -> 13-14 Apr | AB31: =AP31 | AC31: =AS31 -> 03-04 May | AD31: =BB31 | AE31: =AY31 | AF31: =BJ31 | AG31: =IF(AH31="","",TEXT(AH31,"dd")&"-"&TEXT(AI31,"dd mmm")) | AH31: =IFERROR($M31+VLOOKUP($L31,'Voyage days'!$F$38:$H$89,3,FALSE),"") | AI31: =IFERROR(N31+VLOOKUP($L31,'Voyage days'!$F$38:$H$89,3,FALSE),"") | AJ31: =IF(AK31="","",TEXT(AK31,"dd")&"-"&TEXT(AL31,"dd mmm")) -> 13-14 Apr | AK31: =IFERROR($M31+VLOOKUP($L31,'Voyage days'!$F$94:$H$193,3,FALSE),"") -> 46125 | AL31: =IFERROR($N31+VLOOKUP($L31,'Voyage days'!$F$94:$H$193,3,FALSE),"") -> 46126 | AM31: =IF(AN31="","",TEXT(AN31,"dd")&"-"&TEXT(AO31,"dd mmm")) -> 13-14 Apr | AN31: =IFERROR($M31+VLOOKUP($L31,'Voyage days'!$F$203:$H$256,3,FALSE),"") -> 46125 | AO31: =IFERROR($N31+VLOOKUP($L31,'Voyage days'!$F$203:$H$256,3,FALSE),"") -> 46126 | AP31: =IF(AQ31="","",TEXT(AQ31,"dd")&"-"&TEXT(AR31,"dd mmm")) | AQ31: =IFERROR($M31+VLOOKUP($L31,'Voyage days'!$F$294:$H$377,3,FALSE),"") | AR31: =IFERROR($N31+VLOOKUP($L31,'Voyage days'!$F$294:$H$377,3,FALSE),"") | AS31: =IF(AT31="","",TEXT(AT31,"dd")&"-"&TEXT(AU31,"dd mmm")) -> 03-04 May | AT31: =IFERROR($M31+VLOOKUP($L31,'Voyage days'!$F$382:$H$446,3,FALSE),"") -> 46145 | AU31: =IFERROR($N31+VLOOKUP($L31,'Voyage days'!$F$382:$H$446,3,FALSE),"") -> 46146 | AV31: =IF(AW31="","",TEXT(AW31,"dd")&"-"&TEXT(AX31,"dd mmm")) | AW31: =IFERROR($M31+VLOOKUP($L31,'Voyage days'!$F$483:$H$538,3,FALSE),"") | AX31: =IFERROR($N31+VLOOKUP($L31,'Voyage days'!$F$483:$H$538,3,FALSE),"") | AY31: =IF(AZ31="","",TEXT(AZ31,"dd")&"-"&TEXT(BA31,"dd mmm")) | AZ31: =IFERROR($M31+VLOOKUP($L31,'Voyage days'!$F$540:$H$613,3,FALSE),"") | BA31: =IFERROR($N31+VLOOKUP($L31,'Voyage days'!$F$540:$H$613,3,FALSE),"") | BB31: =IF(BC31="","",TEXT(BC31,"dd")&"-"&TEXT(BD31,"dd mmm")) | BC31: =IFERROR($M31+VLOOKUP($L31,'Voyage days'!$F$448:$H$479,3,FALSE),"") | BD31: =IFERROR($N31+VLOOKUP($L31,'Voyage days'!$F$448:$H$479,3,FALSE),"") | BE31: =IF(BF31="","",TEXT(BF31,"dd")&"-"&TEXT(BG31,"dd mmm")) | BF31: =IFERROR($M31+VLOOKUP($L31,'Voyage days'!$F$620:$H$646,3,FALSE),"") | BG31: =IFERROR($N31+VLOOKUP($L31,'Voyage days'!$F$620:$H$646,3,FALSE),"") | BH31: =IF(BI31="","",TEXT(BI31,"dd")&"-"&TEXT(BL31,"dd mmm")) | BI31: =IFERROR($M31+VLOOKUP($L31,'Voyage days'!$F$702:$H$727,3,FALSE),"") | BJ31: =IF(BK31="","",TEXT(BK31,"dd")&"-"&TEXT(BL31,"dd mmm")) | BK31: =IFERROR($M31+VLOOKUP($L31,'Voyage days'!$F$807:$H$878,3,FALSE),"") | BL31: =IFERROR($N31+VLOOKUP($L31,'Voyage days'!$F$807:$H$878,3,FALSE),"") | BM31: =IFERROR($N31+VLOOKUP($L31,'Voyage days'!$F$807:$K$878,6,FALSE),"") | BN31: =if(L31="loads AG", IFERROR($M31+VLOOKUP($L31,'Voyage days'!$M$38:$O$38,3,FALSE),""),"") | BO31: =if(L31="loads USG", IFERROR($M31+VLOOKUP($L31,'Voyage days'!$L$203:$N$203,3,FALSE),""),"") -> 46157
A32: Hellas Sparta | B32: 2016 | C32: 84000 | I32: ATC > AGT | J32: =IF(W32="","NO AIS",IF((W32-M32-1)>0,"Update","")) | L32: loads USG | M32: 46137 | N32: 46138 | P32: ex DD, ETA USG 22 Apr via Cape | R32: Geogas 25-26 Apr USG | S32: BR | T32: 46124 | U32: =IF(V32="","No AIS",VLOOKUP(V32,'Voyage days'!$A$3:$B$1480,2,FALSE)) -> USG | V32: =IF(VLOOKUP(A32,'1) Kpler'!$E$2:$P$1000,8, FALSE)="","",VLOOKUP(A32,'1) Kpler'!$E$2:$P$1000,8, FALSE)) -> Houston | W32: =IF(VLOOKUP(A32,'1) Kpler'!$E$2:$P$1000,9,FALSE)="","",VLOOKUP(A32,'1) Kpler'!$E$2:$P$1000,9,FALSE)) -> 46136.708 | X32: =VLOOKUP(A32,'1) Kpler'!$E$2:$I$1000,4,FALSE) -> ballast | Y32: =AG32 | Z32: =AJ32 -> 25-26 Apr | AA32: =AM32 -> 25-26 Apr | AB32: =AP32 | AC32: =AS32 -> 15-16 May | AD32: =BB32 | AE32: =AY32 | AF32: =BJ32 | AG32: =IF(AH32="","",TEXT(AH32,"dd")&"-"&TEXT(AI32,"dd mmm")) | AH32: =IFERROR($M32+VLOOKUP($L32,'Voyage days'!$F$38:$H$89,3,FALSE),"") | AI32: =IFERROR(N32+VLOOKUP($L32,'Voyage days'!$F$38:$H$89,3,FALSE),"") | AJ32: =IF(AK32="","",TEXT(AK32,"dd")&"-"&TEXT(AL32,"dd mmm")) -> 25-26 Apr | AK32: =IFERROR($M32+VLOOKUP($L32,'Voyage days'!$F$94:$H$193,3,FALSE),"") -> 46137 | AL32: =IFERROR($N32+VLOOKUP($L32,'Voyage days'!$F$94:$H$193,3,FALSE),"") -> 46138 | AM32: =IF(AN32="","",TEXT(AN32,"dd")&"-"&TEXT(AO32,"dd mmm")) -> 25-26 Apr | AN32: =IFERROR($M32+VLOOKUP($L32,'Voyage days'!$F$203:$H$256,3,FALSE),"") -> 46137 | AO32: =IFERROR($N32+VLOOKUP($L32,'Voyage days'!$F$203:$H$256,3,FALSE),"") -> 46138 | AP32: =IF(AQ32="","",TEXT(AQ32,"dd")&"-"&TEXT(AR32,"dd mmm")) | AQ32: =IFERROR($M32+VLOOKUP($L32,'Voyage days'!$F$294:$H$377,3,FALSE),"") | AR32: =IFERROR($N32+VLOOKUP($L32,'Voyage days'!$F$294:$H$377,3,FALSE),"") | AS32: =IF(AT32="","",TEXT(AT32,"dd")&"-"&TEXT(AU32,"dd mmm")) -> 15-16 May | AT32: =IFERROR($M32+VLOOKUP($L32,'Voyage days'!$F$382:$H$446,3,FALSE),"") -> 46157 | AU32: =IFERROR($N32+VLOOKUP($L32,'Voyage days'!$F$382:$H$446,3,FALSE),"") -> 46158 | AV32: =IF(AW32="","",TEXT(AW32,"dd")&"-"&TEXT(AX32,"dd mmm")) | AW32: =IFERROR($M32+VLOOKUP($L32,'Voyage days'!$F$483:$H$538,3,FALSE),"") | AX32: =IFERROR($N32+VLOOKUP($L32,'Voyage days'!$F$483:$H$538,3,FALSE),"") | AY32: =IF(AZ32="","",TEXT(AZ32,"dd")&"-"&TEXT(BA32,"dd mmm")) | AZ32: =IFERROR($M32+VLOOKUP($L32,'Voyage days'!$F$540:$H$613,3,FALSE),"") | BA32: =IFERROR($N32+VLOOKUP($L32,'Voyage days'!$F$540:$H$613,3,FALSE),"") | BB32: =IF(BC32="","",TEXT(BC32,"dd")&"-"&TEXT(BD32,"dd mmm")) | BC32: =IFERROR($M32+VLOOKUP($L32,'Voyage days'!$F$448:$H$479,3,FALSE),"") | BD32: =IFERROR($N32+VLOOKUP($L32,'Voyage days'!$F$448:$H$479,3,FALSE),"") | BE32: =IF(BF32="","",TEXT(BF32,"dd")&"-"&TEXT(BG32,"dd mmm")) | BF32: =IFERROR($M32+VLOOKUP($L32,'Voyage days'!$F$620:$H$646,3,FALSE),"") | BG32: =IFERROR($N32+VLOOKUP($L32,'Voyage days'!$F$620:$H$646,3,FALSE),"") | BH32: =IF(BI32="","",TEXT(BI32,"dd")&"-"&TEXT(BL32,"dd mmm")) | BI32: =IFERROR($M32+VLOOKUP($L32,'Voyage days'!$F$702:$H$727,3,FALSE),"") | BJ32: =IF(BK32="","",TEXT(BK32,"dd")&"-"&TEXT(BL32,"dd mmm")) | BK32: =IFERROR($M32+VLOOKUP($L32,'Voyage days'!$F$807:$H$878,3,FALSE),"") | BL32: =IFERROR($N32+VLOOKUP($L32,'Voyage days'!$F$807:$H$878,3,FALSE),"") | BM32: =IFERROR($N32+VLOOKUP($L32,'Voyage days'!$F$807:$K$878,6,FALSE),"") | BN32: =if(L32="loads AG", IFERROR($M32+VLOOKUP($L32,'Voyage days'!$M$38:$O$38,3,FALSE),""),"") | BO32: =if(L32="loads USG", IFERROR($M32+VLOOKUP($L32,'Voyage days'!$L$203:$N$203,3,FALSE),""),"") -> 46169
A33: Pointis | B33: 2016 | C33: 84000 | I33: ATC | J33: =IF(W33="","NO AIS",IF((W33-M33-1)>0,"Update","")) -> NO AIS | L33: Suez | M33: 46125 | N33: 46126 | P33: drifting off Jizan since 29 Mar | R33: ATC 7 Jan STS Red Sea (G Alkhaleej) | S33: BR | T33: 46124 | U33: =IF(V33="","No AIS",VLOOKUP(V33,'Voyage days'!$A$3:$B$1480,2,FALSE)) -> No AIS | V33: =IF(VLOOKUP(A33,'1) Kpler'!$E$2:$P$1000,8, FALSE)="","",VLOOKUP(A33,'1) Kpler'!$E$2:$P$1000,8, FALSE)) | W33: =IF(VLOOKUP(A33,'1) Kpler'!$E$2:$P$1000,9,FALSE)="","",VLOOKUP(A33,'1) Kpler'!$E$2:$P$1000,9,FALSE)) | X33: =VLOOKUP(A33,'1) Kpler'!$E$2:$I$1000,4,FALSE) -> ballast | Y33: =AG33 -> 22-23 Apr | Z33: =AJ33 -> 01-02 May | AA33: =AM33 -> 04-05 May | AB33: =AP33 -> 28-29 Apr | AC33: =AS33 -> 21-22 Apr | AD33: =BB33 | AE33: =AY33 | AF33: =BJ33 -> 14-15 Apr | AG33: =IF(AH33="","",TEXT(AH33,"dd")&"-"&TEXT(AI33,"dd mmm")) -> 22-23 Apr | AH33: =IFERROR($M33+VLOOKUP($L33,'Voyage days'!$F$38:$H$89,3,FALSE),"") -> 46134 | AI33: =IFERROR(N33+VLOOKUP($L33,'Voyage days'!$F$38:$H$89,3,FALSE),"") -> 46135 | AJ33: =IF(AK33="","",TEXT(AK33,"dd")&"-"&TEXT(AL33,"dd mmm")) -> 01-02 May | AK33: =IFERROR($M33+VLOOKUP($L33,'Voyage days'!$F$94:$H$193,3,FALSE),"") -> 46143 | AL33: =IFERROR($N33+VLOOKUP($L33,'Voyage days'!$F$94:$H$193,3,FALSE),"") -> 46144 | AM33: =IF(AN33="","",TEXT(AN33,"dd")&"-"&TEXT(AO33,"dd mmm")) -> 04-05 May | AN33: =IFERROR($M33+VLOOKUP($L33,'Voyage days'!$F$203:$H$256,3,FALSE),"") -> 46146 | AO33: =IFERROR($N33+VLOOKUP($L33,'Voyage days'!$F$203:$H$256,3,FALSE),"") -> 46147 | AP33: =IF(AQ33="","",TEXT(AQ33,"dd")&"-"&TEXT(AR33,"dd mmm")) -> 28-29 Apr | AQ33: =IFERROR($M33+VLOOKUP($L33,'Voyage days'!$F$294:$H$377,3,FALSE),"") -> 46140 | AR33: =IFERROR($N33+VLOOKUP($L33,'Voyage days'!$F$294:$H$377,3,FALSE),"") -> 46141 | AS33: =IF(AT33="","",TEXT(AT33,"dd")&"-"&TEXT(AU33,"dd mmm")) -> 21-22 Apr | AT33: =IFERROR($M33+VLOOKUP($L33,'Voyage days'!$F$382:$H$446,3,FALSE),"") -> 46133 | AU33: =IFERROR($N33+VLOOKUP($L33,'Voyage days'!$F$382:$H$446,3,FALSE),"") -> 46134 | AV33: =IF(AW33="","",TEXT(AW33,"dd")&"-"&TEXT(AX33,"dd mmm")) | AW33: =IFERROR($M33+VLOOKUP($L33,'Voyage days'!$F$483:$H$538,3,FALSE),"") | AX33: =IFERROR($N33+VLOOKUP($L33,'Voyage days'!$F$483:$H$538,3,FALSE),"") | AY33: =IF(AZ33="","",TEXT(AZ33,"dd")&"-"&TEXT(BA33,"dd mmm")) | AZ33: =IFERROR($M33+VLOOKUP($L33,'Voyage days'!$F$540:$H$613,3,FALSE),"") | BA33: =IFERROR($N33+VLOOKUP($L33,'Voyage days'!$F$540:$H$613,3,FALSE),"") | BB33: =IF(BC33="","",TEXT(BC33,"dd")&"-"&TEXT(BD33,"dd mmm")) | BC33: =IFERROR($M33+VLOOKUP($L33,'Voyage days'!$F$448:$H$479,3,FALSE),"") | BD33: =IFERROR($N33+VLOOKUP($L33,'Voyage days'!$F$448:$H$479,3,FALSE),"") | BE33: =IF(BF33="","",TEXT(BF33,"dd")&"-"&TEXT(BG33,"dd mmm")) | BF33: =IFERROR($M33+VLOOKUP($L33,'Voyage days'!$F$620:$H$646,3,FALSE),"") | BG33: =IFERROR($N33+VLOOKUP($L33,'Voyage days'!$F$620:$H$646,3,FALSE),"") | BH33: =IF(BI33="","",TEXT(BI33,"dd")&"-"&TEXT(BL33,"dd mmm")) | BI33: =IFERROR($M33+VLOOKUP($L33,'Voyage days'!$F$702:$H$727,3,FALSE),"") | BJ33: =IF(BK33="","",TEXT(BK33,"dd")&"-"&TEXT(BL33,"dd mmm")) -> 14-15 Apr | BK33: =IFERROR($M33+VLOOKUP($L33,'Voyage days'!$F$807:$H$878,3,FALSE),"") -> 46126.5 | BL33: =IFERROR($N33+VLOOKUP($L33,'Voyage days'!$F$807:$H$878,3,FALSE),"") -> 46127.5 | BM33: =IFERROR($N33+VLOOKUP($L33,'Voyage days'!$F$807:$K$878,6,FALSE),"") -> 46126 | BN33: =if(L33="loads AG", IFERROR($M33+VLOOKUP($L33,'Voyage days'!$M$38:$O$38,3,FALSE),""),"") | BO33: =if(L33="loads USG", IFERROR($M33+VLOOKUP($L33,'Voyage days'!$L$203:$N$203,3,FALSE),""),"")
A34: Astomos Earth | B34: 41094 | C34: 83000 | I34: BASF | J34: =IF(W34="","NO AIS",IF((W34-M34-1)>0,"Update","")) | L34: loads USG | M34: 46154 | N34: 46155 | P34: ETA Freeport 12 May via Cape | R34: BASF 04-05 May Freeport | S34: BR | T34: 46124 | U34: =IF(V34="","No AIS",VLOOKUP(V34,'Voyage days'!$A$3:$B$1480,2,FALSE)) -> USG | V34: =IF(VLOOKUP(A34,'1) Kpler'!$E$2:$P$1000,8, FALSE)="","",VLOOKUP(A34,'1) Kpler'!$E$2:$P$1000,8, FALSE)) -> Freeport Texas | W34: =IF(VLOOKUP(A34,'1) Kpler'!$E$2:$P$1000,9,FALSE)="","",VLOOKUP(A34,'1) Kpler'!$E$2:$P$1000,9,FALSE)) -> 46154.646 | X34: =VLOOKUP(A34,'1) Kpler'!$E$2:$I$1000,4,FALSE) -> ballast | Y34: =AG34 | Z34: =AJ34 -> 12-13 May | AA34: =AM34 -> 12-13 May | AB34: =AP34 | AC34: =AS34 -> 01-02 Jun | AD34: =BB34 | AE34: =AY34 | AF34: =BJ34 | AG34: =IF(AH34="","",TEXT(AH34,"dd")&"-"&TEXT(AI34,"dd mmm")) | AH34: =IFERROR($M34+VLOOKUP($L34,'Voyage days'!$F$38:$H$89,3,FALSE),"") | AI34: =IFERROR(N34+VLOOKUP($L34,'Voyage days'!$F$38:$H$89,3,FALSE),"") | AJ34: =IF(AK34="","",TEXT(AK34,"dd")&"-"&TEXT(AL34,"dd mmm")) -> 12-13 May | AK34: =IFERROR($M34+VLOOKUP($L34,'Voyage days'!$F$94:$H$193,3,FALSE),"") -> 46154 | AL34: =IFERROR($N34+VLOOKUP($L34,'Voyage days'!$F$94:$H$193,3,FALSE),"") -> 46155 | AM34: =IF(AN34="","",TEXT(AN34,"dd")&"-"&TEXT(AO34,"dd mmm")) -> 12-13 May | AN34: =IFERROR($M34+VLOOKUP($L34,'Voyage days'!$F$203:$H$256,3,FALSE),"") -> 46154 | AO34: =IFERROR($N34+VLOOKUP($L34,'Voyage days'!$F$203:$H$256,3,FALSE),"") -> 46155 | AP34: =IF(AQ34="","",TEXT(AQ34,"dd")&"-"&TEXT(AR34,"dd mmm")) | AQ34: =IFERROR($M34+VLOOKUP($L34,'Voyage days'!$F$294:$H$377,3,FALSE),"") | AR34: =IFERROR($N34+VLOOKUP($L34,'Voyage days'!$F$294:$H$377,3,FALSE),"") | AS34: =IF(AT34="","",TEXT(AT34,"dd")&"-"&TEXT(AU34,"dd mmm")) -> 01-02 Jun | AT34: =IFERROR($M34+VLOOKUP($L34,'Voyage days'!$F$382:$H$446,3,FALSE),"") -> 46174 | AU34: =IFERROR($N34+VLOOKUP($L34,'Voyage days'!$F$382:$H$446,3,FALSE),"") -> 46175 | AV34: =IF(AW34="","",TEXT(AW34,"dd")&"-"&TEXT(AX34,"dd mmm")) | AW34: =IFERROR($M34+VLOOKUP($L34,'Voyage days'!$F$483:$H$538,3,FALSE),"") | AX34: =IFERROR($N34+VLOOKUP($L34,'Voyage days'!$F$483:$H$538,3,FALSE),"") | AY34: =IF(AZ34="","",TEXT(AZ34,"dd")&"-"&TEXT(BA34,"dd mmm")) | AZ34: =IFERROR($M34+VLOOKUP($L34,'Voyage days'!$F$540:$H$613,3,FALSE),"") | BA34: =IFERROR($N34+VLOOKUP($L34,'Voyage days'!$F$540:$H$613,3,FALSE),"") | BB34: =IF(BC34="","",TEXT(BC34,"dd")&"-"&TEXT(BD34,"dd mmm")) | BC34: =IFERROR($M34+VLOOKUP($L34,'Voyage days'!$F$448:$H$479,3,FALSE),"") | BD34: =IFERROR($N34+VLOOKUP($L34,'Voyage days'!$F$448:$H$479,3,FALSE),"") | BE34: =IF(BF34="","",TEXT(BF34,"dd")&"-"&TEXT(BG34,"dd mmm")) | BF34: =IFERROR($M34+VLOOKUP($L34,'Voyage days'!$F$620:$H$646,3,FALSE),"") | BG34: =IFERROR($N34+VLOOKUP($L34,'Voyage days'!$F$620:$H$646,3,FALSE),"") | BH34: =IF(BI34="","",TEXT(BI34,"dd")&"-"&TEXT(BL34,"dd mmm")) | BI34: =IFERROR($M34+VLOOKUP($L34,'Voyage days'!$F$702:$H$727,3,FALSE),"") | BJ34: =IF(BK34="","",TEXT(BK34,"dd")&"-"&TEXT(BL34,"dd mmm")) | BK34: =IFERROR($M34+VLOOKUP($L34,'Voyage days'!$F$807:$H$878,3,FALSE),"") | BL34: =IFERROR($N34+VLOOKUP($L34,'Voyage days'!$F$807:$H$878,3,FALSE),"") | BM34: =IFERROR($N34+VLOOKUP($L34,'Voyage days'!$F$807:$K$878,6,FALSE),"") | BN34: =if(L34="loads AG", IFERROR($M34+VLOOKUP($L34,'Voyage days'!$M$38:$O$38,3,FALSE),""),"") | BO34: =if(L34="loads USG", IFERROR($M34+VLOOKUP($L34,'Voyage days'!$L$203:$N$203,3,FALSE),""),"") -> 46186
A35: BW Freyja | B35: 42551 | C35: 84143 | H35: DF | I35: BASF | J35: =IF(W35="","NO AIS",IF((W35-M35-1)>0,"Update","")) -> NO AIS | L35: East China | M35: 46132 | N35: 46133 | P35: ETA Jinshan 16 Apr | R35: BASF 21-22 Feb Freeport | S35: BR | T35: 46124 | U35: =IF(V35="","No AIS",VLOOKUP(V35,'Voyage days'!$A$3:$B$1480,2,FALSE)) -> No AIS | V35: =IF(VLOOKUP(A35,'1) Kpler'!$E$2:$P$1000,8, FALSE)="","",VLOOKUP(A35,'1) Kpler'!$E$2:$P$1000,8, FALSE)) | W35: =IF(VLOOKUP(A35,'1) Kpler'!$E$2:$P$1000,9,FALSE)="","",VLOOKUP(A35,'1) Kpler'!$E$2:$P$1000,9,FALSE)) | X35: =VLOOKUP(A35,'1) Kpler'!$E$2:$I$1000,4,FALSE) -> ballast | Y35: =AG35 -> 07-08 May | Z35: =AJ35 -> 23-24 May | AA35: =AM35 -> 03-04 Jun | AB35: =AP35 -> 18-19 May | AC35: =AS35 -> 25-26 May | AD35: =BB35 -> 26-27 Apr | AE35: =AY35 -> 27-28 Apr | AF35: =BJ35 -> 03-04 Jun | AG35: =IF(AH35="","",TEXT(AH35,"dd")&"-"&TEXT(AI35,"dd mmm")) -> 07-08 May | AH35: =IFERROR($M35+VLOOKUP($L35,'Voyage days'!$F$38:$H$89,3,FALSE),"") -> 46149 | AI35: =IFERROR(N35+VLOOKUP($L35,'Voyage days'!$F$38:$H$89,3,FALSE),"") -> 46150 | AJ35: =IF(AK35="","",TEXT(AK35,"dd")&"-"&TEXT(AL35,"dd mmm")) -> 23-24 May | AK35: =IFERROR($M35+VLOOKUP($L35,'Voyage days'!$F$94:$H$193,3,FALSE),"") -> 46165 | AL35: =IFERROR($N35+VLOOKUP($L35,'Voyage days'!$F$94:$H$193,3,FALSE),"") -> 46166 | AM35: =IF(AN35="","",TEXT(AN35,"dd")&"-"&TEXT(AO35,"dd mmm")) -> 03-04 Jun | AN35: =IFERROR($M35+VLOOKUP($L35,'Voyage days'!$F$203:$H$256,3,FALSE),"") -> 46176 | AO35: =IFERROR($N35+VLOOKUP($L35,'Voyage days'!$F$203:$H$256,3,FALSE),"") -> 46177 | AP35: =IF(AQ35="","",TEXT(AQ35,"dd")&"-"&TEXT(AR35,"dd mmm")) -> 18-19 May | AQ35: =IFERROR($M35+VLOOKUP($L35,'Voyage days'!$F$294:$H$377,3,FALSE),"") -> 46160 | AR35: =IFERROR($N35+VLOOKUP($L35,'Voyage days'!$F$294:$H$377,3,FALSE),"") -> 46161 | AS35: =IF(AT35="","",TEXT(AT35,"dd")&"-"&TEXT(AU35,"dd mmm")) -> 25-26 May | AT35: =IFERROR($M35+VLOOKUP($L35,'Voyage days'!$F$382:$H$446,3,FALSE),"") -> 46167 | AU35: =IFERROR($N35+VLOOKUP($L35,'Voyage days'!$F$382:$H$446,3,FALSE),"") -> 46168 | AV35: =IF(AW35="","",TEXT(AW35,"dd")&"-"&TEXT(AX35,"dd mmm")) -> 04-05 May | AW35: =IFERROR($M35+VLOOKUP($L35,'Voyage days'!$F$483:$H$538,3,FALSE),"") -> 46146 | AX35: =IFERROR($N35+VLOOKUP($L35,'Voyage days'!$F$483:$H$538,3,FALSE),"") -> 46147 | AY35: =IF(AZ35="","",TEXT(AZ35,"dd")&"-"&TEXT(BA35,"dd mmm")) -> 27-28 Apr | AZ35: =IFERROR($M35+VLOOKUP($L35,'Voyage days'!$F$540:$H$613,3,FALSE),"") -> 46139.25 | BA35: =IFERROR($N35+VLOOKUP($L35,'Voyage days'!$F$540:$H$613,3,FALSE),"") -> 46140.25 | BB35: =IF(BC35="","",TEXT(BC35,"dd")&"-"&TEXT(BD35,"dd mmm")) -> 26-27 Apr | BC35: =IFERROR($M35+VLOOKUP($L35,'Voyage days'!$F$448:$H$479,3,FALSE),"") -> 46138 | BD35: =IFERROR($N35+VLOOKUP($L35,'Voyage days'!$F$448:$H$479,3,FALSE),"") -> 46139 | BE35: =IF(BF35="","",TEXT(BF35,"dd")&"-"&TEXT(BG35,"dd mmm")) -> 03-04 May | BF35: =IFERROR($M35+VLOOKUP($L35,'Voyage days'!$F$620:$H$646,3,FALSE),"") -> 46145 | BG35: =IFERROR($N35+VLOOKUP($L35,'Voyage days'!$F$620:$H$646,3,FALSE),"") -> 46146 | BH35: =IF(BI35="","",TEXT(BI35,"dd")&"-"&TEXT(BL35,"dd mmm")) -> 27-04 Jun | BI35: =IFERROR($M35+VLOOKUP($L35,'Voyage days'!$F$702:$H$727,3,FALSE),"") -> 46139.25 | BJ35: =IF(BK35="","",TEXT(BK35,"dd")&"-"&TEXT(BL35,"dd mmm")) -> 03-04 Jun | BK35: =IFERROR($M35+VLOOKUP($L35,'Voyage days'!$F$807:$H$878,3,FALSE),"") -> 46176 | BL35: =IFERROR($N35+VLOOKUP($L35,'Voyage days'!$F$807:$H$878,3,FALSE),"") -> 46177 | BM35: =IFERROR($N35+VLOOKUP($L35,'Voyage days'!$F$807:$K$878,6,FALSE),"") -> 46151 | BN35: =if(L35="loads AG", IFERROR($M35+VLOOKUP($L35,'Voyage days'!$M$38:$O$38,3,FALSE),""),"") | BO35: =if(L35="loads USG", IFERROR($M35+VLOOKUP($L35,'Voyage days'!$L$203:$N$203,3,FALSE),""),"")
A36: Gas Young | B36: 2017 | C36: 84000 | I36: BB Energy | J36: =IF(W36="","NO AIS",IF((W36-M36-1)>0,"Update","")) -> NO AIS | L36: Indo | M36: 46132 | N36: 46133 | P36: ETA Darwin 12-13 Apr | R36: Total 10-11 Apr Darwin | S36: BR | T36: 46124 | U36: =IF(V36="","No AIS",VLOOKUP(V36,'Voyage days'!$A$3:$B$1480,2,FALSE)) -> No AIS | V36: =IF(VLOOKUP(A36,'1) Kpler'!$E$2:$P$1000,8, FALSE)="","",VLOOKUP(A36,'1) Kpler'!$E$2:$P$1000,8, FALSE)) | W36: =IF(VLOOKUP(A36,'1) Kpler'!$E$2:$P$1000,9,FALSE)="","",VLOOKUP(A36,'1) Kpler'!$E$2:$P$1000,9,FALSE)) | X36: =VLOOKUP(A36,'1) Kpler'!$E$2:$I$1000,4,FALSE) -> ballast | Y36: =AG36 -> 01-02 May | Z36: =AJ36 -> 29-30 May | AA36: =AM36 -> 27-28 May | AB36: =AP36 -> 10-11 May | AC36: =AS36 -> 19-20 May | AD36: =BB36 -> 23-24 Apr | AE36: =AY36 -> 24-25 Apr | AF36: =BJ36 -> 27-28 May | AG36: =IF(AH36="","",TEXT(AH36,"dd")&"-"&TEXT(AI36,"dd mmm")) -> 01-02 May | AH36: =IFERROR($M36+VLOOKUP($L36,'Voyage days'!$F$38:$H$89,3,FALSE),"") -> 46143 | AI36: =IFERROR(N36+VLOOKUP($L36,'Voyage days'!$F$38:$H$89,3,FALSE),"") -> 46144 | AJ36: =IF(AK36="","",TEXT(AK36,"dd")&"-"&TEXT(AL36,"dd mmm")) -> 29-30 May | AK36: =IFERROR($M36+VLOOKUP($L36,'Voyage days'!$F$94:$H$193,3,FALSE),"") -> 46171 | AL36: =IFERROR($N36+VLOOKUP($L36,'Voyage days'!$F$94:$H$193,3,FALSE),"") -> 46172 | AM36: =IF(AN36="","",TEXT(AN36,"dd")&"-"&TEXT(AO36,"dd mmm")) -> 27-28 May | AN36: =IFERROR($M36+VLOOKUP($L36,'Voyage days'!$F$203:$H$256,3,FALSE),"") -> 46169 | AO36: =IFERROR($N36+VLOOKUP($L36,'Voyage days'!$F$203:$H$256,3,FALSE),"") -> 46170 | AP36: =IF(AQ36="","",TEXT(AQ36,"dd")&"-"&TEXT(AR36,"dd mmm")) -> 10-11 May | AQ36: =IFERROR($M36+VLOOKUP($L36,'Voyage days'!$F$294:$H$377,3,FALSE),"") -> 46152 | AR36: =IFERROR($N36+VLOOKUP($L36,'Voyage days'!$F$294:$H$377,3,FALSE),"") -> 46153 | AS36: =IF(AT36="","",TEXT(AT36,"dd")&"-"&TEXT(AU36,"dd mmm")) -> 19-20 May | AT36: =IFERROR($M36+VLOOKUP($L36,'Voyage days'!$F$382:$H$446,3,FALSE),"") -> 46161 | AU36: =IFERROR($N36+VLOOKUP($L36,'Voyage days'!$F$382:$H$446,3,FALSE),"") -> 46162 | AV36: =IF(AW36="","",TEXT(AW36,"dd")&"-"&TEXT(AX36,"dd mmm")) -> 29-30 Apr | AW36: =IFERROR($M36+VLOOKUP($L36,'Voyage days'!$F$483:$H$538,3,FALSE),"") -> 46141 | AX36: =IFERROR($N36+VLOOKUP($L36,'Voyage days'!$F$483:$H$538,3,FALSE),"") -> 46142 | AY36: =IF(AZ36="","",TEXT(AZ36,"dd")&"-"&TEXT(BA36,"dd mmm")) -> 24-25 Apr | AZ36: =IFERROR($M36+VLOOKUP($L36,'Voyage days'!$F$540:$H$613,3,FALSE),"") -> 46136 | BA36: =IFERROR($N36+VLOOKUP($L36,'Voyage days'!$F$540:$H$613,3,FALSE),"") -> 46137 | BB36: =IF(BC36="","",TEXT(BC36,"dd")&"-"&TEXT(BD36,"dd mmm")) -> 23-24 Apr | BC36: =IFERROR($M36+VLOOKUP($L36,'Voyage days'!$F$448:$H$479,3,FALSE),"") -> 46135 | BD36: =IFERROR($N36+VLOOKUP($L36,'Voyage days'!$F$448:$H$479,3,FALSE),"") -> 46136 | BE36: =IF(BF36="","",TEXT(BF36,"dd")&"-"&TEXT(BG36,"dd mmm")) | BF36: =IFERROR($M36+VLOOKUP($L36,'Voyage days'!$F$620:$H$646,3,FALSE),"") | BG36: =IFERROR($N36+VLOOKUP($L36,'Voyage days'!$F$620:$H$646,3,FALSE),"") | BH36: =IF(BI36="","",TEXT(BI36,"dd")&"-"&TEXT(BL36,"dd mmm")) -> 28-28 May | BI36: =IFERROR($M36+VLOOKUP($L36,'Voyage days'!$F$702:$H$727,3,FALSE),"") -> 46140 | BJ36: =IF(BK36="","",TEXT(BK36,"dd")&"-"&TEXT(BL36,"dd mmm")) -> 27-28 May | BK36: =IFERROR($M36+VLOOKUP($L36,'Voyage days'!$F$807:$H$878,3,FALSE),"") -> 46169 | BL36: =IFERROR($N36+VLOOKUP($L36,'Voyage days'!$F$807:$H$878,3,FALSE),"") -> 46170 | BM36: =IFERROR($N36+VLOOKUP($L36,'Voyage days'!$F$807:$K$878,6,FALSE),"") -> 46146 | BN36: =if(L36="loads AG", IFERROR($M36+VLOOKUP($L36,'Voyage days'!$M$38:$O$38,3,FALSE),""),"") | BO36: =if(L36="loads USG", IFERROR($M36+VLOOKUP($L36,'Voyage days'!$L$203:$N$203,3,FALSE),""),"")
A37: Tethys | B37: 2013 | C37: 82000 | H37: S | I37: BB Energy | J37: =IF(W37="","NO AIS",IF((W37-M37-1)>0,"Update","")) | L37: loads WAF | M37: 46134 | N37: 46137 | P37: ETA Soyo 22 Apr, ex Singapore 31 Mar | R37: Total 21-25 Apr Soyo | S37: BR | T37: 46124 | U37: =IF(V37="","No AIS",VLOOKUP(V37,'Voyage days'!$A$3:$B$1480,2,FALSE)) -> WAF | V37: =IF(VLOOKUP(A37,'1) Kpler'!$E$2:$P$1000,8, FALSE)="","",VLOOKUP(A37,'1) Kpler'!$E$2:$P$1000,8, FALSE)) -> Soyo | W37: =IF(VLOOKUP(A37,'1) Kpler'!$E$2:$P$1000,9,FALSE)="","",VLOOKUP(A37,'1) Kpler'!$E$2:$P$1000,9,FALSE)) -> 46134.583 | X37: =VLOOKUP(A37,'1) Kpler'!$E$2:$I$1000,4,FALSE) -> ballast | Y37: =AG37 | Z37: =AJ37 | AA37: =AM37 | AB37: =AP37 -> 22-25 Apr | AC37: =AS37 | AD37: =BB37 | AE37: =AY37 | AF37: =BJ37 | AG37: =IF(AH37="","",TEXT(AH37,"dd")&"-"&TEXT(AI37,"dd mmm")) | AH37: =IFERROR($M37+VLOOKUP($L37,'Voyage days'!$F$38:$H$89,3,FALSE),"") | AI37: =IFERROR(N37+VLOOKUP($L37,'Voyage days'!$F$38:$H$89,3,FALSE),"") | AJ37: =IF(AK37="","",TEXT(AK37,"dd")&"-"&TEXT(AL37,"dd mmm")) | AK37: =IFERROR($M37+VLOOKUP($L37,'Voyage days'!$F$94:$H$193,3,FALSE),"") | AL37: =IFERROR($N37+VLOOKUP($L37,'Voyage days'!$F$94:$H$193,3,FALSE),"") | AM37: =IF(AN37="","",TEXT(AN37,"dd")&"-"&TEXT(AO37,"dd mmm")) | AN37: =IFERROR($M37+VLOOKUP($L37,'Voyage days'!$F$203:$H$256,3,FALSE),"") | AO37: =IFERROR($N37+VLOOKUP($L37,'Voyage days'!$F$203:$H$256,3,FALSE),"") | AP37: =IF(AQ37="","",TEXT(AQ37,"dd")&"-"&TEXT(AR37,"dd mmm")) -> 22-25 Apr | AQ37: =IFERROR($M37+VLOOKUP($L37,'Voyage days'!$F$294:$H$377,3,FALSE),"") -> 46134 | AR37: =IFERROR($N37+VLOOKUP($L37,'Voyage days'!$F$294:$H$377,3,FALSE),"") -> 46137 | AS37: =IF(AT37="","",TEXT(AT37,"dd")&"-"&TEXT(AU37,"dd mmm")) | AT37: =IFERROR($M37+VLOOKUP($L37,'Voyage days'!$F$382:$H$446,3,FALSE),"") | AU37: =IFERROR($N37+VLOOKUP($L37,'Voyage days'!$F$382:$H$446,3,FALSE),"") | AV37: =IF(AW37="","",TEXT(AW37,"dd")&"-"&TEXT(AX37,"dd mmm")) | AW37: =IFERROR($M37+VLOOKUP($L37,'Voyage days'!$F$483:$H$538,3,FALSE),"") | AX37: =IFERROR($N37+VLOOKUP($L37,'Voyage days'!$F$483:$H$538,3,FALSE),"") | AY37: =IF(AZ37="","",TEXT(AZ37,"dd")&"-"&TEXT(BA37,"dd mmm")) | AZ37: =IFERROR($M37+VLOOKUP($L37,'Voyage days'!$F$540:$H$613,3,FALSE),"") | BA37: =IFERROR($N37+VLOOKUP($L37,'Voyage days'!$F$540:$H$613,3,FALSE),"") | BB37: =IF(BC37="","",TEXT(BC37,"dd")&"-"&TEXT(BD37,"dd mmm")) | BC37: =IFERROR($M37+VLOOKUP($L37,'Voyage days'!$F$448:$H$479,3,FALSE),"") | BD37: =IFERROR($N37+VLOOKUP($L37,'Voyage days'!$F$448:$H$479,3,FALSE),"") | BE37: =IF(BF37="","",TEXT(BF37,"dd")&"-"&TEXT(BG37,"dd mmm")) | BF37: =IFERROR($M37+VLOOKUP($L37,'Voyage days'!$F$620:$H$646,3,FALSE),"") | BG37: =IFERROR($N37+VLOOKUP($L37,'Voyage days'!$F$620:$H$646,3,FALSE),"") | BH37: =IF(BI37="","",TEXT(BI37,"dd")&"-"&TEXT(BL37,"dd mmm")) | BI37: =IFERROR($M37+VLOOKUP($L37,'Voyage days'!$F$702:$H$727,3,FALSE),"") | BJ37: =IF(BK37="","",TEXT(BK37,"dd")&"-"&TEXT(BL37,"dd mmm")) | BK37: =IFERROR($M37+VLOOKUP($L37,'Voyage days'!$F$807:$H$878,3,FALSE),"") | BL37: =IFERROR($N37+VLOOKUP($L37,'Voyage days'!$F$807:$H$878,3,FALSE),"") | BM37: =IFERROR($N37+VLOOKUP($L37,'Voyage days'!$F$807:$K$878,6,FALSE),"") | BN37: =if(L37="loads AG", IFERROR($M37+VLOOKUP($L37,'Voyage days'!$M$38:$O$38,3,FALSE),""),"") | BO37: =if(L37="loads USG", IFERROR($M37+VLOOKUP($L37,'Voyage days'!$L$203:$N$203,3,FALSE),""),"")
A38: Bella Niagara | B38: 2024 | C38: 91000 | H38: DF | I38: BGN | J38: =IF(W38="","NO AIS",IF((W38-M38-1)>0,"Update","")) -> Update | L38: loads USG | M38: 46141 | N38: 46142 | O38: eu | P38: ETA USG 29 Apr | R38: BGN 28-1 Mar Nederland | S38: GP | T38: 46125 | U38: =IF(V38="","No AIS",VLOOKUP(V38,'Voyage days'!$A$3:$B$1480,2,FALSE)) -> USG | V38: =IF(VLOOKUP(A38,'1) Kpler'!$E$2:$P$1000,8, FALSE)="","",VLOOKUP(A38,'1) Kpler'!$E$2:$P$1000,8, FALSE)) -> Energy Transfer Nederland | W38: =IF(VLOOKUP(A38,'1) Kpler'!$E$2:$P$1000,9,FALSE)="","",VLOOKUP(A38,'1) Kpler'!$E$2:$P$1000,9,FALSE)) -> 46143.667 | X38: =VLOOKUP(A38,'1) Kpler'!$E$2:$I$1000,4,FALSE) -> ballast | Y38: =AG38 | Z38: =AJ38 -> 29-30 Apr | AA38: =AM38 -> 29-30 Apr | AB38: =AP38 | AC38: =AS38 -> 19-20 May | AD38: =BB38 | AE38: =AY38 | AF38: =BJ38 | AG38: =IF(AH38="","",TEXT(AH38,"dd")&"-"&TEXT(AI38,"dd mmm")) | AH38: =IFERROR($M38+VLOOKUP($L38,'Voyage days'!$F$38:$H$89,3,FALSE),"") | AI38: =IFERROR(N38+VLOOKUP($L38,'Voyage days'!$F$38:$H$89,3,FALSE),"") | AJ38: =IF(AK38="","",TEXT(AK38,"dd")&"-"&TEXT(AL38,"dd mmm")) -> 29-30 Apr | AK38: =IFERROR($M38+VLOOKUP($L38,'Voyage days'!$F$94:$H$193,3,FALSE),"") -> 46141 | AL38: =IFERROR($N38+VLOOKUP($L38,'Voyage days'!$F$94:$H$193,3,FALSE),"") -> 46142 | AM38: =IF(AN38="","",TEXT(AN38,"dd")&"-"&TEXT(AO38,"dd mmm")) -> 29-30 Apr | AN38: =IFERROR($M38+VLOOKUP($L38,'Voyage days'!$F$203:$H$256,3,FALSE),"") -> 46141 | AO38: =IFERROR($N38+VLOOKUP($L38,'Voyage days'!$F$203:$H$256,3,FALSE),"") -> 46142 | AP38: =IF(AQ38="","",TEXT(AQ38,"dd")&"-"&TEXT(AR38,"dd mmm")) | AQ38: =IFERROR($M38+VLOOKUP($L38,'Voyage days'!$F$294:$H$377,3,FALSE),"") | AR38: =IFERROR($N38+VLOOKUP($L38,'Voyage days'!$F$294:$H$377,3,FALSE),"") | AS38: =IF(AT38="","",TEXT(AT38,"dd")&"-"&TEXT(AU38,"dd mmm")) -> 19-20 May | AT38: =IFERROR($M38+VLOOKUP($L38,'Voyage days'!$F$382:$H$446,3,FALSE),"") -> 46161 | AU38: =IFERROR($N38+VLOOKUP($L38,'Voyage days'!$F$382:$H$446,3,FALSE),"") -> 46162 | AV38: =IF(AW38="","",TEXT(AW38,"dd")&"-"&TEXT(AX38,"dd mmm")) | AW38: =IFERROR($M38+VLOOKUP($L38,'Voyage days'!$F$483:$H$538,3,FALSE),"") | AX38: =IFERROR($N38+VLOOKUP($L38,'Voyage days'!$F$483:$H$538,3,FALSE),"") | AY38: =IF(AZ38="","",TEXT(AZ38,"dd")&"-"&TEXT(BA38,"dd mmm")) | AZ38: =IFERROR($M38+VLOOKUP($L38,'Voyage days'!$F$540:$H$613,3,FALSE),"") | BA38: =IFERROR($N38+VLOOKUP($L38,'Voyage days'!$F$540:$H$613,3,FALSE),"") | BB38: =IF(BC38="","",TEXT(BC38,"dd")&"-"&TEXT(BD38,"dd mmm")) | BC38: =IFERROR($M38+VLOOKUP($L38,'Voyage days'!$F$448:$H$479,3,FALSE),"") | BD38: =IFERROR($N38+VLOOKUP($L38,'Voyage days'!$F$448:$H$479,3,FALSE),"") | BE38: =IF(BF38="","",TEXT(BF38,"dd")&"-"&TEXT(BG38,"dd mmm")) | BF38: =IFERROR($M38+VLOOKUP($L38,'Voyage days'!$F$620:$H$646,3,FALSE),"") | BG38: =IFERROR($N38+VLOOKUP($L38,'Voyage days'!$F$620:$H$646,3,FALSE),"") | BH38: =IF(BI38="","",TEXT(BI38,"dd")&"-"&TEXT(BL38,"dd mmm")) | BI38: =IFERROR($M38+VLOOKUP($L38,'Voyage days'!$F$702:$H$727,3,FALSE),"") | BJ38: =IF(BK38="","",TEXT(BK38,"dd")&"-"&TEXT(BL38,"dd mmm")) | BK38: =IFERROR($M38+VLOOKUP($L38,'Voyage days'!$F$807:$H$878,3,FALSE),"") | BL38: =IFERROR($N38+VLOOKUP($L38,'Voyage days'!$F$807:$H$878,3,FALSE),"") | BM38: =IFERROR($N38+VLOOKUP($L38,'Voyage days'!$F$807:$K$878,6,FALSE),"") | BN38: =if(L38="loads AG", IFERROR($M38+VLOOKUP($L38,'Voyage days'!$M$38:$O$38,3,FALSE),""),"") | BO38: =if(L38="loads USG", IFERROR($M38+VLOOKUP($L38,'Voyage days'!$L$203:$N$203,3,FALSE),""),"") -> 46173
A39: BW Yushi | B39: 2020 | C39: 83000 | H39: S | I39: BGN | J39: =IF(W39="","NO AIS",IF((W39-M39-1)>0,"Update","")) | K39: Cape | L39: Indo | M39: 46139 | N39: 46140 | P39: ETA Merak 23 Apr | R39: BGN 10-11 Mar Freeport | S39: GP | T39: 46125 | U39: =IF(V39="","No AIS",VLOOKUP(V39,'Voyage days'!$A$3:$B$1480,2,FALSE)) -> Indo + 4 | V39: =IF(VLOOKUP(A39,'1) Kpler'!$E$2:$P$1000,8, FALSE)="","",VLOOKUP(A39,'1) Kpler'!$E$2:$P$1000,8, FALSE)) -> Oiltank. Merak | W39: =IF(VLOOKUP(A39,'1) Kpler'!$E$2:$P$1000,9,FALSE)="","",VLOOKUP(A39,'1) Kpler'!$E$2:$P$1000,9,FALSE)) -> 46135.328 | X39: =VLOOKUP(A39,'1) Kpler'!$E$2:$I$1000,4,FALSE) -> loaded | Y39: =AG39 -> 08-09 May | Z39: =AJ39 -> 05-06 Jun | AA39: =AM39 -> 03-04 Jun | AB39: =AP39 -> 17-18 May | AC39: =AS39 -> 26-27 May | AD39: =BB39 -> 30-01 May | AE39: =AY39 -> 01-02 May | AF39: =BJ39 -> 03-04 Jun | AG39: =IF(AH39="","",TEXT(AH39,"dd")&"-"&TEXT(AI39,"dd mmm")) -> 08-09 May | AH39: =IFERROR($M39+VLOOKUP($L39,'Voyage days'!$F$38:$H$89,3,FALSE),"") -> 46150 | AI39: =IFERROR(N39+VLOOKUP($L39,'Voyage days'!$F$38:$H$89,3,FALSE),"") -> 46151 | AJ39: =IF(AK39="","",TEXT(AK39,"dd")&"-"&TEXT(AL39,"dd mmm")) -> 05-06 Jun | AK39: =IFERROR($M39+VLOOKUP($L39,'Voyage days'!$F$94:$H$193,3,FALSE),"") -> 46178 | AL39: =IFERROR($N39+VLOOKUP($L39,'Voyage days'!$F$94:$H$193,3,FALSE),"") -> 46179 | AM39: =IF(AN39="","",TEXT(AN39,"dd")&"-"&TEXT(AO39,"dd mmm")) -> 03-04 Jun | AN39: =IFERROR($M39+VLOOKUP($L39,'Voyage days'!$F$203:$H$256,3,FALSE),"") -> 46176 | AO39: =IFERROR($N39+VLOOKUP($L39,'Voyage days'!$F$203:$H$256,3,FALSE),"") -> 46177 | AP39: =IF(AQ39="","",TEXT(AQ39,"dd")&"-"&TEXT(AR39,"dd mmm")) -> 17-18 May | AQ39: =IFERROR($M39+VLOOKUP($L39,'Voyage days'!$F$294:$H$377,3,FALSE),"") -> 46159 | AR39: =IFERROR($N39+VLOOKUP($L39,'Voyage days'!$F$294:$H$377,3,FALSE),"") -> 46160 | AS39: =IF(AT39="","",TEXT(AT39,"dd")&"-"&TEXT(AU39,"dd mmm")) -> 26-27 May | AT39: =IFERROR($M39+VLOOKUP($L39,'Voyage days'!$F$382:$H$446,3,FALSE),"") -> 46168 | AU39: =IFERROR($N39+VLOOKUP($L39,'Voyage days'!$F$382:$H$446,3,FALSE),"") -> 46169 | AV39: =IF(AW39="","",TEXT(AW39,"dd")&"-"&TEXT(AX39,"dd mmm")) -> 06-07 May | AW39: =IFERROR($M39+VLOOKUP($L39,'Voyage days'!$F$483:$H$538,3,FALSE),"") -> 46148 | AX39: =IFERROR($N39+VLOOKUP($L39,'Voyage days'!$F$483:$H$538,3,FALSE),"") -> 46149 | AY39: =IF(AZ39="","",TEXT(AZ39,"dd")&"-"&TEXT(BA39,"dd mmm")) -> 01-02 May | AZ39: =IFERROR($M39+VLOOKUP($L39,'Voyage days'!$F$540:$H$613,3,FALSE),"") -> 46143 | BA39: =IFERROR($N39+VLOOKUP($L39,'Voyage days'!$F$540:$H$613,3,FALSE),"") -> 46144 | BB39: =IF(BC39="","",TEXT(BC39,"dd")&"-"&TEXT(BD39,"dd mmm")) -> 30-01 May | BC39: =IFERROR($M39+VLOOKUP($L39,'Voyage days'!$F$448:$H$479,3,FALSE),"") -> 46142 | BD39: =IFERROR($N39+VLOOKUP($L39,'Voyage days'!$F$448:$H$479,3,FALSE),"") -> 46143 | BE39: =IF(BF39="","",TEXT(BF39,"dd")&"-"&TEXT(BG39,"dd mmm")) | BF39: =IFERROR($M39+VLOOKUP($L39,'Voyage days'!$F$620:$H$646,3,FALSE),"") | BG39: =IFERROR($N39+VLOOKUP($L39,'Voyage days'!$F$620:$H$646,3,FALSE),"") | BH39: =IF(BI39="","",TEXT(BI39,"dd")&"-"&TEXT(BL39,"dd mmm")) -> 05-04 Jun | BI39: =IFERROR($M39+VLOOKUP($L39,'Voyage days'!$F$702:$H$727,3,FALSE),"") -> 46147 | BJ39: =IF(BK39="","",TEXT(BK39,"dd")&"-"&TEXT(BL39,"dd mmm")) -> 03-04 Jun | BK39: =IFERROR($M39+VLOOKUP($L39,'Voyage days'!$F$807:$H$878,3,FALSE),"") -> 46176 | BL39: =IFERROR($N39+VLOOKUP($L39,'Voyage days'!$F$807:$H$878,3,FALSE),"") -> 46177 | BM39: =IFERROR($N39+VLOOKUP($L39,'Voyage days'!$F$807:$K$878,6,FALSE),"") -> 46153 | BN39: =if(L39="loads AG", IFERROR($M39+VLOOKUP($L39,'Voyage days'!$M$38:$O$38,3,FALSE),""),"") | BO39: =if(L39="loads USG", IFERROR($M39+VLOOKUP($L39,'Voyage days'!$L$203:$N$203,3,FALSE),""),"")
A40: Challenger | B40: 42353 | C40: 84000 | H40: S | I40: BGN | J40: =IF(W40="","NO AIS",IF((W40-M40-1)>0,"Update","")) | L40: Suez | M40: 46146 | N40: 46140 | O40: eu | P40: ETA Port Said 27 Apr | R40: BGN 08-09 Apr MH | S40: GP | T40: 46125 | U40: =IF(V40="","No AIS",VLOOKUP(V40,'Voyage days'!$A$3:$B$1480,2,FALSE)) -> East Med | V40: =IF(VLOOKUP(A40,'1) Kpler'!$E$2:$P$1000,8, FALSE)="","",VLOOKUP(A40,'1) Kpler'!$E$2:$P$1000,8, FALSE)) -> Valletta | W40: =IF(VLOOKUP(A40,'1) Kpler'!$E$2:$P$1000,9,FALSE)="","",VLOOKUP(A40,'1) Kpler'!$E$2:$P$1000,9,FALSE)) -> 46136.875 | X40: =VLOOKUP(A40,'1) Kpler'!$E$2:$I$1000,4,FALSE) -> loaded | Y40: =AG40 -> 13-07 May | Z40: =AJ40 -> 22-16 May | AA40: =AM40 -> 25-19 May | AB40: =AP40 -> 19-13 May | AC40: =AS40 -> 12-06 May | AD40: =BB40 | AE40: =AY40 | AF40: =BJ40 -> 05-29 Apr | AG40: =IF(AH40="","",TEXT(AH40,"dd")&"-"&TEXT(AI40,"dd mmm")) -> 13-07 May | AH40: =IFERROR($M40+VLOOKUP($L40,'Voyage days'!$F$38:$H$89,3,FALSE),"") -> 46155 | AI40: =IFERROR(N40+VLOOKUP($L40,'Voyage days'!$F$38:$H$89,3,FALSE),"") -> 46149 | AJ40: =IF(AK40="","",TEXT(AK40,"dd")&"-"&TEXT(AL40,"dd mmm")) -> 22-16 May | AK40: =IFERROR($M40+VLOOKUP($L40,'Voyage days'!$F$94:$H$193,3,FALSE),"") -> 46164 | AL40: =IFERROR($N40+VLOOKUP($L40,'Voyage days'!$F$94:$H$193,3,FALSE),"") -> 46158 | AM40: =IF(AN40="","",TEXT(AN40,"dd")&"-"&TEXT(AO40,"dd mmm")) -> 25-19 May | AN40: =IFERROR($M40+VLOOKUP($L40,'Voyage days'!$F$203:$H$256,3,FALSE),"") -> 46167 | AO40: =IFERROR($N40+VLOOKUP($L40,'Voyage days'!$F$203:$H$256,3,FALSE),"") -> 46161 | AP40: =IF(AQ40="","",TEXT(AQ40,"dd")&"-"&TEXT(AR40,"dd mmm")) -> 19-13 May | AQ40: =IFERROR($M40+VLOOKUP($L40,'Voyage days'!$F$294:$H$377,3,FALSE),"") -> 46161 | AR40: =IFERROR($N40+VLOOKUP($L40,'Voyage days'!$F$294:$H$377,3,FALSE),"") -> 46155 | AS40: =IF(AT40="","",TEXT(AT40,"dd")&"-"&TEXT(AU40,"dd mmm")) -> 12-06 May | AT40: =IFERROR($M40+VLOOKUP($L40,'Voyage days'!$F$382:$H$446,3,FALSE),"") -> 46154 | AU40: =IFERROR($N40+VLOOKUP($L40,'Voyage days'!$F$382:$H$446,3,FALSE),"") -> 46148 | AV40: =IF(AW40="","",TEXT(AW40,"dd")&"-"&TEXT(AX40,"dd mmm")) | AW40: =IFERROR($M40+VLOOKUP($L40,'Voyage days'!$F$483:$H$538,3,FALSE),"") | AX40: =IFERROR($N40+VLOOKUP($L40,'Voyage days'!$F$483:$H$538,3,FALSE),"") | AY40: =IF(AZ40="","",TEXT(AZ40,"dd")&"-"&TEXT(BA40,"dd mmm")) | AZ40: =IFERROR($M40+VLOOKUP($L40,'Voyage days'!$F$540:$H$613,3,FALSE),"") | BA40: =IFERROR($N40+VLOOKUP($L40,'Voyage days'!$F$540:$H$613,3,FALSE),"") | BB40: =IF(BC40="","",TEXT(BC40,"dd")&"-"&TEXT(BD40,"dd mmm")) | BC40: =IFERROR($M40+VLOOKUP($L40,'Voyage days'!$F$448:$H$479,3,FALSE),"") | BD40: =IFERROR($N40+VLOOKUP($L40,'Voyage days'!$F$448:$H$479,3,FALSE),"") | BE40: =IF(BF40="","",TEXT(BF40,"dd")&"-"&TEXT(BG40,"dd mmm")) | BF40: =IFERROR($M40+VLOOKUP($L40,'Voyage days'!$F$620:$H$646,3,FALSE),"") | BG40: =IFERROR($N40+VLOOKUP($L40,'Voyage days'!$F$620:$H$646,3,FALSE),"") | BH40: =IF(BI40="","",TEXT(BI40,"dd")&"-"&TEXT(BL40,"dd mmm")) | BI40: =IFERROR($M40+VLOOKUP($L40,'Voyage days'!$F$702:$H$727,3,FALSE),"") | BJ40: =IF(BK40="","",TEXT(BK40,"dd")&"-"&TEXT(BL40,"dd mmm")) -> 05-29 Apr | BK40: =IFERROR($M40+VLOOKUP($L40,'Voyage days'!$F$807:$H$878,3,FALSE),"") -> 46147.5 | BL40: =IFERROR($N40+VLOOKUP($L40,'Voyage days'!$F$807:$H$878,3,FALSE),"") -> 46141.5 | BM40: =IFERROR($N40+VLOOKUP($L40,'Voyage days'!$F$807:$K$878,6,FALSE),"") -> 46140 | BN40: =if(L40="loads AG", IFERROR($M40+VLOOKUP($L40,'Voyage days'!$M$38:$O$38,3,FALSE),""),"") | BO40: =if(L40="loads USG", IFERROR($M40+VLOOKUP($L40,'Voyage days'!$L$203:$N$203,3,FALSE),""),"")
A41: Crystal Oasis | B41: 2022 | C41: 84000 | H41: DF | I41: BGN | J41: =IF(W41="","NO AIS",IF((W41-M41-1)>0,"Update","")) | K41: Cape | L41: Cape laden | M41: 46158 | N41: 46159 | P41: Pendung firm disport | R41: BGN 17-18 Mar Nederland | S41: GP | T41: 46125 | U41: =IF(V41="","No AIS",VLOOKUP(V41,'Voyage days'!$A$3:$B$1480,2,FALSE)) -> Port Louis | V41: =IF(VLOOKUP(A41,'1) Kpler'!$E$2:$P$1000,8, FALSE)="","",VLOOKUP(A41,'1) Kpler'!$E$2:$P$1000,8, FALSE)) -> Port Louis | W41: =IF(VLOOKUP(A41,'1) Kpler'!$E$2:$P$1000,9,FALSE)="","",VLOOKUP(A41,'1) Kpler'!$E$2:$P$1000,9,FALSE)) -> 46134.375 | X41: =VLOOKUP(A41,'1) Kpler'!$E$2:$I$1000,4,FALSE) -> loaded | Y41: =AG41 -> 16-17 Jun | Z41: =AJ41 | AA41: =AM41 | AB41: =AP41 | AC41: =AS41 | AD41: =BB41 -> 08-09 Jun | AE41: =AY41 -> 05-06 Jun | AF41: =BJ41 -> 16-17 May | AG41: =IF(AH41="","",TEXT(AH41,"dd")&"-"&TEXT(AI41,"dd mmm")) -> 16-17 Jun | AH41: =IFERROR($M41+VLOOKUP($L41,'Voyage days'!$F$38:$H$89,3,FALSE),"") -> 46189 | AI41: =IFERROR(N41+VLOOKUP($L41,'Voyage days'!$F$38:$H$89,3,FALSE),"") -> 46190 | AJ41: =IF(AK41="","",TEXT(AK41,"dd")&"-"&TEXT(AL41,"dd mmm")) | AK41: =IFERROR($M41+VLOOKUP($L41,'Voyage days'!$F$94:$H$193,3,FALSE),"") | AL41: =IFERROR($N41+VLOOKUP($L41,'Voyage days'!$F$94:$H$193,3,FALSE),"") | AM41: =IF(AN41="","",TEXT(AN41,"dd")&"-"&TEXT(AO41,"dd mmm")) | AN41: =IFERROR($M41+VLOOKUP($L41,'Voyage days'!$F$203:$H$256,3,FALSE),"") | AO41: =IFERROR($N41+VLOOKUP($L41,'Voyage days'!$F$203:$H$256,3,FALSE),"") | AP41: =IF(AQ41="","",TEXT(AQ41,"dd")&"-"&TEXT(AR41,"dd mmm")) | AQ41: =IFERROR($M41+VLOOKUP($L41,'Voyage days'!$F$294:$H$377,3,FALSE),"") | AR41: =IFERROR($N41+VLOOKUP($L41,'Voyage days'!$F$294:$H$377,3,FALSE),"") | AS41: =IF(AT41="","",TEXT(AT41,"dd")&"-"&TEXT(AU41,"dd mmm")) | AT41: =IFERROR($M41+VLOOKUP($L41,'Voyage days'!$F$382:$H$446,3,FALSE),"") | AU41: =IFERROR($N41+VLOOKUP($L41,'Voyage days'!$F$382:$H$446,3,FALSE),"") | AV41: =IF(AW41="","",TEXT(AW41,"dd")&"-"&TEXT(AX41,"dd mmm")) -> 31-01 Jun | AW41: =IFERROR($M41+VLOOKUP($L41,'Voyage days'!$F$483:$H$538,3,FALSE),"") -> 46173 | AX41: =IFERROR($N41+VLOOKUP($L41,'Voyage days'!$F$483:$H$538,3,FALSE),"") -> 46174 | AY41: =IF(AZ41="","",TEXT(AZ41,"dd")&"-"&TEXT(BA41,"dd mmm")) -> 05-06 Jun | AZ41: =IFERROR($M41+VLOOKUP($L41,'Voyage days'!$F$540:$H$613,3,FALSE),"") -> 46178 | BA41: =IFERROR($N41+VLOOKUP($L41,'Voyage days'!$F$540:$H$613,3,FALSE),"") -> 46179 | BB41: =IF(BC41="","",TEXT(BC41,"dd")&"-"&TEXT(BD41,"dd mmm")) -> 08-09 Jun | BC41: =IFERROR($M41+VLOOKUP($L41,'Voyage days'!$F$448:$H$479,3,FALSE),"") -> 46181 | BD41: =IFERROR($N41+VLOOKUP($L41,'Voyage days'!$F$448:$H$479,3,FALSE),"") -> 46182 | BE41: =IF(BF41="","",TEXT(BF41,"dd")&"-"&TEXT(BG41,"dd mmm")) | BF41: =IFERROR($M41+VLOOKUP($L41,'Voyage days'!$F$620:$H$646,3,FALSE),"") | BG41: =IFERROR($N41+VLOOKUP($L41,'Voyage days'!$F$620:$H$646,3,FALSE),"") | BH41: =IF(BI41="","",TEXT(BI41,"dd")&"-"&TEXT(BL41,"dd mmm")) -> 05-17 May | BI41: =IFERROR($M41+VLOOKUP($L41,'Voyage days'!$F$702:$H$727,3,FALSE),"") -> 46178 | BJ41: =IF(BK41="","",TEXT(BK41,"dd")&"-"&TEXT(BL41,"dd mmm")) -> 16-17 May | BK41: =IFERROR($M41+VLOOKUP($L41,'Voyage days'!$F$807:$H$878,3,FALSE),"") -> 46158 | BL41: =IFERROR($N41+VLOOKUP($L41,'Voyage days'!$F$807:$H$878,3,FALSE),"") -> 46159 | BM41: =IFERROR($N41+VLOOKUP($L41,'Voyage days'!$F$807:$K$878,6,FALSE),"") -> 46159 | BN41: =if(L41="loads AG", IFERROR($M41+VLOOKUP($L41,'Voyage days'!$M$38:$O$38,3,FALSE),""),"") | BO41: =if(L41="loads USG", IFERROR($M41+VLOOKUP($L41,'Voyage days'!$L$203:$N$203,3,FALSE),""),"")
A42: Crystal Odyssey | B42: 2025 | C42: 86700 | I42: BGN | L42: Eu | M42: 46129 | N42: 46132 | P42: ETA Horizon Tangier 13 Apr | R42: BGN 23-24 Mar Nederland | S42: GP | T42: 46125 | U42: =IF(V42="","No AIS",VLOOKUP(V42,'Voyage days'!$A$3:$B$1480,2,FALSE)) -> Gibraltar | V42: =IF(VLOOKUP(A42,'1) Kpler'!$E$2:$P$1000,8, FALSE)="","",VLOOKUP(A42,'1) Kpler'!$E$2:$P$1000,8, FALSE)) -> Jorf Lasfar | W42: =IF(VLOOKUP(A42,'1) Kpler'!$E$2:$P$1000,9,FALSE)="","",VLOOKUP(A42,'1) Kpler'!$E$2:$P$1000,9,FALSE)) -> 46132.5 | X42: =VLOOKUP(A42,'1) Kpler'!$E$2:$I$1000,4,FALSE) -> loaded | Y42: =AG42 | Z42: =AJ42 -> 01-04 May | AA42: =AM42 -> 02-05 May | AB42: =AP42 -> 28-01 May | AC42: =AS42 -> 19-22 Apr | AD42: =BB42 | AE42: =AY42 | AF42: =BJ42 -> 01-04 May | AG42: =IF(AH42="","",TEXT(AH42,"dd")&"-"&TEXT(AI42,"dd mmm")) | AH42: =IFERROR($M42+VLOOKUP($L42,'Voyage days'!$F$38:$H$89,3,FALSE),"") | AI42: =IFERROR(N42+VLOOKUP($L42,'Voyage days'!$F$38:$H$89,3,FALSE),"") | AJ42: =IF(AK42="","",TEXT(AK42,"dd")&"-"&TEXT(AL42,"dd mmm")) -> 01-04 May | AK42: =IFERROR($M42+VLOOKUP($L42,'Voyage days'!$F$94:$H$193,3,FALSE),"") -> 46143 | AL42: =IFERROR($N42+VLOOKUP($L42,'Voyage days'!$F$94:$H$193,3,FALSE),"") -> 46146 | AM42: =IF(AN42="","",TEXT(AN42,"dd")&"-"&TEXT(AO42,"dd mmm")) -> 02-05 May | AN42: =IFERROR($M42+VLOOKUP($L42,'Voyage days'!$F$203:$H$256,3,FALSE),"") -> 46144 | AO42: =IFERROR($N42+VLOOKUP($L42,'Voyage days'!$F$203:$H$256,3,FALSE),"") -> 46147 | AP42: =IF(AQ42="","",TEXT(AQ42,"dd")&"-"&TEXT(AR42,"dd mmm")) -> 28-01 May | AQ42: =IFERROR($M42+VLOOKUP($L42,'Voyage days'!$F$294:$H$377,3,FALSE),"") -> 46140 | AR42: =IFERROR($N42+VLOOKUP($L42,'Voyage days'!$F$294:$H$377,3,FALSE),"") -> 46143 | AS42: =IF(AT42="","",TEXT(AT42,"dd")&"-"&TEXT(AU42,"dd mmm")) -> 19-22 Apr | AT42: =IFERROR($M42+VLOOKUP($L42,'Voyage days'!$F$382:$H$446,3,FALSE),"") -> 46131 | AU42: =IFERROR($N42+VLOOKUP($L42,'Voyage days'!$F$382:$H$446,3,FALSE),"") -> 46134 | AV42: =IF(AW42="","",TEXT(AW42,"dd")&"-"&TEXT(AX42,"dd mmm")) | AW42: =IFERROR($M42+VLOOKUP($L42,'Voyage days'!$F$483:$H$538,3,FALSE),"") | AX42: =IFERROR($N42+VLOOKUP($L42,'Voyage days'!$F$483:$H$538,3,FALSE),"") | AY42: =IF(AZ42="","",TEXT(AZ42,"dd")&"-"&TEXT(BA42,"dd mmm")) | AZ42: =IFERROR($M42+VLOOKUP($L42,'Voyage days'!$F$540:$H$613,3,FALSE),"") | BA42: =IFERROR($N42+VLOOKUP($L42,'Voyage days'!$F$540:$H$613,3,FALSE),"") | BB42: =IF(BC42="","",TEXT(BC42,"dd")&"-"&TEXT(BD42,"dd mmm")) | BC42: =IFERROR($M42+VLOOKUP($L42,'Voyage days'!$F$448:$H$479,3,FALSE),"") | BD42: =IFERROR($N42+VLOOKUP($L42,'Voyage days'!$F$448:$H$479,3,FALSE),"") | BE42: =IF(BF42="","",TEXT(BF42,"dd")&"-"&TEXT(BG42,"dd mmm")) | BF42: =IFERROR($M42+VLOOKUP($L42,'Voyage days'!$F$620:$H$646,3,FALSE),"") | BG42: =IFERROR($N42+VLOOKUP($L42,'Voyage days'!$F$620:$H$646,3,FALSE),"") | BH42: =IF(BI42="","",TEXT(BI42,"dd")&"-"&TEXT(BL42,"dd mmm")) | BI42: =IFERROR($M42+VLOOKUP($L42,'Voyage days'!$F$702:$H$727,3,FALSE),"") | BJ42: =IF(BK42="","",TEXT(BK42,"dd")&"-"&TEXT(BL42,"dd mmm")) -> 01-04 May | BK42: =IFERROR($M42+VLOOKUP($L42,'Voyage days'!$F$807:$H$878,3,FALSE),"") -> 46143 | BL42: =IFERROR($N42+VLOOKUP($L42,'Voyage days'!$F$807:$H$878,3,FALSE),"") -> 46146 | BM42: =IFERROR($N42+VLOOKUP($L42,'Voyage days'!$F$807:$K$878,6,FALSE),"") -> 46132 | BN42: =if(L42="loads AG", IFERROR($M42+VLOOKUP($L42,'Voyage days'!$M$38:$O$38,3,FALSE),""),"") | BO42: =if(L42="loads USG", IFERROR($M42+VLOOKUP($L42,'Voyage days'!$L$203:$N$203,3,FALSE),""),"")
A43: Future Ace | B43: 43570 | C43: 83000 | H43: S | I43: BGN | J43: =IF(W43="","NO AIS",IF((W43-M43-1)>0,"Update","")) -> NO AIS | L43: Far East | M43: 46151 | N43: 46152 | P43: Ex Nederland 06 Apr | R43: BGN 21-22 Mar Nederland | S43: GP | T43: 46125 | U43: =IF(V43="","No AIS",VLOOKUP(V43,'Voyage days'!$A$3:$B$1480,2,FALSE)) -> No AIS | V43: =IF(VLOOKUP(A43,'1) Kpler'!$E$2:$P$1000,8, FALSE)="","",VLOOKUP(A43,'1) Kpler'!$E$2:$P$1000,8, FALSE)) | W43: =IF(VLOOKUP(A43,'1) Kpler'!$E$2:$P$1000,9,FALSE)="","",VLOOKUP(A43,'1) Kpler'!$E$2:$P$1000,9,FALSE)) | X43: =VLOOKUP(A43,'1) Kpler'!$E$2:$I$1000,4,FALSE) -> loaded | Y43: =AG43 -> 27-28 May | Z43: =AJ43 -> 09-10 Jun | AA43: =AM43 -> 16-17 Jun | AB43: =AP43 -> 08-09 Jun | AC43: =AS43 -> 14-15 Jun | AD43: =BB43 -> 17-18 May | AE43: =AY43 -> 17-18 May | AF43: =BJ43 -> 24-25 Jun | AG43: =IF(AH43="","",TEXT(AH43,"dd")&"-"&TEXT(AI43,"dd mmm")) -> 27-28 May | AH43: =IFERROR($M43+VLOOKUP($L43,'Voyage days'!$F$38:$H$89,3,FALSE),"") -> 46169 | AI43: =IFERROR(N43+VLOOKUP($L43,'Voyage days'!$F$38:$H$89,3,FALSE),"") -> 46170 | AJ43: =IF(AK43="","",TEXT(AK43,"dd")&"-"&TEXT(AL43,"dd mmm")) -> 09-10 Jun | AK43: =IFERROR($M43+VLOOKUP($L43,'Voyage days'!$F$94:$H$193,3,FALSE),"") -> 46182 | AL43: =IFERROR($N43+VLOOKUP($L43,'Voyage days'!$F$94:$H$193,3,FALSE),"") -> 46183 | AM43: =IF(AN43="","",TEXT(AN43,"dd")&"-"&TEXT(AO43,"dd mmm")) -> 16-17 Jun | AN43: =IFERROR($M43+VLOOKUP($L43,'Voyage days'!$F$203:$H$256,3,FALSE),"") -> 46189 | AO43: =IFERROR($N43+VLOOKUP($L43,'Voyage days'!$F$203:$H$256,3,FALSE),"") -> 46190 | AP43: =IF(AQ43="","",TEXT(AQ43,"dd")&"-"&TEXT(AR43,"dd mmm")) -> 08-09 Jun | AQ43: =IFERROR($M43+VLOOKUP($L43,'Voyage days'!$F$294:$H$377,3,FALSE),"") -> 46181 | AR43: =IFERROR($N43+VLOOKUP($L43,'Voyage days'!$F$294:$H$377,3,FALSE),"") -> 46182 | AS43: =IF(AT43="","",TEXT(AT43,"dd")&"-"&TEXT(AU43,"dd mmm")) -> 14-15 Jun | AT43: =IFERROR($M43+VLOOKUP($L43,'Voyage days'!$F$382:$H$446,3,FALSE),"") -> 46187 | AU43: =IFERROR($N43+VLOOKUP($L43,'Voyage days'!$F$382:$H$446,3,FALSE),"") -> 46188 | AV43: =IF(AW43="","",TEXT(AW43,"dd")&"-"&TEXT(AX43,"dd mmm")) -> 22-23 May | AW43: =IFERROR($M43+VLOOKUP($L43,'Voyage days'!$F$483:$H$538,3,FALSE),"") -> 46164 | AX43: =IFERROR($N43+VLOOKUP($L43,'Voyage days'!$F$483:$H$538,3,FALSE),"") -> 46165 | AY43: =IF(AZ43="","",TEXT(AZ43,"dd")&"-"&TEXT(BA43,"dd mmm")) -> 17-18 May | AZ43: =IFERROR($M43+VLOOKUP($L43,'Voyage days'!$F$540:$H$613,3,FALSE),"") -> 46159.25 | BA43: =IFERROR($N43+VLOOKUP($L43,'Voyage days'!$F$540:$H$613,3,FALSE),"") -> 46160.25 | BB43: =IF(BC43="","",TEXT(BC43,"dd")&"-"&TEXT(BD43,"dd mmm")) -> 17-18 May | BC43: =IFERROR($M43+VLOOKUP($L43,'Voyage days'!$F$448:$H$479,3,FALSE),"") -> 46159 | BD43: =IFERROR($N43+VLOOKUP($L43,'Voyage days'!$F$448:$H$479,3,FALSE),"") -> 46160 | BE43: =IF(BF43="","",TEXT(BF43,"dd")&"-"&TEXT(BG43,"dd mmm")) -> 20-21 May | BF43: =IFERROR($M43+VLOOKUP($L43,'Voyage days'!$F$620:$H$646,3,FALSE),"") -> 46162 | BG43: =IFERROR($N43+VLOOKUP($L43,'Voyage days'!$F$620:$H$646,3,FALSE),"") -> 46163 | BH43: =IF(BI43="","",TEXT(BI43,"dd")&"-"&TEXT(BL43,"dd mmm")) -> 17-25 Jun | BI43: =IFERROR($M43+VLOOKUP($L43,'Voyage days'!$F$702:$H$727,3,FALSE),"") -> 46159.25 | BJ43: =IF(BK43="","",TEXT(BK43,"dd")&"-"&TEXT(BL43,"dd mmm")) -> 24-25 Jun | BK43: =IFERROR($M43+VLOOKUP($L43,'Voyage days'!$F$807:$H$878,3,FALSE),"") -> 46197 | BL43: =IFERROR($N43+VLOOKUP($L43,'Voyage days'!$F$807:$H$878,3,FALSE),"") -> 46198 | BM43: =IFERROR($N43+VLOOKUP($L43,'Voyage days'!$F$807:$K$878,6,FALSE),"") -> 46172 | BN43: =if(L43="loads AG", IFERROR($M43+VLOOKUP($L43,'Voyage days'!$M$38:$O$38,3,FALSE),""),"") | BO43: =if(L43="loads USG", IFERROR($M43+VLOOKUP($L43,'Voyage days'!$L$203:$N$203,3,FALSE),""),"")
A44: Gas Ares | B44: 2021 | C44: 84000 | H44: S | I44: BGN | J44: =IF(W44="","NO AIS",IF((W44-M44-1)>0,"Update","")) -> Update | L44: loads USG | M44: 46132 | N44: 46133 | P44: ETA Balboa 14 Apr | R44: BGN 20-21 Apr USG | S44: GP | T44: 46125 | U44: =IF(V44="","No AIS",VLOOKUP(V44,'Voyage days'!$A$3:$B$1480,2,FALSE)) -> USG | V44: =IF(VLOOKUP(A44,'1) Kpler'!$E$2:$P$1000,8, FALSE)="","",VLOOKUP(A44,'1) Kpler'!$E$2:$P$1000,8, FALSE)) -> Energy Transfer Nederland | W44: =IF(VLOOKUP(A44,'1) Kpler'!$E$2:$P$1000,9,FALSE)="","",VLOOKUP(A44,'1) Kpler'!$E$2:$P$1000,9,FALSE)) -> 46133.792 | X44: =VLOOKUP(A44,'1) Kpler'!$E$2:$I$1000,4,FALSE) -> ballast | Y44: =AG44 | Z44: =AJ44 -> 20-21 Apr | AA44: =AM44 -> 20-21 Apr | AB44: =AP44 | AC44: =AS44 -> 10-11 May | AD44: =BB44 | AE44: =AY44 | AF44: =BJ44 | AG44: =IF(AH44="","",TEXT(AH44,"dd")&"-"&TEXT(AI44,"dd mmm")) | AH44: =IFERROR($M44+VLOOKUP($L44,'Voyage days'!$F$38:$H$89,3,FALSE),"") | AI44: =IFERROR(N44+VLOOKUP($L44,'Voyage days'!$F$38:$H$89,3,FALSE),"") | AJ44: =IF(AK44="","",TEXT(AK44,"dd")&"-"&TEXT(AL44,"dd mmm")) -> 20-21 Apr | AK44: =IFERROR($M44+VLOOKUP($L44,'Voyage days'!$F$94:$H$193,3,FALSE),"") -> 46132 | AL44: =IFERROR($N44+VLOOKUP($L44,'Voyage days'!$F$94:$H$193,3,FALSE),"") -> 46133 | AM44: =IF(AN44="","",TEXT(AN44,"dd")&"-"&TEXT(AO44,"dd mmm")) -> 20-21 Apr | AN44: =IFERROR($M44+VLOOKUP($L44,'Voyage days'!$F$203:$H$256,3,FALSE),"") -> 46132 | AO44: =IFERROR($N44+VLOOKUP($L44,'Voyage days'!$F$203:$H$256,3,FALSE),"") -> 46133 | AP44: =IF(AQ44="","",TEXT(AQ44,"dd")&"-"&TEXT(AR44,"dd mmm")) | AQ44: =IFERROR($M44+VLOOKUP($L44,'Voyage days'!$F$294:$H$377,3,FALSE),"") | AR44: =IFERROR($N44+VLOOKUP($L44,'Voyage days'!$F$294:$H$377,3,FALSE),"") | AS44: =IF(AT44="","",TEXT(AT44,"dd")&"-"&TEXT(AU44,"dd mmm")) -> 10-11 May | AT44: =IFERROR($M44+VLOOKUP($L44,'Voyage days'!$F$382:$H$446,3,FALSE),"") -> 46152 | AU44: =IFERROR($N44+VLOOKUP($L44,'Voyage days'!$F$382:$H$446,3,FALSE),"") -> 46153 | AV44: =IF(AW44="","",TEXT(AW44,"dd")&"-"&TEXT(AX44,"dd mmm")) | AW44: =IFERROR($M44+VLOOKUP($L44,'Voyage days'!$F$483:$H$538,3,FALSE),"") | AX44: =IFERROR($N44+VLOOKUP($L44,'Voyage days'!$F$483:$H$538,3,FALSE),"") | AY44: =IF(AZ44="","",TEXT(AZ44,"dd")&"-"&TEXT(BA44,"dd mmm")) | AZ44: =IFERROR($M44+VLOOKUP($L44,'Voyage days'!$F$540:$H$613,3,FALSE),"") | BA44: =IFERROR($N44+VLOOKUP($L44,'Voyage days'!$F$540:$H$613,3,FALSE),"") | BB44: =IF(BC44="","",TEXT(BC44,"dd")&"-"&TEXT(BD44,"dd mmm")) | BC44: =IFERROR($M44+VLOOKUP($L44,'Voyage days'!$F$448:$H$479,3,FALSE),"") | BD44: =IFERROR($N44+VLOOKUP($L44,'Voyage days'!$F$448:$H$479,3,FALSE),"") | BE44: =IF(BF44="","",TEXT(BF44,"dd")&"-"&TEXT(BG44,"dd mmm")) | BF44: =IFERROR($M44+VLOOKUP($L44,'Voyage days'!$F$620:$H$646,3,FALSE),"") | BG44: =IFERROR($N44+VLOOKUP($L44,'Voyage days'!$F$620:$H$646,3,FALSE),"") | BH44: =IF(BI44="","",TEXT(BI44,"dd")&"-"&TEXT(BL44,"dd mmm")) | BI44: =IFERROR($M44+VLOOKUP($L44,'Voyage days'!$F$702:$H$727,3,FALSE),"") | BJ44: =IF(BK44="","",TEXT(BK44,"dd")&"-"&TEXT(BL44,"dd mmm")) | BK44: =IFERROR($M44+VLOOKUP($L44,'Voyage days'!$F$807:$H$878,3,FALSE),"") | BL44: =IFERROR($N44+VLOOKUP($L44,'Voyage days'!$F$807:$H$878,3,FALSE),"") | BM44: =IFERROR($N44+VLOOKUP($L44,'Voyage days'!$F$807:$K$878,6,FALSE),"") | BN44: =if(L44="loads AG", IFERROR($M44+VLOOKUP($L44,'Voyage days'!$M$38:$O$38,3,FALSE),""),"") | BO44: =if(L44="loads USG", IFERROR($M44+VLOOKUP($L44,'Voyage days'!$L$203:$N$203,3,FALSE),""),"") -> 46164
